Workbook

Sheet Read me
A1: Big Brother data: proofreading sheet
A2: Generated 2026-10-25T17:24:33+00:00 from the Wikipedia and Big Brother Wiki pages cached in this repo. Adapted from Wikipedia (CC BY-SA 4.0) and the Big Brother Wiki (CC BY-SA 3.0); this workbook is licensed CC BY-SA 4.0 (https://creativecommons.org/licenses/by-sa/4.0/).
A4: How to proofread
A5: Only the yellow columns are for you: set “Looks right?” to OK, Wrong or Unsure, and write what should change in “Correction”.
A6: Example: on Weeks, BB26 · Week 4, you might set Wrong and write “Veto use should say Tucker used it on himself”.
A7: Every row has a Source link to the exact revision the data came from: Wikipedia, or the Big Brother Wiki (bigbrother.fandom.com) on the BB Wiki tabs.
A8: Filters are on every header row; shaded Weeks rows are weeks that aren’t plain evictions.
A10: Tabs
A11: Weeks (114 rows): one row per eviction round — HOH, noms, veto, twist rows, final noms, evicted, tally, plus the HOH/veto competition names and what the veto did.
A12: Votes (1112 rows): every houseguest’s vote in every round, or why they didn’t vote. “With the house” is a formula.
A13: Players (131 rows): totals are COUNTIFS formulas over Weeks and Votes, so fixing a week there updates them.
A14: Competitions (150 rows): competition names found in the episode summaries, with the sentence each came from.
... A25: Player totals: count only the rounds the grid models (twist rounds shown as notes are left out).

Sheet Weeks
A1: Season | B1: Week | C1: Round | D1: Status | E1: Note | F1: HOH | G1: HOH comp | H1: Noms | I1: Veto | J1: Veto comp | K1: Veto use | L1: Twist rows | M1: Final noms | N1: Evicted | O1: Tally | P1: Source | Q1: Looks right? | R1: Correction | S1: hoh_key | T1: veto_key | U1: noms_key | V1: final_key | W1: twist_key
A2: BB28 | B2: Week 1 | D2: ok | F2: Dee | G2: 175 Million BC | H2: Mallory, Taylor, Yash | I2: Mallory | J2: Back From the Future | K2: Used on Mallory (themselves); replacement: Ashley; Yash saved by a twist | L2: Block Buster winner: Yash | M2: Ashley, Taylor | N2: Ashley | O2: 14 of 14 votes to evict | P2: Wikipedia | S2: ;Dee; | T2: ;Mallory; | U2: ;Mallory;Taylor;Yash; | V2: ;Ashley;Taylor; | W2: ;Yash;
A3: BB28 | B3: Week 2 | D3: ok | F3: Devens | G3: Achy Breaky HOH | H3: Jason, Lyric, Melody | I3: Devens | J3: Flower Power | K3: Used on Lyric; replacement: Rome; Jason saved by a twist | L3: Block Buster winner: Jason | M3: Melody, Rome | N3: Rome | O3: 12 of 13 votes to evict | P3: Wikipedia | S3: ;Devens; | T3: ;Devens; | U3: ;Jason;Lyric;Melody; | V3: ;Melody;Rome; | W3: ;Jason;
A4: BB28 | B4: Week 3 | D4: ok | F4: Kamu | G4: Wrestlegasm 85 | H4: La Trice, Lyric, Mallory | I4: Lyric | J4: The Pickle Ball | K4: Used on Lyric (themselves); replacement: Jason; Mallory saved by a twist | L4: Block Buster winner: Mallory | M4: Jason, La Trice | N4: Jason | O4: 12 of 12 votes to evict | P4: Wikipedia | S4: ;Kamu; | T4: ;Lyric; | U4: ;La Trice;Lyric;Mallory; | V4: ;Jason;La Trice; | W4: ;Mallory;
A5: BB28 | B5: Week 4 | D5: ok | F5: Haley | G5: Jack the Ripper | H5: Drew, Melody, Taylor | I5: Taylor | J5: Murder at the Masquerade | K5: Used on Taylor (themselves); replacement: Lyric; Drew saved by a twist | L5: Block Buster winner: Drew | M5: Lyric, Melody | N5: Lyric | O5: 8 of 11 votes to evict | P5: Wikipedia | S5: ;Haley; | T5: ;Taylor; | U5: ;Drew;Melody;Taylor; | V5: ;Lyric;Melody; | W5: ;Drew;
A6: BB28 | B6: Week 5 | D6: ok | F6: La Trice | G6: Sasquatch Watch | H6: Barrett, Chuk, Haley | I6: Kamu | J6: Saturday Night Veto | K6: Not used; Haley saved by a twist | L6: Block Buster winner: Haley | M6: Barrett, Chuk | N6: Chuk | O6: 9 of 10 votes to evict | P6: Wikipedia | S6: ;La Trice; | T6: ;Kamu; | U6: ;Barrett;Chuk;Haley; | V6: ;Barrett;Chuk; | W6: ;Haley;
A7: BB28 | B7: Week 6 | D7: ok | F7: Yash | G7: Bugs in the System | H7: Angela, Dee, Haley | I7: Yash, Devens | J7: OTEV the Belligerent B-Movie Blob | K7: Used on Dee; replacement: Kamu; Angela saved by a twist | L7: Block Buster winner: Angela | M7: Haley, Kamu | N7: Kamu | O7: 8 of 9 votes to evict | P7: Wikipedia | S7: ;Yash; | T7: ;Yash;Devens; | U7: ;Angela;Dee;Haley; | V7: ;Haley;Kamu; | W7: ;Angela;
A8: BB28 | B8: Week 7 | D8: ok | F8: Dee | G8: Norse By Norsewest | H8: Drew, La Trice, Taylor | I8: La Trice | J8: Feel The Burn | K8: Used on La Trice (themselves); replacement: Mallory; Drew saved by a twist | L8: Block Buster winner: Drew | M8: Mallory, Taylor | N8: Mallory | O8: 6 of 8 votes to evict | P8: Wikipedia | S8: ;Dee; | T8: ;La Trice; | U8: ;Drew;La Trice;Taylor; | V8: ;Mallory;Taylor; | W8: ;Drew;
A9: BB28 | B9: Week 8 | C9: Day 53 | D9: note | E9: Two rounds: Day 52 / Day 53; Round 1 (Day 52): Non-standard outcome: Haley Yash's choice to eliminate | F9: Drew | G9: 2026: A Zing Odyssey | H9: La Trice, Taylor, Yash | I9: Yash | J9: The Gold, the Bad, and the Ugly | K9: Used on Yash (themselves) | L9: Block Buster winner: Devens | M9: La Trice, Taylor | N9: La Trice | O9: 4 of 6 votes to evict | P9: Wikipedia | S9: ;Drew; | T9: ;Yash; | U9: ;La Trice;Taylor;Yash; | V9: ;La Trice;Taylor; | W9: ;Devens;
A10: BB28 | B10: Week 9 | D10: ok | F10: Barrett | G10: Rainbow Rollers | H10: Angela, Dee, Devens | I10: Yash | J10: BB Comics | K10: Not used; Devens saved by a twist | L10: Block Buster winner: Devens | M10: Angela, Dee | N10: Angela | O10: 3 of 5 votes to evict | P10: Wikipedia | S10: ;Barrett; | T10: ;Yash; | U10: ;Angela;Dee;Devens; | V10: ;Angela;Dee; | W10: ;Devens;
A11: BB28 | B11: Week 10 | C11: Day 67 | D11: ok | E11: Double eviction | F11: Yash | G11: Wet and Wild West | H11: Barrett, Drew, Melody | I11: Drew | J11: Circle of Trust | K11: Used on Drew (themselves); replacement: Taylor; Melody saved by a twist | L11: Block Buster winner: Melody | M11: Barrett, Taylor | N11: Barrett | O11: 3 of 4 votes to evict | P11: Wikipedia | S11: ;Yash; | T11: ;Drew; | U11: ;Barrett;Drew;Melody; | V11: ;Barrett;Taylor; | W11: ;Melody;
A12: BB28 | B12: Week 10 | C12: Day 73 | D12: ok | E12: Double eviction | F12: Melody | G12: Bleeping Through Time | H12: Dee, Devens | I12: Devens | J12: Great Ball of China | K12: Used on Devens (themselves); replacement: Yash | M12: Dee, Yash | N12: Yash | O12: 2 of 3 votes to evict | P12: Wikipedia | S12: ;Melody; | T12: ;Devens; | U12: ;Dee;Devens; | V12: ;Dee;Yash;
A13: BB28 | B13: Week 11 | C13: Day 74 | D13: ok | E13: Two evictions | F13: Devens | G13: Reverse the Curse | H13: Drew, Melody | I13: Drew | J13: Block Like an Egyptian | K13: Used on Drew (themselves); replacement: Taylor | M13: Melody, Taylor | N13: Melody | O13: 2 of 3 votes to evict | P13: Wikipedia | S13: ;Devens; | T13: ;Drew; | U13: ;Drew;Melody; | V13: ;Melody;Taylor;
A14: BB28 | B14: Week 11 | C14: Day 77 | D14: ok | E14: Two evictions | F14: Taylor | G14: Eternally Yours | H14: Dee, Drew | I14: Drew | J14: Time Travel Toilet | K14: Used on Drew (themselves); replacement: Devens | M14: Dee, Devens | N14: Dee | O14: Drew's choice to evict | P14: Wikipedia | S14: ;Taylor; | T14: ;Drew; | U14: ;Dee;Drew; | V14: ;Dee;Devens;
A15: BB28 | B15: Week 12 | D15: note | E15: Finale; Non-standard outcome: Drew Devens' choice to evict | P15: Wikipedia
A16: BB27 | B16: Week 1 | D16: ok | F16: Vince | G16: Destroy the Lair | H16: Amy, Ashley, Zae | I16: Ashley | J16: Campsite Caper | K16: Used on Ashley (themselves) | L16: Block Buster winner: Kelley | M16: Amy, Zae | N16: Zae | O16: 9 of 14 votes to evict | P16: Wikipedia | S16: ;Vince; | T16: ;Ashley; | U16: ;Amy;Ashley;Zae; | V16: ;Amy;Zae; | W16: ;Kelley;
A17: BB27 | B17: Week 2 | D17: ok | F17: Jimmy | G17: BB Break In | H17: Adrian, Keanu, Kelley | I17: Keanu, Kelley | J17: Caught Creepin | K17: Used on Keanu, Kelley (themselves); replacement: Amy, Will; Adrian saved by a twist | L17: Block Buster winner: Adrian | M17: Amy, Will | N17: Amy | O17: 13 of 13 votes to evict | P17: Wikipedia | S17: ;Jimmy; | T17: ;Keanu;Kelley; | U17: ;Adrian;Keanu;Kelley; | V17: ;Amy;Will; | W17: ;Adrian;
A18: BB27 | B18: Week 3 | D18: ok | F18: Lauren | G18: Twin Witness News | H18: Keanu, Kelley, Will | I18: Keanu | J18: Basement Break In | K18: Used on Keanu (themselves); replacement: Adrian; Kelley saved by a twist | L18: Block Buster winner: Kelley | M18: Adrian, Will | N18: Adrian | O18: 8 of 12 votes to evict | P18: Wikipedia | S18: ;Lauren; | T18: ;Keanu; | U18: ;Keanu;Kelley;Will; | V18: ;Adrian;Will; | W18: ;Kelley;
A19: BB27 | B19: Week 4 | D19: ok | F19: Rylie, Mickey | G19: Killer Carnival | H19: Keanu, Kelley, Rylie | I19: Keanu | J19: Flee the Scene | K19: Used on Keanu (themselves); replacement: Jimmy; Rylie saved by a twist | L19: Block Buster winner: Rylie | M19: Jimmy, Kelley | N19: Jimmy | O19: 9 of 11 votes to evict | P19: Wikipedia | S19: ;Rylie;Mickey; | T19: ;Keanu; | U19: ;Keanu;Kelley;Rylie; | V19: ;Jimmy;Kelley; | W19: ;Rylie;
A20: BB27 | B20: Week 5 | D20: ok | F20: Ava | G20: Jack the Dipper | H20: Keanu, Vince, Zach | I20: Katherine | J20: Elusive Target | K20: Not used; Keanu saved by a twist | L20: Block Buster winner: Keanu | M20: Vince, Zach | N20: Zach | O20: 8 of 10 votes to evict | P20: Wikipedia | S20: ;Ava; | T20: ;Katherine; | U20: ;Keanu;Vince;Zach; | V20: ;Vince;Zach; | W20: ;Keanu;
A21: BB27 | B21: Week 6 | D21: ok | F21: Rachel | G21: The Party Slasher | H21: Mickey, Morgan, Vince | I21: Lauren | J21: OTEV the Hog Father | K21: Used on Vince; replacement: Rylie; Mickey saved by a twist | L21: Block Buster winner: Mickey | M21: Morgan, Rylie | N21: Rylie | O21: 5 of 9 votes to evict | P21: Wikipedia | S21: ;Rachel; | T21: ;Lauren; | U21: ;Mickey;Morgan;Vince; | V21: ;Morgan;Rylie; | W21: ;Mickey;
A22: BB27 | B22: Week 7 | D22: ok | F22: Vince | G22: Mystere Express | H22: Ava, Kelley, Mickey | I22: Mickey | J22: Wine to Die For | K22: Used on Mickey (themselves); replacement: Katherine; Kelley saved by a twist | L22: Block Buster winner: Kelley | M22: Ava, Katherine | N22: Katherine | O22: 7 of 8 votes to evict | P22: Wikipedia | S22: ;Vince; | T22: ;Mickey; | U22: ;Ava;Kelley;Mickey; | V22: ;Ava;Katherine; | W22: ;Kelley;
A23: BB27 | B23: Week 8 | D23: ok | F23: Keanu | G23: Mystere Moments | H23: Mickey, Morgan, Vince | I23: Morgan | J23: Charcuterie Protection Agency | K23: Used on Morgan (themselves); replacement: Ashley; Vince saved by a twist | L23: Block Buster winner: Vince | M23: Ashley, Mickey | N23: Mickey | O23: 6 of 7 votes to evict | P23: Wikipedia | S23: ;Keanu; | T23: ;Morgan; | U23: ;Mickey;Morgan;Vince; | V23: ;Ashley;Mickey; | W23: ;Vince;
A24: BB27 | B24: Week 9 | C24: Day 60 | D24: note | E24: Two rounds: Day 59 / Day 60; Round 1 (Day 59): Non-standard outcome: Rachel Eliminated by competition | F24: Lauren | G24: Mastermind's Maniacal Maze | H24: Ashley, Morgan, Will | I24: Morgan | J24: BB Comics | K24: Used on Morgan (themselves) | L24: Block Buster winner: Keanu | M24: Ashley, Will | N24: Will | O24: 3 of 5 votes to evict | P24: Wikipedia | S24: ;Lauren; | T24: ;Morgan; | U24: ;Ashley;Morgan;Will; | V24: ;Ashley;Will; | W24: ;Keanu;
A25: BB27 | B25: Week 10 | C25: Day 67 | D25: ok | E25: Double eviction | F25: Vince | G25: The Last Zing: The True Story of Zingbot's Demise | H25: Ava, Keanu, Kelley | I25: Morgan | J25: BB CSI | K25: Used on Ava | L25: Block Buster winner: Lauren | M25: Keanu, Kelley | N25: Kelley | O25: 3 of 5 votes to evict | P25: Wikipedia | S25: ;Vince; | T25: ;Morgan; | U25: ;Ava;Keanu;Kelley; | V25: ;Keanu;Kelley; | W25: ;Lauren;
A26: BB27 | B26: Week 10 | C26: Day 73 | D26: ok | E26: Double eviction | F26: Morgan | G26: Wretched Reactor | H26: Keanu, Lauren | I26: Keanu | J26: Masterfind | K26: Used on Keanu (themselves); replacement: Ava | M26: Ava, Lauren | N26: Lauren | O26: 2 of 3 votes to evict | P26: Wikipedia | S26: ;Morgan; | T26: ;Keanu; | U26: ;Keanu;Lauren; | V26: ;Ava;Lauren;
A27: BB27 | B27: Week 11 | C27: Day 74 | D27: ok | E27: Two evictions | F27: Vince | G27: Torturous Trial | H27: Ava, Keanu | I27: Morgan | J27: Masterpieces | K27: Not used | M27: Ava, Keanu | N27: Keanu | O27: 2 of 2 votes to evict | P27: Wikipedia | S27: ;Vince; | T27: ;Morgan; | U27: ;Ava;Keanu; | V27: ;Ava;Keanu;
A28: BB27 | B28: Week 11 | C28: Day 77 | D28: ok | E28: Two evictions | F28: Morgan | G28: ForensiScope | H28: Ashley, Ava | I28: Morgan | J28: Organized Crime | K28: Not used | M28: Ashley, Ava | N28: Ava | O28: Vince's choice to evict | P28: Wikipedia | S28: ;Morgan; | T28: ;Morgan; | U28: ;Ashley;Ava; | V28: ;Ashley;Ava;
A29: BB27 | B29: Week 12 | C29: Day 83 | D29: note | E29: Finale | F29: Ashley | G29: Unmask the Mastermind | M29: Morgan, Vince | N29: Morgan | O29: Ashley's choice to evict | P29: Wikipedia | S29: ;Ashley; | V29: ;Morgan;Vince;
A30: BB26 | B30: Week 1 | D30: ok | F30: Angela | G30: New Rule | H30: Kenney, Kimo, Lisa | I30: Lisa | J30: BB AI Spelling Bee | K30: Used on Lisa (themselves); replacement: Matt; Kimo saved by a twist | L30: AI Arena winner: Kimo | M30: Kenney, Matt | N30: Matt | O30: 8 of 11 votes to evict | P30: Wikipedia | S30: ;Angela; | T30: ;Lisa; | U30: ;Kenney;Kimo;Lisa; | V30: ;Kenney;Matt; | W30: ;Kimo;
A31: BB26 | B31: Week 2 | D31: ok | F31: Chelsie | G31: Animal Obsession | H31: Angela, Kenney, Lisa | I31: Kenney | J31: Code Tower | K31: Used on Kenney (themselves) | L31: AI Arena winner: Tucker | M31: Angela, Lisa | N31: Lisa | O31: 11 of 12 votes to evict | P31: Wikipedia | S31: ;Chelsie; | T31: ;Kenney; | U31: ;Angela;Kenney;Lisa; | V31: ;Angela;Lisa; | W31: ;Tucker;
A32: BB26 | B32: Week 3 | D32: ok | F32: Cedric | G32: Ainsley Land | H32: Angela, Kenney, Tucker | I32: Tucker, Makensy | J32: Recharge My Core | K32: Used on Angela; replacement: Quinn; Tucker saved by a twist | L32: AI Arena winner: Tucker | M32: Kenney, Quinn | N32: Kenney | O32: 10 of 11 votes to evict | P32: Wikipedia | S32: ;Cedric; | T32: ;Tucker;Makensy; | U32: ;Angela;Kenney;Tucker; | V32: ;Kenney;Quinn; | W32: ;Tucker;
A33: BB26 | B33: Week 4 | D33: ok | F33: Angela, Quinn | G33: Bad AI | H33: Cedric, Makensy, Tucker | I33: Tucker | J33: Binary Bridge | K33: Used on Tucker (themselves); replacement: Rubina; Makensy saved by a twist | L33: AI Arena winner: Makensy | M33: Cedric, Rubina | N33: Cedric | O33: 6 of 9 votes to evict | P33: Wikipedia | S33: ;Angela;Quinn; | T33: ;Tucker; | U33: ;Cedric;Makensy;Tucker; | V33: ;Cedric;Rubina; | W33: ;Makensy;
A34: BB26 | B34: Week 5 | D34: ok | F34: Tucker | G34: Firewall | H34: Brooklyn, Cam, Quinn | I34: Tucker | J34: Hide-N-Go Veto | K34: Used on Quinn | L34: AI Arena winner: Chelsie | M34: Brooklyn, Cam | N34: Brooklyn | O34: 8 of 9 votes to evict | P34: Wikipedia | S34: ;Tucker; | T34: ;Tucker; | U34: ;Brooklyn;Cam;Quinn; | V34: ;Brooklyn;Cam; | W34: ;Chelsie;
A35: BB26 | B35: Week 6 | D35: ok | F35: T'kor | G35: Sound Bites | H35: Cam, Makensy, Tucker | I35: Cam | J35: A.I. Apocalypse | K35: Used on Cam (themselves); replacement: Angela; Makensy saved by a twist | L35: AI Arena winner: Makensy | M35: Angela, Tucker | N35: Tucker | O35: 5 of 8 votes to evict | P35: Wikipedia | S35: ;T'kor; | T35: ;Cam; | U35: ;Cam;Makensy;Tucker; | V35: ;Angela;Tucker; | W35: ;Makensy;
A36: BB26 | B36: Week 7 | D36: ok | F36: Quinn | G36: What Came First? | H36: Angela, Kimo, Rubina | I36: Leah | J36: Bot Builders | K36: Used on Angela; replacement: Joseph; Rubina saved by a twist | L36: AI Arena winner: Rubina | M36: Joseph, Kimo | N36: Joseph | O36: 4 of 7 votes to evict | P36: Wikipedia | S36: ;Quinn; | T36: ;Leah; | U36: ;Angela;Kimo;Rubina; | V36: ;Joseph;Kimo; | W36: ;Rubina;
A37: BB26 | B37: Week 8 | D37: ok | F37: Chelsie | G37: Ding Cam | H37: Angela, Kimo | I37: Makensy | J37: OTEV the Trash-Talking Trash Panda | K37: Used on Angela; replacement: Quinn | M37: Kimo, Quinn | N37: Quinn | O37: 4 of 6 votes to evict | P37: Wikipedia | S37: ;Chelsie; | T37: ;Makensy; | U37: ;Angela;Kimo; | V37: ;Kimo;Quinn;
A38: BB26 | B38: Week 9 | D38: ok | F38: Leah | G38: Getting Toasted | H38: Kimo, Rubina | I38: Angela, Leah | J38: Too Much of a Good Thing | K38: Used on Kimo; replacement: T'kor | M38: Rubina, T'kor | N38: T'kor | O38: 4 of 5 votes to evict | P38: Wikipedia | S38: ;Leah; | T38: ;Angela;Leah; | U38: ;Kimo;Rubina; | V38: ;Rubina;T'kor;
A39: BB26 | B39: Week 10 | C39: Day 67 | D39: ok | E39: Double eviction | F39: Makensy | G39: Eye Candy | H39: Angela, Kimo | I39: Makensy | J39: The Wild Robot | K39: Used on Kimo; replacement: Leah | M39: Angela, Leah | N39: Leah | O39: 4 of 4 votes to evict | P39: Wikipedia | S39: ;Makensy; | T39: ;Makensy; | U39: ;Angela;Kimo; | V39: ;Angela;Leah;
A40: BB26 | B40: Week 10 | C40: Day 73 | D40: ok | E40: Double eviction | F40: Chelsie | G40: Warning Messages | H40: Angela, Kimo | I40: Kimo | J40: Eye in the Sky | K40: Used on Kimo (themselves); replacement: Rubina | M40: Angela, Rubina | N40: Angela | O40: 3 of 3 votes to evict | P40: Wikipedia | S40: ;Chelsie; | T40: ;Kimo; | U40: ;Angela;Kimo; | V40: ;Angela;Rubina;
A41: BB26 | B41: Week 11 | D41: ok | F41: Makensy | G41: Killer Keycard | H41: Kimo, Rubina | I41: Makensy | J41: BB Comics | K41: Not used | M41: Kimo, Rubina | N41: Kimo | O41: 2 of 2 votes to evict | P41: Wikipedia | S41: ;Makensy; | T41: ;Makensy; | U41: ;Kimo;Rubina; | V41: ;Kimo;Rubina;
A42: BB26 | B42: Week 12 | D42: ok | F42: Chelsie | G42: Hidden Agenda | H42: Cam, Makensy | I42: Makensy | J42: Passcode Protectors | K42: Used on Makensy (themselves); replacement: Rubina | M42: Cam, Rubina | N42: Rubina | O42: Makensy's choice to evict | P42: Wikipedia | S42: ;Chelsie; | T42: ;Makensy; | U42: ;Cam;Makensy; | V42: ;Cam;Rubina;
A43: BB26 | B43: Week 13 | C43: Day 90 | D43: note | E43: Finale | F43: Makensy | G43: Cerebral Shutdown | M43: Cam, Chelsie | N43: Cam | O43: Makensy's choice to evict | P43: Wikipedia | S43: ;Makensy; | V43: ;Cam;Chelsie;
A44: BB25 | B44: Week 1 | D44: ok | F44: Reilly | G44: Crash Course in Comics | H44: Cory, Felicia, Jared, Kirsten | I44: Hisam | J44: Atomic Wedgie | K44: Used on Cory, Jared | M44: Felicia, Kirsten | N44: Kirsten | O44: 13 of 13 votes to evict | P44: Wikipedia | S44: ;Reilly; | T44: ;Hisam; | U44: ;Cory;Felicia;Jared;Kirsten; | V44: ;Felicia;Kirsten;
A45: BB25 | B45: Week 2 | D45: ok | F45: Hisam | G45: Escape The Nether Region | H45: Cameron, Reilly | I45: Hisam | J45: Twisted Tasks | K45: Not used | M45: Cameron, Reilly | N45: Reilly | O45: 12 of 12 votes to evict | P45: Wikipedia | S45: ;Hisam; | T45: ;Hisam; | U45: ;Cameron;Reilly; | V45: ;Cameron;Reilly;
A46: BB25 | B46: Week 3 | D46: ok | F46: Felicia | G46: Snot-a-Winner | H46: Cameron, Jag | I46: Jag | J46: Cock-a-Doodle Zoom | K46: Used on Jag (themselves); replacement: Hisam | M46: Cameron, Hisam | N46: Hisam | O46: 11 of 11 votes to evict | P46: Wikipedia | S46: ;Felicia; | T46: ;Jag; | U46: ;Cameron;Jag; | V46: ;Cameron;Hisam;
A47: BB25 | B47: Week 4 | D47: ok | F47: Cameron | G47: Revenge of the Pressure Cooker | H47: Blue, Jag | I47: Red | J47: Artifact Stack | K47: Not used | M47: Blue, Jag | N47: Jag | O47: 10 of 10 votes to evict | P47: Wikipedia | S47: ;Cameron; | T47: ;Red; | U47: ;Blue;Jag; | V47: ;Blue;Jag;
A48: BB25 | B48: Week 5 | D48: ok | F48: Jared | G48: BB Odd Couples | H48: Cameron, Red | I48: Cameron | J48: Sludge Stackers | K48: Used on Cameron (themselves); replacement: Jag | M48: Jag, Red | N48: Red | O48: 8 of 10 votes to evict | P48: Wikipedia | S48: ;Jared; | T48: ;Cameron; | U48: ;Cameron;Red; | V48: ;Jag;Red;
A49: BB25 | B49: Week 6 | D49: ok | F49: Cameron | G49: Name That Toot | H49: Felicia, Izzy | I49: Jared | J49: Buddy Ball | K49: Not used | M49: Felicia, Izzy | N49: Izzy | O49: 8 of 9 votes to evict | P49: Wikipedia | S49: ;Cameron; | T49: ;Jared; | U49: ;Felicia;Izzy; | V49: ;Felicia;Izzy;
A50: BB25 | B50: Week 7 | C50: Day 45 | D50: ok | E50: Double eviction | F50: Jared | G50: Attack of the 50 Foot Meatball | H50: America, Cory | I50: Jag | J50: Sweaty Scrimmage | K50: Used on Cory; replacement: Cameron | M50: America, Cameron | N50: Cameron | O50: 8 of 8 votes to evict | P50: Wikipedia | S50: ;Jared; | T50: ;Jag; | U50: ;America;Cory; | V50: ;America;Cameron;
A51: BB25 | B51: Week 7 | C51: Day 51 | D51: ok | E51: Double eviction | F51: Cory | G51: Soul Mates | H51: Blue, Jared | I51: Matt | J51: Monster Kill | K51: Not used | M51: Blue, Jared | N51: Jared | O51: 6 of 7 votes to evict | P51: Wikipedia | S51: ;Cory; | T51: ;Matt; | U51: ;Blue;Jared; | V51: ;Blue;Jared;
A52: BB25 | B52: Week 8 | D52: note | E52: Non-standard outcome: Cameron Won re-entry into game | P52: Wikipedia
A53: BB25 | B53: Week 9 | D53: ok | F53: Cameron | G53: We Come in Pieces | H53: Felicia, Mecole | I53: Cameron | J53: BB Exorcism | K53: Not used | M53: Felicia, Mecole | N53: Mecole | O53: 7 of 7 votes to evict | P53: Wikipedia | S53: ;Cameron; | T53: ;Cameron; | U53: ;Felicia;Mecole; | V53: ;Felicia;Mecole;
A54: BB25 | B54: Week 10 | D54: ok | F54: Bowie Jane | G54: Humili-Gram | H54: Cirie, Felicia | I54: Jag | J54: OTEV the Zinging Robot | K54: Used on Felicia; replacement: Cameron | M54: Cameron, Cirie | N54: Cameron | O54: 6 of 6 votes to evict | P54: Wikipedia | S54: ;Bowie Jane; | T54: ;Jag; | U54: ;Cirie;Felicia; | V54: ;Cameron;Cirie;
A55: BB25 | B55: Week 11 | D55: ok | F55: Jag | G55: BB Comics | H55: Blue, Felicia | I55: Blue, Jag | J55: Superhero Training Academy | K55: Used on Blue, Felicia; replacement: America, Cory | M55: America, Cory | N55: Cory | O55: 5 of 5 votes to evict | P55: Wikipedia | S55: ;Jag; | T55: ;Blue;Jag; | U55: ;Blue;Felicia; | V55: ;America;Cory;
A56: BB25 | B56: Week 12 | C56: Day 80 | D56: ok | E56: Double eviction | F56: Jag | G56: Johnny Mac: Demented Dentist | H56: America, Blue | I56: Jag | J56: Embarrassing Expedition | K56: Not used | M56: America, Blue | N56: Blue | O56: 4 of 4 votes to evict | P56: Wikipedia | S56: ;Jag; | T56: ;Jag; | U56: ;America;Blue; | V56: ;America;Blue;
A57: BB25 | B57: Week 12 | C57: Day 86 | D57: ok | E57: Double eviction | F57: Bowie Jane | G57: Triple Feature | H57: America, Felicia | I57: Matt | J57: Drive-In Drop | K57: Not used | M57: America, Felicia | N57: America | O57: 3 of 3 votes to evict | P57: Wikipedia | S57: ;Bowie Jane; | T57: ;Matt; | U57: ;America;Felicia; | V57: ;America;Felicia;
A58: BB25 | B58: Week 13 | D58: ok | F58: Matt | G58: Superhero Smackdown | H58: Cirie, Felicia | I58: Jag | J58: Swamp Slasher | K58: Not used | M58: Cirie, Felicia | N58: Cirie | O58: 2 of 2 votes to evict | P58: Wikipedia | S58: ;Matt; | T58: ;Jag; | U58: ;Cirie;Felicia; | V58: ;Cirie;Felicia;
A59: BB25 | B59: Week 14 | C59: Day 94 | D59: note | E59: Finale; Two evictions | F59: Bowie Jane | G59: Chenbot Volume #1 | H59: Felicia, Matt | I59: Jag | J59: Scrambled Timeline | K59: Not used | M59: Felicia, Matt | N59: Felicia | O59: Jag's choice to evict | P59: Wikipedia | S59: ;Bowie Jane; | T59: ;Jag; | U59: ;Felicia;Matt; | V59: ;Felicia;Matt;
A60: BB25 | B60: Week 14 | C60: Day 100 | D60: note | E60: Finale; Two evictions | F60: Jag | G60: Multiverse Mix-Up | M60: Bowie Jane, Matt | N60: Bowie Jane | O60: Jag's choice to evict | P60: Wikipedia | S60: ;Jag; | V60: ;Bowie Jane;Matt;
A61: BB24 | B61: Week 1 | D61: note | E61: Non-standard outcome: Eviction cancelled | P61: Wikipedia
A62: BB24 | B62: Week 2 | D62: ok | F62: Jasmine | G62: The BB Pie Fest | H62: Pooch, Taylor | I62: Michael | J62: Mermaid Fest | K62: Not used | M62: Pooch, Taylor | N62: Pooch | O62: 12 of 12 votes to evict | P62: Wikipedia | S62: ;Jasmine; | T62: ;Michael; | U62: ;Pooch;Taylor; | V62: ;Pooch;Taylor;
A63: BB24 | B63: Week 3 | D63: ok | F63: Turner | G63: Get Lit | H63: Brittany, Michael | I63: Brittany, Michael | J63: Woodstack | K63: Used on Brittany, Michael (themselves); replacement: Ameerah, Terrance | M63: Ameerah, Terrance | N63: Ameerah | O63: 7 of 11 votes to evict | P63: Wikipedia | S63: ;Turner; | T63: ;Brittany;Michael; | U63: ;Brittany;Michael; | V63: ;Ameerah;Terrance;
A64: BB24 | B64: Week 4 | D64: ok | F64: Monte | G64: The Invitation | H64: Alyssa, Indy | I64: Daniel, Kyle | J64: Trippy Watch Party | K64: Used on Alyssa, Indy; replacement: Nicole, Taylor | M64: Nicole, Taylor | N64: Nicole | O64: 9 of 10 votes to evict | P64: Wikipedia | S64: ;Monte; | T64: ;Daniel;Kyle; | U64: ;Alyssa;Indy; | V64: ;Nicole;Taylor;
A65: BB24 | B65: Week 5 | D65: ok | F65: Michael | G65: Mind Your Step | H65: Joseph, Monte, Terrance | I65: Brittany, Michael | J65: OTEV the Singing Stageroach | K65: Used on Joseph, Monte, Terrance; replacement: Daniel, Kyle | M65: Daniel, Kyle | N65: Daniel | O65: 8 of 9 votes to evict | P65: Wikipedia | S65: ;Michael; | T65: ;Brittany;Michael; | U65: ;Joseph;Monte;Terrance; | V65: ;Daniel;Kyle;
A66: BB24 | B66: Week 6 | D66: ok | F66: Taylor | G66: Conspiracy Fest | H66: Indy, Terrance | I66: Kyle | J66: Punkaroo | K66: Not used | M66: Indy, Terrance | N66: Indy | O66: 7 of 8 votes to evict | P66: Wikipedia | S66: ;Taylor; | T66: ;Kyle; | U66: ;Indy;Terrance; | V66: ;Indy;Terrance;
A67: BB24 | B67: Week 7 | C67: Inside | D67: ok | E67: Two rounds: Inside / Outside | F67: Michael | G67: Do You See The VIP? | H67: Jasmine, Monte | I67: Brittany | J67: One, Two, Three, VIP | K67: Not used | M67: Jasmine, Monte | N67: Jasmine | O67: 2 of 2 votes to evict | P67: Wikipedia | S67: ;Michael; | T67: ;Brittany; | U67: ;Jasmine;Monte; | V67: ;Jasmine;Monte;
A68: BB24 | B68: Week 7 | C68: Outside | D68: ok | E68: Two rounds: Inside / Outside | F68: Terrance | G68: Do You See The VIP? | H68: Joseph, Turner | I68: Terrance | J68: Lunch is Served | K68: Used on Turner; replacement: Kyle | M68: Joseph, Kyle | N68: Joseph | O68: 2 of 2 votes to evict | P68: Wikipedia | S68: ;Terrance; | T68: ;Terrance; | U68: ;Joseph;Turner; | V68: ;Joseph;Kyle;
A69: BB24 | B69: Week 8 | D69: ok | F69: Turner | G69: Carni-Small | H69: Brittany, Taylor | I69: Michael | J69: Pride Slide | K69: Used on Brittany; replacement: Kyle | M69: Kyle, Taylor | N69: Kyle | O69: 5 of 5 votes to evict | P69: Wikipedia | S69: ;Turner; | T69: ;Michael; | U69: ;Brittany;Taylor; | V69: ;Kyle;Taylor;
A70: BB24 | B70: Week 9 | C70: Day 59 | D70: ok | E70: Double eviction | F70: Michael | G70: Burning Bot | H70: Alyssa, Terrance | I70: Michael | J70: BB Comics | K70: Not used | M70: Alyssa, Terrance | N70: Terrance | O70: 4 of 4 votes to evict | P70: Wikipedia | S70: ;Michael; | T70: ;Michael; | U70: ;Alyssa;Terrance; | V70: ;Alyssa;Terrance;
A71: BB24 | B71: Week 9 | C71: Day 65 | D71: ok | E71: Double eviction | F71: Turner | G71: Laser Focus | H71: Alyssa, Brittany | I71: Monte | J71: Amp It Up | K71: Used on Alyssa; replacement: Michael | M71: Brittany, Michael | N71: Michael | O71: 3 of 3 votes to evict | P71: Wikipedia | S71: ;Turner; | T71: ;Monte; | U71: ;Alyssa;Brittany; | V71: ;Brittany;Michael;
A72: BB24 | B72: Week 10 | D72: ok | F72: Monte | G72: Horror Fest Lockdown | H72: Alyssa, Brittany | I72: Brittany | J72: Snooze Fest | K72: Used on Brittany (themselves); replacement: Taylor | M72: Alyssa, Taylor | N72: Alyssa | O72: 2 of 3 votes to evict | P72: Wikipedia | S72: ;Monte; | T72: ;Brittany; | U72: ;Alyssa;Brittany; | V72: ;Alyssa;Taylor;
A73: BB24 | B73: Week 11 | D73: ok | F73: Taylor | G73: Fashion Fest | H73: Brittany, Turner | I73: Monte | J73: Mathletes | K73: Not used | M73: Brittany, Turner | N73: Brittany | O73: Monte's choice to evict | P73: Wikipedia | S73: ;Taylor; | T73: ;Monte; | U73: ;Brittany;Turner; | V73: ;Brittany;Turner;
A74: BB24 | B74: Week 12 | C74: Day 82 | D74: note | E74: Finale | F74: Monte | G74: Festival Lineup | M74: Taylor, Turner | N74: Turner | O74: Monte's choice to evict | P74: Wikipedia | S74: ;Monte; | V74: ;Taylor;Turner;
A75: BB23 | B75: Week 1 | D75: ok | F75: Frenchie | G75: House of Cards | H75: Alyssa, Kyland | I75: Derek X. | J75: Massive Cocktails | K75: Used on Kyland; replacement: Travis | L75: Wild Card winner: Christian | M75: Alyssa, Travis | N75: Travis | O75: 11 of 13 votes to evict | P75: Wikipedia | S75: ;Frenchie; | T75: ;Derek X.; | U75: ;Alyssa;Kyland; | V75: ;Alyssa;Travis; | W75: ;Christian;
A76: BB23 | B76: Week 2 | D76: ok | F76: Kyland | G76: Pool Sharks | H76: Britini, Frenchie | I76: Derek X. | J76: Fun Tan Lotion | K76: Not used | L76: Wild Card winner: Sarah Beth | M76: Britini, Frenchie | N76: Frenchie | O76: 11 of 12 votes to evict | P76: Wikipedia | S76: ;Kyland; | T76: ;Derek X.; | U76: ;Britini;Frenchie; | V76: ;Britini;Frenchie; | W76: ;Sarah Beth;
A77: BB23 | B77: Week 3 | D77: ok | F77: Xavier | G77: Tom Talks BB | H77: Brent, Britini | I77: Christian | J77: Room Key Rumble | K77: Not used | L77: Wild Card winner: Tiffany | M77: Brent, Britini | N77: Brent | O77: 11 of 11 votes to evict | P77: Wikipedia | S77: ;Xavier; | T77: ;Christian; | U77: ;Brent;Britini; | V77: ;Brent;Britini; | W77: ;Tiffany;
A78: BB23 | B78: Week 4 | D78: ok | F78: Christian | G78: Pier Pressure | H78: Hannah, Whitney | I78: Christian | J78: Bump, Set, Veto | K78: Not used | L78: Wild Card winner: Claire | M78: Hannah, Whitney | N78: Whitney | O78: 10 of 10 votes to evict | P78: Wikipedia | S78: ;Christian; | T78: ;Christian; | U78: ;Hannah;Whitney; | V78: ;Hannah;Whitney; | W78: ;Claire;
A79: BB23 | B79: Week 5 | D79: ok | F79: Derek X. | G79: Whale of a Time | H79: Britini, Sarah Beth | I79: Britini | J79: Kingdom of Curl-A-Lot | K79: Used on Britini (themselves); replacement: Christian | M79: Christian, Sarah Beth | N79: Christian | O79: 7 of 9 votes to evict | P79: Wikipedia | S79: ;Derek X.; | T79: ;Britini; | U79: ;Britini;Sarah Beth; | V79: ;Christian;Sarah Beth;
A80: BB23 | B80: Week 6 | D80: ok | F80: Kyland | G80: Name That Croon | H80: Claire, Derek F. | I80: Alyssa, Kyland | J80: OTEV the Jacked Jellyfish | K80: Used on Claire; replacement: Britini | M80: Britini, Derek F. | N80: Britini | O80: 7 of 8 votes to evict | P80: Wikipedia | S80: ;Kyland; | T80: ;Alyssa;Kyland; | U80: ;Claire;Derek F.; | V80: ;Britini;Derek F.;
A81: BB23 | B81: Week 7 | D81: ok | F81: Sarah Beth | G81: Dash to Dinner | H81: Claire, Derek F., Xavier | I81: Xavier | J81: Domino Effect | K81: Used on Derek F., Xavier; replacement: Derek X. | M81: Claire, Derek X. | N81: Derek X. | O81: 5 of 7 votes to evict | P81: Wikipedia | S81: ;Sarah Beth; | T81: ;Xavier; | U81: ;Claire;Derek F.;Xavier; | V81: ;Claire;Derek X.;
A82: BB23 | B82: Week 8 | D82: ok | F82: Tiffany, Claire | G82: BB NFT's | H82: Kyland, Sarah Beth, Xavier | I82: Hannah | J82: BB High School Hijinks | K82: Used on Xavier | M82: Kyland, Sarah Beth | N82: Sarah Beth | O82: 5 of 6 votes to evict | P82: Wikipedia | S82: ;Tiffany;Claire; | T82: ;Hannah; | U82: ;Kyland;Sarah Beth;Xavier; | V82: ;Kyland;Sarah Beth;
A83: BB23 | B83: Week 9 | C83: Day 59 | D83: ok | E83: Double eviction | F83: Tiffany | G83: The Flying BB-inos | H83: Alyssa, Xavier | I83: Alyssa | J83: Micro-Cocktails | K83: Used on Alyssa (themselves); replacement: Claire | M83: Claire, Xavier | N83: Claire | O83: 4 of 5 votes to evict | P83: Wikipedia | S83: ;Tiffany; | T83: ;Alyssa; | U83: ;Alyssa;Xavier; | V83: ;Claire;Xavier;
A84: BB23 | B84: Week 9 | C84: Day 65 | D84: ok | E84: Double eviction | F84: Hannah | G84: Crash, Boom, Pow | H84: Alyssa, Xavier | I84: Xavier | J84: Logo, Let's Go | K84: Used on Xavier (themselves); replacement: Kyland | M84: Alyssa, Kyland | N84: Alyssa | O84: 3 of 4 votes to evict | P84: Wikipedia | S84: ;Hannah; | T84: ;Xavier; | U84: ;Alyssa;Xavier; | V84: ;Alyssa;Kyland;
A85: BB23 | B85: Week 10 | C85: Day 66 | D85: ok | E85: Double eviction | F85: Kyland | G85: The Cluckster | H85: Hannah, Tiffany | I85: Kyland | J85: BB Comics | K85: Not used | M85: Hannah, Tiffany | N85: Tiffany | O85: 3 of 3 votes to evict | P85: Wikipedia | S85: ;Kyland; | T85: ;Kyland; | U85: ;Hannah;Tiffany; | V85: ;Hannah;Tiffany;
A86: BB23 | B86: Week 10 | C86: Day 71 | D86: ok | E86: Double eviction | F86: Azah | G86: BB Ballers | H86: Hannah, Xavier | I86: Kyland | J86: What The Bleep? | K86: Used on Xavier; replacement: Derek F. | M86: Derek F., Hannah | N86: Hannah | O86: 2 of 2 votes to evict | P86: Wikipedia | S86: ;Azah; | T86: ;Kyland; | U86: ;Hannah;Xavier; | V86: ;Derek F.;Hannah;
A87: BB23 | B87: Week 11 | D87: ok | F87: Xavier | G87: BB: Crime Lab | H87: Azah, Kyland | I87: Xavier | J87: BB Winning Days | K87: Not used | M87: Azah, Kyland | N87: Kyland | O87: Derek F.'s choice to evict | P87: Wikipedia | S87: ;Xavier; | T87: ;Xavier; | U87: ;Azah;Kyland; | V87: ;Azah;Kyland;
A88: BB23 | B88: Week 12 | C88: Day 85 | D88: note | E88: Finale | F88: Xavier | G88: Bouncy Boat Bash | M88: Azah, Derek F. | N88: Azah | O88: Xavier's choice to evict | P88: Wikipedia | S88: ;Xavier; | V88: ;Azah;Derek F.;
A89: BB22 | B89: Week 1 | D89: ok | F89: Cody | G89: Star Steppin' | H89: Keesha, Kevin | I89: Enzo | J89: It's Bananas | K89: Not used | L89: Room winner: Kaysar, (Janelle) | M89: Keesha, Kevin | N89: Keesha | O89: 13 of 13 votes to evict | P89: Wikipedia | S89: ;Cody; | T89: ;Enzo; | U89: ;Keesha;Kevin; | V89: ;Keesha;Kevin; | W89: ;Kaysar;
A90: BB22 | B90: Week 2 | D90: ok | F90: Memphis | G90: Big Brother Watch Party | H90: David, Nicole A. | I90: Memphis | J90: All-Starry Night | K90: Not used | L90: Room winner: Christmas, (Ian) | M90: David, Nicole A. | N90: Nicole A. | O90: 10 of 12 votes to evict | P90: Wikipedia | S90: ;Memphis; | T90: ;Memphis; | U90: ;David;Nicole A.; | V90: ;David;Nicole A.; | W90: ;Christmas;
A91: BB22 | B91: Week 3 | D91: ok | F91: Tyler | G91: Mug Shots | H91: Janelle, Kaysar | I91: Cody | J91: Cupcake Clash | K91: Not used | L91: Room winner: Enzo, (Christmas) | M91: Janelle, Kaysar | N91: Janelle | O91: 9 of 11 votes to evict | P91: Wikipedia | S91: ;Tyler; | T91: ;Cody; | U91: ;Janelle;Kaysar; | V91: ;Janelle;Kaysar; | W91: ;Enzo;
A92: BB22 | B92: Week 4 | D92: ok | F92: Enzo | G92: Carnival Quick Shot | H92: Kaysar, Kevin | I92: Kevin | J92: Face the Puppetmaster | K92: Used on Kevin (themselves); replacement: Christmas | M92: Christmas, Kaysar | N92: Kaysar | O92: 10 of 10 votes to evict | P92: Wikipedia | S92: ;Enzo; | T92: ;Kevin; | U92: ;Kaysar;Kevin; | V92: ;Christmas;Kaysar;
A93: BB22 | B93: Week 5 | D93: ok | F93: Christmas | G93: Filter Face-Off | H93: Bayleigh, Da'Vonne | I93: Christmas | J93: Mathcathalon | K93: Not used | L93: Room winner: Christmas, Dani, David | M93: Bayleigh, Da'Vonne | N93: Bayleigh | O93: 9 of 9 votes to evict | P93: Wikipedia | S93: ;Christmas; | T93: ;Christmas; | U93: ;Bayleigh;Da'Vonne; | V93: ;Bayleigh;Da'Vonne; | W93: ;Christmas;Dani;David;
A94: BB22 | B94: Week 6 | D94: ok | F94: Dani | G94: Power Trip | H94: David, Kevin, Tyler | I94: Da'Vonne | J94: Microbrews | K94: Used on David, Kevin; replacement: Ian | M94: Ian, Tyler | N94: Ian | O94: 5 of 8 votes to evict | P94: Wikipedia | S94: ;Dani; | T94: ;Da'Vonne; | U94: ;David;Kevin;Tyler; | V94: ;Ian;Tyler;
A95: BB22 | B95: Week 7 | D95: ok | F95: Memphis | G95: Hydrant Hustle | H95: Da'Vonne, Kevin | I95: Tyler | J95: Tiger Zing | K95: Not used | M95: Da'Vonne, Kevin | N95: Da'Vonne | O95: 5 of 7 votes to evict | P95: Wikipedia | S95: ;Memphis; | T95: ;Tyler; | U95: ;Da'Vonne;Kevin; | V95: ;Da'Vonne;Kevin;
A96: BB22 | B96: Week 8 | C96: Day 52 | D96: ok | E96: Double eviction | F96: Cody | G96: Going for the Green | H96: David, Kevin | I96: Cody | J96: OTEV the Psychedelic Salamander | K96: Not used | M96: David, Kevin | N96: Kevin | O96: 6 of 6 votes to evict | P96: Wikipedia | S96: ;Cody; | T96: ;Cody; | U96: ;David;Kevin; | V96: ;David;Kevin;
A97: BB22 | B97: Week 8 | C97: Day 58 | D97: ok | E97: Double eviction | F97: Memphis | G97: It's All About Will | H97: David, Nicole F. | I97: Christmas | J97: Ice in Your Veins | K97: Not used | M97: David, Nicole F. | N97: David | O97: 3 of 5 votes to evict | P97: Wikipedia | S97: ;Memphis; | T97: ;Christmas; | U97: ;David;Nicole F.; | V97: ;David;Nicole F.;
A98: BB22 | B98: Week 9 | D98: ok | F98: Cody | G98: Namaste Off the Block | H98: Christmas, Tyler | I98: Cody | J98: Snapshot Shuffle | K98: Not used | M98: Christmas, Tyler | N98: Tyler | O98: 3 of 3 votes to evict | P98: Wikipedia | S98: ;Cody; | T98: ;Cody; | U98: ;Christmas;Tyler; | V98: ;Christmas;Tyler;
A99: BB22 | B99: Week 10 | D99: ok | F99: Nicole F. | G99: Stashing Pumpkins | H99: Christmas, Memphis | I99: Nicole F. | J99: BB Comics | K99: Not used | M99: Christmas, Memphis | N99: Memphis | O99: 2 of 2 votes to evict | P99: Wikipedia | S99: ;Nicole F.; | T99: ;Nicole F.; | U99: ;Christmas;Memphis; | V99: ;Christmas;Memphis;
A100: BB22 | B100: Week 11 | D100: ok | F100: Enzo | G100: Knight Moves | H100: Christmas, Nicole F. | I100: Cody | J100: The Fast and the Furriest | K100: Not used | M100: Christmas, Nicole F. | N100: Christmas | O100: Cody's choice to evict | P100: Wikipedia | S100: ;Enzo; | T100: ;Cody; | U100: ;Christmas;Nicole F.; | V100: ;Christmas;Nicole F.;
...

Sheet Votes
A1: Season | B1: Week | C1: Round | D1: Voter | E1: Voted to evict | F1: Didn't vote because | G1: Evicted | H1: With the house | I1: Source | J1: Looks right? | K1: Correction
A2: BB28 | B2: Week 1 | D2: Devens | E2: Ashley | G2: Ashley | H2: =IF(E2="","",IF(E2=G2,"Yes","No")) -> Yes | I2: Wikipedia
A3: BB28 | B3: Week 1 | D3: Drew | E3: Ashley | G3: Ashley | H3: =IF(E3="","",IF(E3=G3,"Yes","No")) -> Yes | I3: Wikipedia
A4: BB28 | B4: Week 1 | D4: Melody | E4: Ashley | G4: Ashley | H4: =IF(E4="","",IF(E4=G4,"Yes","No")) -> Yes | I4: Wikipedia
A5: BB28 | B5: Week 1 | D5: Yash | E5: Ashley | G5: Ashley | H5: =IF(E5="","",IF(E5=G5,"Yes","No")) -> Yes | I5: Wikipedia
A6: BB28 | B6: Week 1 | D6: Barrett | E6: Ashley | G6: Ashley | H6: =IF(E6="","",IF(E6=G6,"Yes","No")) -> Yes | I6: Wikipedia
A7: BB28 | B7: Week 1 | D7: Angela | E7: Ashley | G7: Ashley | H7: =IF(E7="","",IF(E7=G7,"Yes","No")) -> Yes | I7: Wikipedia
A8: BB28 | B8: Week 1 | D8: La Trice | E8: Ashley | G8: Ashley | H8: =IF(E8="","",IF(E8=G8,"Yes","No")) -> Yes | I8: Wikipedia
A9: BB28 | B9: Week 1 | D9: Haley | E9: Ashley | G9: Ashley | H9: =IF(E9="","",IF(E9=G9,"Yes","No")) -> Yes | I9: Wikipedia
A10: BB28 | B10: Week 1 | D10: Mallory | E10: Ashley | G10: Ashley | H10: =IF(E10="","",IF(E10=G10,"Yes","No")) -> Yes | I10: Wikipedia
A11: BB28 | B11: Week 1 | D11: Kamu | E11: Ashley | G11: Ashley | H11: =IF(E11="","",IF(E11=G11,"Yes","No")) -> Yes | I11: Wikipedia
A12: BB28 | B12: Week 1 | D12: Chuk | E12: Ashley | G12: Ashley | H12: =IF(E12="","",IF(E12=G12,"Yes","No")) -> Yes | I12: Wikipedia
A13: BB28 | B13: Week 1 | D13: Lyric | E13: Ashley | G13: Ashley | H13: =IF(E13="","",IF(E13=G13,"Yes","No")) -> Yes | I13: Wikipedia
... A15: BB28 | B15: Week 1 | D15: Rome | E15: Ashley | G15: Ashley | H15: =IF(E15="","",IF(E15=G15,"Yes","No")) -> Yes | I15: Wikipedia
A16: BB28 | B16: Week 1 | D16: Taylor | F16: Nominated | G16: Ashley | H16: =IF(E16="","",IF(E16=G16,"Yes","No")) | I16: Wikipedia
A17: BB28 | B17: Week 1 | D17: Dee | F17: Head of Household | G17: Ashley | H17: =IF(E17="","",IF(E17=G17,"Yes","No")) | I17: Wikipedia
A18: BB28 | B18: Week 1 | D18: Ashley | F18: Nominated | G18: Ashley | H18: =IF(E18="","",IF(E18=G18,"Yes","No")) | I18: Wikipedia
A19: BB28 | B19: Week 2 | D19: Taylor | E19: Melody | G19: Rome | H19: =IF(E19="","",IF(E19=G19,"Yes","No")) -> No | I19: Wikipedia
A20: BB28 | B20: Week 2 | D20: Drew | E20: Rome | G20: Rome | H20: =IF(E20="","",IF(E20=G20,"Yes","No")) -> Yes | I20: Wikipedia
A21: BB28 | B21: Week 2 | D21: Dee | E21: Rome | G21: Rome | H21: =IF(E21="","",IF(E21=G21,"Yes","No")) -> Yes | I21: Wikipedia
A22: BB28 | B22: Week 2 | D22: Yash | E22: Rome | G22: Rome | H22: =IF(E22="","",IF(E22=G22,"Yes","No")) -> Yes | I22: Wikipedia
A23: BB28 | B23: Week 2 | D23: Barrett | E23: Rome | G23: Rome | H23: =IF(E23="","",IF(E23=G23,"Yes","No")) -> Yes | I23: Wikipedia
A24: BB28 | B24: Week 2 | D24: Angela | E24: Rome | G24: Rome | H24: =IF(E24="","",IF(E24=G24,"Yes","No")) -> Yes | I24: Wikipedia
A25: BB28 | B25: Week 2 | D25: La Trice | E25: Rome | G25: Rome | H25: =IF(E25="","",IF(E25=G25,"Yes","No")) -> Yes | I25: Wikipedia
A26: BB28 | B26: Week 2 | D26: Haley | E26: Rome | G26: Rome | H26: =IF(E26="","",IF(E26=G26,"Yes","No")) -> Yes | I26: Wikipedia
A27: BB28 | B27: Week 2 | D27: Mallory | E27: Rome | G27: Rome | H27: =IF(E27="","",IF(E27=G27,"Yes","No")) -> Yes | I27: Wikipedia
A28: BB28 | B28: Week 2 | D28: Kamu | E28: Rome | G28: Rome | H28: =IF(E28="","",IF(E28=G28,"Yes","No")) -> Yes | I28: Wikipedia
A29: BB28 | B29: Week 2 | D29: Chuk | E29: Rome | G29: Rome | H29: =IF(E29="","",IF(E29=G29,"Yes","No")) -> Yes | I29: Wikipedia
A30: BB28 | B30: Week 2 | D30: Lyric | E30: Rome | G30: Rome | H30: =IF(E30="","",IF(E30=G30,"Yes","No")) -> Yes | I30: Wikipedia
A31: BB28 | B31: Week 2 | D31: Jason | E31: Rome | G31: Rome | H31: =IF(E31="","",IF(E31=G31,"Yes","No")) -> Yes | I31: Wikipedia
A32: BB28 | B32: Week 2 | D32: Devens | F32: Head of Household | G32: Rome | H32: =IF(E32="","",IF(E32=G32,"Yes","No")) | I32: Wikipedia
A33: BB28 | B33: Week 2 | D33: Melody | F33: Nominated | G33: Rome | H33: =IF(E33="","",IF(E33=G33,"Yes","No")) | I33: Wikipedia
A34: BB28 | B34: Week 2 | D34: Rome | F34: Nominated | G34: Rome | H34: =IF(E34="","",IF(E34=G34,"Yes","No")) | I34: Wikipedia
A35: BB28 | B35: Week 3 | D35: Devens | E35: Jason | G35: Jason | H35: =IF(E35="","",IF(E35=G35,"Yes","No")) -> Yes | I35: Wikipedia
A36: BB28 | B36: Week 3 | D36: Taylor | E36: Jason | G36: Jason | H36: =IF(E36="","",IF(E36=G36,"Yes","No")) -> Yes | I36: Wikipedia
A37: BB28 | B37: Week 3 | D37: Drew | E37: Jason | G37: Jason | H37: =IF(E37="","",IF(E37=G37,"Yes","No")) -> Yes | I37: Wikipedia
A38: BB28 | B38: Week 3 | D38: Dee | E38: Jason | G38: Jason | H38: =IF(E38="","",IF(E38=G38,"Yes","No")) -> Yes | I38: Wikipedia
A39: BB28 | B39: Week 3 | D39: Melody | E39: Jason | G39: Jason | H39: =IF(E39="","",IF(E39=G39,"Yes","No")) -> Yes | I39: Wikipedia
A40: BB28 | B40: Week 3 | D40: Yash | E40: Jason | G40: Jason | H40: =IF(E40="","",IF(E40=G40,"Yes","No")) -> Yes | I40: Wikipedia
A41: BB28 | B41: Week 3 | D41: Barrett | E41: Jason | G41: Jason | H41: =IF(E41="","",IF(E41=G41,"Yes","No")) -> Yes | I41: Wikipedia
A42: BB28 | B42: Week 3 | D42: Angela | E42: Jason | G42: Jason | H42: =IF(E42="","",IF(E42=G42,"Yes","No")) -> Yes | I42: Wikipedia
A43: BB28 | B43: Week 3 | D43: Haley | E43: Jason | G43: Jason | H43: =IF(E43="","",IF(E43=G43,"Yes","No")) -> Yes | I43: Wikipedia
A44: BB28 | B44: Week 3 | D44: Mallory | E44: Jason | G44: Jason | H44: =IF(E44="","",IF(E44=G44,"Yes","No")) -> Yes | I44: Wikipedia
A45: BB28 | B45: Week 3 | D45: Chuk | E45: Jason | G45: Jason | H45: =IF(E45="","",IF(E45=G45,"Yes","No")) -> Yes | I45: Wikipedia
A46: BB28 | B46: Week 3 | D46: Lyric | E46: Jason | G46: Jason | H46: =IF(E46="","",IF(E46=G46,"Yes","No")) -> Yes | I46: Wikipedia
A47: BB28 | B47: Week 3 | D47: La Trice | F47: Nominated | G47: Jason | H47: =IF(E47="","",IF(E47=G47,"Yes","No")) | I47: Wikipedia
A48: BB28 | B48: Week 3 | D48: Kamu | F48: Head of Household | G48: Jason | H48: =IF(E48="","",IF(E48=G48,"Yes","No")) | I48: Wikipedia
A49: BB28 | B49: Week 3 | D49: Jason | F49: Nominated | G49: Jason | H49: =IF(E49="","",IF(E49=G49,"Yes","No")) | I49: Wikipedia
A50: BB28 | B50: Week 4 | D50: Devens | E50: Lyric | G50: Lyric | H50: =IF(E50="","",IF(E50=G50,"Yes","No")) -> Yes | I50: Wikipedia
A51: BB28 | B51: Week 4 | D51: Taylor | E51: Lyric | G51: Lyric | H51: =IF(E51="","",IF(E51=G51,"Yes","No")) -> Yes | I51: Wikipedia
A52: BB28 | B52: Week 4 | D52: Drew | E52: Lyric | G52: Lyric | H52: =IF(E52="","",IF(E52=G52,"Yes","No")) -> Yes | I52: Wikipedia
A53: BB28 | B53: Week 4 | D53: Dee | E53: Lyric | G53: Lyric | H53: =IF(E53="","",IF(E53=G53,"Yes","No")) -> Yes | I53: Wikipedia
A54: BB28 | B54: Week 4 | D54: Yash | E54: Melody | G54: Lyric | H54: =IF(E54="","",IF(E54=G54,"Yes","No")) -> No | I54: Wikipedia
A55: BB28 | B55: Week 4 | D55: Barrett | E55: Lyric | G55: Lyric | H55: =IF(E55="","",IF(E55=G55,"Yes","No")) -> Yes | I55: Wikipedia
A56: BB28 | B56: Week 4 | D56: Angela | E56: Lyric | G56: Lyric | H56: =IF(E56="","",IF(E56=G56,"Yes","No")) -> Yes | I56: Wikipedia
A57: BB28 | B57: Week 4 | D57: La Trice | E57: Lyric | G57: Lyric | H57: =IF(E57="","",IF(E57=G57,"Yes","No")) -> Yes | I57: Wikipedia
A58: BB28 | B58: Week 4 | D58: Mallory | E58: Lyric | G58: Lyric | H58: =IF(E58="","",IF(E58=G58,"Yes","No")) -> Yes | I58: Wikipedia
A59: BB28 | B59: Week 4 | D59: Kamu | E59: Melody | G59: Lyric | H59: =IF(E59="","",IF(E59=G59,"Yes","No")) -> No | I59: Wikipedia
A60: BB28 | B60: Week 4 | D60: Chuk | E60: Melody | G60: Lyric | H60: =IF(E60="","",IF(E60=G60,"Yes","No")) -> No | I60: Wikipedia
A61: BB28 | B61: Week 4 | D61: Melody | F61: Nominated | G61: Lyric | H61: =IF(E61="","",IF(E61=G61,"Yes","No")) | I61: Wikipedia
A62: BB28 | B62: Week 4 | D62: Haley | F62: Head of Household | G62: Lyric | H62: =IF(E62="","",IF(E62=G62,"Yes","No")) | I62: Wikipedia
A63: BB28 | B63: Week 4 | D63: Lyric | F63: Nominated | G63: Lyric | H63: =IF(E63="","",IF(E63=G63,"Yes","No")) | I63: Wikipedia
A64: BB28 | B64: Week 5 | D64: Devens | E64: Chuk | G64: Chuk | H64: =IF(E64="","",IF(E64=G64,"Yes","No")) -> Yes | I64: Wikipedia
A65: BB28 | B65: Week 5 | D65: Taylor | E65: Chuk | G65: Chuk | H65: =IF(E65="","",IF(E65=G65,"Yes","No")) -> Yes | I65: Wikipedia
A66: BB28 | B66: Week 5 | D66: Drew | E66: Chuk | G66: Chuk | H66: =IF(E66="","",IF(E66=G66,"Yes","No")) -> Yes | I66: Wikipedia
A67: BB28 | B67: Week 5 | D67: Dee | E67: Chuk | G67: Chuk | H67: =IF(E67="","",IF(E67=G67,"Yes","No")) -> Yes | I67: Wikipedia
A68: BB28 | B68: Week 5 | D68: Melody | E68: Chuk | G68: Chuk | H68: =IF(E68="","",IF(E68=G68,"Yes","No")) -> Yes | I68: Wikipedia
A69: BB28 | B69: Week 5 | D69: Yash | E69: Chuk | G69: Chuk | H69: =IF(E69="","",IF(E69=G69,"Yes","No")) -> Yes | I69: Wikipedia
A70: BB28 | B70: Week 5 | D70: Angela | E70: Chuk | G70: Chuk | H70: =IF(E70="","",IF(E70=G70,"Yes","No")) -> Yes | I70: Wikipedia
A71: BB28 | B71: Week 5 | D71: Haley | E71: Barrett | G71: Chuk | H71: =IF(E71="","",IF(E71=G71,"Yes","No")) -> No | I71: Wikipedia
A72: BB28 | B72: Week 5 | D72: Mallory | E72: Chuk | G72: Chuk | H72: =IF(E72="","",IF(E72=G72,"Yes","No")) -> Yes | I72: Wikipedia
A73: BB28 | B73: Week 5 | D73: Kamu | E73: Chuk | G73: Chuk | H73: =IF(E73="","",IF(E73=G73,"Yes","No")) -> Yes | I73: Wikipedia
A74: BB28 | B74: Week 5 | D74: Barrett | F74: Nominated | G74: Chuk | H74: =IF(E74="","",IF(E74=G74,"Yes","No")) | I74: Wikipedia
A75: BB28 | B75: Week 5 | D75: La Trice | F75: Head of Household | G75: Chuk | H75: =IF(E75="","",IF(E75=G75,"Yes","No")) | I75: Wikipedia
A76: BB28 | B76: Week 5 | D76: Chuk | F76: Nominated | G76: Chuk | H76: =IF(E76="","",IF(E76=G76,"Yes","No")) | I76: Wikipedia
A77: BB28 | B77: Week 6 | D77: Devens | E77: Kamu | G77: Kamu | H77: =IF(E77="","",IF(E77=G77,"Yes","No")) -> Yes | I77: Wikipedia
A78: BB28 | B78: Week 6 | D78: Taylor | E78: Kamu | G78: Kamu | H78: =IF(E78="","",IF(E78=G78,"Yes","No")) -> Yes | I78: Wikipedia
A79: BB28 | B79: Week 6 | D79: Drew | E79: Kamu | G79: Kamu | H79: =IF(E79="","",IF(E79=G79,"Yes","No")) -> Yes | I79: Wikipedia
A80: BB28 | B80: Week 6 | D80: Dee | E80: Kamu | G80: Kamu | H80: =IF(E80="","",IF(E80=G80,"Yes","No")) -> Yes | I80: Wikipedia
A81: BB28 | B81: Week 6 | D81: Melody | E81: Kamu | G81: Kamu | H81: =IF(E81="","",IF(E81=G81,"Yes","No")) -> Yes | I81: Wikipedia
A82: BB28 | B82: Week 6 | D82: Barrett | E82: Kamu | G82: Kamu | H82: =IF(E82="","",IF(E82=G82,"Yes","No")) -> Yes | I82: Wikipedia
A83: BB28 | B83: Week 6 | D83: Angela | E83: Kamu | G83: Kamu | H83: =IF(E83="","",IF(E83=G83,"Yes","No")) -> Yes | I83: Wikipedia
A84: BB28 | B84: Week 6 | D84: La Trice | E84: Haley | G84: Kamu | H84: =IF(E84="","",IF(E84=G84,"Yes","No")) -> No | I84: Wikipedia
A85: BB28 | B85: Week 6 | D85: Mallory | E85: Kamu | G85: Kamu | H85: =IF(E85="","",IF(E85=G85,"Yes","No")) -> Yes | I85: Wikipedia
A86: BB28 | B86: Week 6 | D86: Yash | F86: Head of Household | G86: Kamu | H86: =IF(E86="","",IF(E86=G86,"Yes","No")) | I86: Wikipedia
A87: BB28 | B87: Week 6 | D87: Haley | F87: Nominated | G87: Kamu | H87: =IF(E87="","",IF(E87=G87,"Yes","No")) | I87: Wikipedia
A88: BB28 | B88: Week 6 | D88: Kamu | F88: Nominated | G88: Kamu | H88: =IF(E88="","",IF(E88=G88,"Yes","No")) | I88: Wikipedia
A89: BB28 | B89: Week 7 | D89: Devens | E89: Mallory | G89: Mallory | H89: =IF(E89="","",IF(E89=G89,"Yes","No")) -> Yes | I89: Wikipedia
A90: BB28 | B90: Week 7 | D90: Drew | E90: Mallory | G90: Mallory | H90: =IF(E90="","",IF(E90=G90,"Yes","No")) -> Yes | I90: Wikipedia
A91: BB28 | B91: Week 7 | D91: Melody | E91: Taylor | G91: Mallory | H91: =IF(E91="","",IF(E91=G91,"Yes","No")) -> No | I91: Wikipedia
A92: BB28 | B92: Week 7 | D92: Yash | E92: Mallory | G92: Mallory | H92: =IF(E92="","",IF(E92=G92,"Yes","No")) -> Yes | I92: Wikipedia
A93: BB28 | B93: Week 7 | D93: Barrett | E93: Taylor | G93: Mallory | H93: =IF(E93="","",IF(E93=G93,"Yes","No")) -> No | I93: Wikipedia
A94: BB28 | B94: Week 7 | D94: Angela | E94: Mallory | G94: Mallory | H94: =IF(E94="","",IF(E94=G94,"Yes","No")) -> Yes | I94: Wikipedia
A95: BB28 | B95: Week 7 | D95: La Trice | E95: Mallory | G95: Mallory | H95: =IF(E95="","",IF(E95=G95,"Yes","No")) -> Yes | I95: Wikipedia
A96: BB28 | B96: Week 7 | D96: Haley | E96: Mallory | G96: Mallory | H96: =IF(E96="","",IF(E96=G96,"Yes","No")) -> Yes | I96: Wikipedia
A97: BB28 | B97: Week 7 | D97: Taylor | F97: Nominated | G97: Mallory | H97: =IF(E97="","",IF(E97=G97,"Yes","No")) | I97: Wikipedia
A98: BB28 | B98: Week 7 | D98: Dee | F98: Head of Household | G98: Mallory | H98: =IF(E98="","",IF(E98=G98,"Yes","No")) | I98: Wikipedia
A99: BB28 | B99: Week 7 | D99: Mallory | F99: Nominated | G99: Mallory | H99: =IF(E99="","",IF(E99=G99,"Yes","No")) | I99: Wikipedia
A100: BB28 | B100: Week 8 | C100: Day 53 | D100: Devens | E100: La Trice | G100: La Trice | H100: =IF(E100="","",IF(E100=G100,"Yes","No")) -> Yes | I100: Wikipedia
A101: BB28 | B101: Week 8 | C101: Day 53 | D101: Dee | E101: La Trice | G101: La Trice | H101: =IF(E101="","",IF(E101=G101,"Yes","No")) -> Yes | I101: Wikipedia
...

Sheet Players
A1: Season | B1: Player | C1: Result | D1: HOHs | E1: Vetoes | F1: Twist wins | G1: Noms | H1: Final noms | I1: Votes against | J1: Votes cast | K1: With the house | L1: Source | M1: Looks right? | N1: Correction
A2: BB28 | B2: Devens | C2: Winner | D2: =COUNTIFS(Weeks!$A$2:$A$115,$A2,Weeks!$S$2:$S$115,"*;"&$B2&";*") -> 2 | E2: =COUNTIFS(Weeks!$A$2:$A$115,$A2,Weeks!$T$2:$T$115,"*;"&$B2&";*") -> 3 | F2: =COUNTIFS(Weeks!$A$2:$A$115,$A2,Weeks!$W$2:$W$115,"*;"&$B2&";*") -> 2 | G2: =COUNTIFS(Weeks!$A$2:$A$115,$A2,Weeks!$U$2:$U$115,"*;"&$B2&";*") -> 2 | H2: =COUNTIFS(Weeks!$A$2:$A$115,$A2,Weeks!$V$2:$V$115,"*;"&$B2&";*") -> 1 | I2: =COUNTIFS(Votes!$A$2:$A$1113,$A2,Votes!$E$2:$E$1113,$B2) -> 0 | J2: =COUNTIFS(Votes!$A$2:$A$1113,$A2,Votes!$D$2:$D$1113,$B2,Votes!$E$2:$E$1113,"<>") -> 11 | K2: =COUNTIFS(Votes!$A$2:$A$1113,$A2,Votes!$D$2:$D$1113,$B2,Votes!$H$2:$H$1113,"Yes") -> 11 | L2: Wikipedia
A3: BB28 | B3: Taylor | C3: Runner-up | D3: =COUNTIFS(Weeks!$A$2:$A$115,$A3,Weeks!$S$2:$S$115,"*;"&$B3&";*") -> 1 | E3: =COUNTIFS(Weeks!$A$2:$A$115,$A3,Weeks!$T$2:$T$115,"*;"&$B3&";*") -> 1 | F3: =COUNTIFS(Weeks!$A$2:$A$115,$A3,Weeks!$W$2:$W$115,"*;"&$B3&";*") -> 0 | G3: =COUNTIFS(Weeks!$A$2:$A$115,$A3,Weeks!$U$2:$U$115,"*;"&$B3&";*") -> 4 | H3: =COUNTIFS(Weeks!$A$2:$A$115,$A3,Weeks!$V$2:$V$115,"*;"&$B3&";*") -> 5 | I3: =COUNTIFS(Votes!$A$2:$A$1113,$A3,Votes!$E$2:$E$1113,$B3) -> 6 | J3: =COUNTIFS(Votes!$A$2:$A$1113,$A3,Votes!$D$2:$D$1113,$B3,Votes!$E$2:$E$1113,"<>") -> 7 | K3: =COUNTIFS(Votes!$A$2:$A$1113,$A3,Votes!$D$2:$D$1113,$B3,Votes!$H$2:$H$1113,"Yes") -> 5 | L3: Wikipedia
A4: BB28 | B4: Drew | C4: Evicted (Day 87) | D4: =COUNTIFS(Weeks!$A$2:$A$115,$A4,Weeks!$S$2:$S$115,"*;"&$B4&";*") -> 1 | E4: =COUNTIFS(Weeks!$A$2:$A$115,$A4,Weeks!$T$2:$T$115,"*;"&$B4&";*") -> 3 | F4: =COUNTIFS(Weeks!$A$2:$A$115,$A4,Weeks!$W$2:$W$115,"*;"&$B4&";*") -> 2 | G4: =COUNTIFS(Weeks!$A$2:$A$115,$A4,Weeks!$U$2:$U$115,"*;"&$B4&";*") -> 5 | H4: =COUNTIFS(Weeks!$A$2:$A$115,$A4,Weeks!$V$2:$V$115,"*;"&$B4&";*") -> 0 | I4: =COUNTIFS(Votes!$A$2:$A$1113,$A4,Votes!$E$2:$E$1113,$B4) -> 0 | J4: =COUNTIFS(Votes!$A$2:$A$1113,$A4,Votes!$D$2:$D$1113,$B4,Votes!$E$2:$E$1113,"<>") -> 12 | K4: =COUNTIFS(Votes!$A$2:$A$1113,$A4,Votes!$D$2:$D$1113,$B4,Votes!$H$2:$H$1113,"Yes") -> 10 | L4: Wikipedia
A5: BB28 | B5: Dee | C5: Evicted (Day 80) | D5: =COUNTIFS(Weeks!$A$2:$A$115,$A5,Weeks!$S$2:$S$115,"*;"&$B5&";*") -> 2 | E5: =COUNTIFS(Weeks!$A$2:$A$115,$A5,Weeks!$T$2:$T$115,"*;"&$B5&";*") -> 0 | F5: =COUNTIFS(Weeks!$A$2:$A$115,$A5,Weeks!$W$2:$W$115,"*;"&$B5&";*") -> 0 | G5: =COUNTIFS(Weeks!$A$2:$A$115,$A5,Weeks!$U$2:$U$115,"*;"&$B5&";*") -> 4 | H5: =COUNTIFS(Weeks!$A$2:$A$115,$A5,Weeks!$V$2:$V$115,"*;"&$B5&";*") -> 3 | I5: =COUNTIFS(Votes!$A$2:$A$1113,$A5,Votes!$E$2:$E$1113,$B5) -> 4 | J5: =COUNTIFS(Votes!$A$2:$A$1113,$A5,Votes!$D$2:$D$1113,$B5,Votes!$E$2:$E$1113,"<>") -> 8 | K5: =COUNTIFS(Votes!$A$2:$A$1113,$A5,Votes!$D$2:$D$1113,$B5,Votes!$H$2:$H$1113,"Yes") -> 8 | L5: Wikipedia
A6: BB28 | B6: Melody | C6: Evicted (Day 77) | D6: =COUNTIFS(Weeks!$A$2:$A$115,$A6,Weeks!$S$2:$S$115,"*;"&$B6&";*") -> 1 | E6: =COUNTIFS(Weeks!$A$2:$A$115,$A6,Weeks!$T$2:$T$115,"*;"&$B6&";*") -> 0 | F6: =COUNTIFS(Weeks!$A$2:$A$115,$A6,Weeks!$W$2:$W$115,"*;"&$B6&";*") -> 1 | G6: =COUNTIFS(Weeks!$A$2:$A$115,$A6,Weeks!$U$2:$U$115,"*;"&$B6&";*") -> 4 | H6: =COUNTIFS(Weeks!$A$2:$A$115,$A6,Weeks!$V$2:$V$115,"*;"&$B6&";*") -> 3 | I6: =COUNTIFS(Votes!$A$2:$A$1113,$A6,Votes!$E$2:$E$1113,$B6) -> 6 | J6: =COUNTIFS(Votes!$A$2:$A$1113,$A6,Votes!$D$2:$D$1113,$B6,Votes!$E$2:$E$1113,"<>") -> 8 | K6: =COUNTIFS(Votes!$A$2:$A$1113,$A6,Votes!$D$2:$D$1113,$B6,Votes!$H$2:$H$1113,"Yes") -> 4 | L6: Wikipedia
A7: BB28 | B7: Yash | C7: Evicted (Day 73) | D7: =COUNTIFS(Weeks!$A$2:$A$115,$A7,Weeks!$S$2:$S$115,"*;"&$B7&";*") -> 2 | E7: =COUNTIFS(Weeks!$A$2:$A$115,$A7,Weeks!$T$2:$T$115,"*;"&$B7&";*") -> 3 | F7: =COUNTIFS(Weeks!$A$2:$A$115,$A7,Weeks!$W$2:$W$115,"*;"&$B7&";*") -> 1 | G7: =COUNTIFS(Weeks!$A$2:$A$115,$A7,Weeks!$U$2:$U$115,"*;"&$B7&";*") -> 2 | H7: =COUNTIFS(Weeks!$A$2:$A$115,$A7,Weeks!$V$2:$V$115,"*;"&$B7&";*") -> 1 | I7: =COUNTIFS(Votes!$A$2:$A$1113,$A7,Votes!$E$2:$E$1113,$B7) -> 2 | J7: =COUNTIFS(Votes!$A$2:$A$1113,$A7,Votes!$D$2:$D$1113,$B7,Votes!$E$2:$E$1113,"<>") -> 8 | K7: =COUNTIFS(Votes!$A$2:$A$1113,$A7,Votes!$D$2:$D$1113,$B7,Votes!$H$2:$H$1113,"Yes") -> 7 | L7: Wikipedia
A8: BB28 | B8: Barrett | C8: Evicted (Day 73) | D8: =COUNTIFS(Weeks!$A$2:$A$115,$A8,Weeks!$S$2:$S$115,"*;"&$B8&";*") -> 1 | E8: =COUNTIFS(Weeks!$A$2:$A$115,$A8,Weeks!$T$2:$T$115,"*;"&$B8&";*") -> 0 | F8: =COUNTIFS(Weeks!$A$2:$A$115,$A8,Weeks!$W$2:$W$115,"*;"&$B8&";*") -> 0 | G8: =COUNTIFS(Weeks!$A$2:$A$115,$A8,Weeks!$U$2:$U$115,"*;"&$B8&";*") -> 2 | H8: =COUNTIFS(Weeks!$A$2:$A$115,$A8,Weeks!$V$2:$V$115,"*;"&$B8&";*") -> 2 | I8: =COUNTIFS(Votes!$A$2:$A$1113,$A8,Votes!$E$2:$E$1113,$B8) -> 4 | J8: =COUNTIFS(Votes!$A$2:$A$1113,$A8,Votes!$D$2:$D$1113,$B8,Votes!$E$2:$E$1113,"<>") -> 7 | K8: =COUNTIFS(Votes!$A$2:$A$1113,$A8,Votes!$D$2:$D$1113,$B8,Votes!$H$2:$H$1113,"Yes") -> 6 | L8: Wikipedia
A9: BB28 | B9: Angela | C9: Evicted (Day 66) | D9: =COUNTIFS(Weeks!$A$2:$A$115,$A9,Weeks!$S$2:$S$115,"*;"&$B9&";*") -> 0 | E9: =COUNTIFS(Weeks!$A$2:$A$115,$A9,Weeks!$T$2:$T$115,"*;"&$B9&";*") -> 0 | F9: =COUNTIFS(Weeks!$A$2:$A$115,$A9,Weeks!$W$2:$W$115,"*;"&$B9&";*") -> 1 | G9: =COUNTIFS(Weeks!$A$2:$A$115,$A9,Weeks!$U$2:$U$115,"*;"&$B9&";*") -> 2 | H9: =COUNTIFS(Weeks!$A$2:$A$115,$A9,Weeks!$V$2:$V$115,"*;"&$B9&";*") -> 1 | I9: =COUNTIFS(Votes!$A$2:$A$1113,$A9,Votes!$E$2:$E$1113,$B9) -> 3 | J9: =COUNTIFS(Votes!$A$2:$A$1113,$A9,Votes!$D$2:$D$1113,$B9,Votes!$E$2:$E$1113,"<>") -> 8 | K9: =COUNTIFS(Votes!$A$2:$A$1113,$A9,Votes!$D$2:$D$1113,$B9,Votes!$H$2:$H$1113,"Yes") -> 7 | L9: Wikipedia
A10: BB28 | B10: La Trice | C10: Evicted (Day 59) | D10: =COUNTIFS(Weeks!$A$2:$A$115,$A10,Weeks!$S$2:$S$115,"*;"&$B10&";*") -> 1 | E10: =COUNTIFS(Weeks!$A$2:$A$115,$A10,Weeks!$T$2:$T$115,"*;"&$B10&";*") -> 1 | F10: =COUNTIFS(Weeks!$A$2:$A$115,$A10,Weeks!$W$2:$W$115,"*;"&$B10&";*") -> 0 | G10: =COUNTIFS(Weeks!$A$2:$A$115,$A10,Weeks!$U$2:$U$115,"*;"&$B10&";*") -> 3 | H10: =COUNTIFS(Weeks!$A$2:$A$115,$A10,Weeks!$V$2:$V$115,"*;"&$B10&";*") -> 2 | I10: =COUNTIFS(Votes!$A$2:$A$1113,$A10,Votes!$E$2:$E$1113,$B10) -> 4 | J10: =COUNTIFS(Votes!$A$2:$A$1113,$A10,Votes!$D$2:$D$1113,$B10,Votes!$E$2:$E$1113,"<>") -> 5 | K10: =COUNTIFS(Votes!$A$2:$A$1113,$A10,Votes!$D$2:$D$1113,$B10,Votes!$H$2:$H$1113,"Yes") -> 4 | L10: Wikipedia
A11: BB28 | B11: Haley | C11: Eliminated (Day 53) | D11: =COUNTIFS(Weeks!$A$2:$A$115,$A11,Weeks!$S$2:$S$115,"*;"&$B11&";*") -> 1 | E11: =COUNTIFS(Weeks!$A$2:$A$115,$A11,Weeks!$T$2:$T$115,"*;"&$B11&";*") -> 0 | F11: =COUNTIFS(Weeks!$A$2:$A$115,$A11,Weeks!$W$2:$W$115,"*;"&$B11&";*") -> 1 | G11: =COUNTIFS(Weeks!$A$2:$A$115,$A11,Weeks!$U$2:$U$115,"*;"&$B11&";*") -> 2 | H11: =COUNTIFS(Weeks!$A$2:$A$115,$A11,Weeks!$V$2:$V$115,"*;"&$B11&";*") -> 1 | I11: =COUNTIFS(Votes!$A$2:$A$1113,$A11,Votes!$E$2:$E$1113,$B11) -> 1 | J11: =COUNTIFS(Votes!$A$2:$A$1113,$A11,Votes!$D$2:$D$1113,$B11,Votes!$E$2:$E$1113,"<>") -> 5 | K11: =COUNTIFS(Votes!$A$2:$A$1113,$A11,Votes!$D$2:$D$1113,$B11,Votes!$H$2:$H$1113,"Yes") -> 4 | L11: Wikipedia
A12: BB28 | B12: Mallory | C12: Evicted (Day 52) | D12: =COUNTIFS(Weeks!$A$2:$A$115,$A12,Weeks!$S$2:$S$115,"*;"&$B12&";*") -> 0 | E12: =COUNTIFS(Weeks!$A$2:$A$115,$A12,Weeks!$T$2:$T$115,"*;"&$B12&";*") -> 1 | F12: =COUNTIFS(Weeks!$A$2:$A$115,$A12,Weeks!$W$2:$W$115,"*;"&$B12&";*") -> 1 | G12: =COUNTIFS(Weeks!$A$2:$A$115,$A12,Weeks!$U$2:$U$115,"*;"&$B12&";*") -> 2 | H12: =COUNTIFS(Weeks!$A$2:$A$115,$A12,Weeks!$V$2:$V$115,"*;"&$B12&";*") -> 1 | I12: =COUNTIFS(Votes!$A$2:$A$1113,$A12,Votes!$E$2:$E$1113,$B12) -> 6 | J12: =COUNTIFS(Votes!$A$2:$A$1113,$A12,Votes!$D$2:$D$1113,$B12,Votes!$E$2:$E$1113,"<>") -> 6 | K12: =COUNTIFS(Votes!$A$2:$A$1113,$A12,Votes!$D$2:$D$1113,$B12,Votes!$H$2:$H$1113,"Yes") -> 6 | L12: Wikipedia
A13: BB28 | B13: Kamu | C13: Evicted (Day 45) | D13: =COUNTIFS(Weeks!$A$2:$A$115,$A13,Weeks!$S$2:$S$115,"*;"&$B13&";*") -> 1 | E13: =COUNTIFS(Weeks!$A$2:$A$115,$A13,Weeks!$T$2:$T$115,"*;"&$B13&";*") -> 1 | F13: =COUNTIFS(Weeks!$A$2:$A$115,$A13,Weeks!$W$2:$W$115,"*;"&$B13&";*") -> 0 | G13: =COUNTIFS(Weeks!$A$2:$A$115,$A13,Weeks!$U$2:$U$115,"*;"&$B13&";*") -> 0 | H13: =COUNTIFS(Weeks!$A$2:$A$115,$A13,Weeks!$V$2:$V$115,"*;"&$B13&";*") -> 1 | I13: =COUNTIFS(Votes!$A$2:$A$1113,$A13,Votes!$E$2:$E$1113,$B13) -> 8 | J13: =COUNTIFS(Votes!$A$2:$A$1113,$A13,Votes!$D$2:$D$1113,$B13,Votes!$E$2:$E$1113,"<>") -> 4 | K13: =COUNTIFS(Votes!$A$2:$A$1113,$A13,Votes!$D$2:$D$1113,$B13,Votes!$H$2:$H$1113,"Yes") -> 3 | L13: Wikipedia
... A132: BB21 | B132: David | C132: Remained evicted (Day 30) | D132: =COUNTIFS(Weeks!$A$2:$A$115,$A132,Weeks!$S$2:$S$115,"*;"&$B132&";*") -> 0 | E132: =COUNTIFS(Weeks!$A$2:$A$115,$A132,Weeks!$T$2:$T$115,"*;"&$B132&";*") -> 0 | F132: =COUNTIFS(Weeks!$A$2:$A$115,$A132,Weeks!$W$2:$W$115,"*;"&$B132&";*") -> 0 | G132: =COUNTIFS(Weeks!$A$2:$A$115,$A132,Weeks!$U$2:$U$115,"*;"&$B132&";*") -> 0 | H132: =COUNTIFS(Weeks!$A$2:$A$115,$A132,Weeks!$V$2:$V$115,"*;"&$B132&";*") -> 0 | I132: =COUNTIFS(Votes!$A$2:$A$1113,$A132,Votes!$E$2:$E$1113,$B132) -> 0 | J132: =COUNTIFS(Votes!$A$2:$A$1113,$A132,Votes!$D$2:$D$1113,$B132,Votes!$E$2:$E$1113,"<>") -> 0 | K132: =COUNTIFS(Votes!$A$2:$A$1113,$A132,Votes!$D$2:$D$1113,$B132,Votes!$H$2:$H$1113,"Yes") -> 0 | L132: Wikipedia

Sheet Competitions
A1: Season | B1: Week | C1: Kind | D1: Competition | E1: Won by | F1: Round | G1: From the summary | H1: Source | I1: Looks right? | J1: Correction
A2: BB28 | B2: Week 1 | C2: Veto | D2: Back From the Future | E2: (not tied to a winner) | G2: In the Power of Veto Competition ("Back From the Future"), each HouseGuest must help future Howie Gordon defeat future Will Kirby by constructing a path between the "Table Time Machine" and Will's throne using a series of tubes. | H2: Wikipedia
A3: BB28 | B3: Week 2 | C3: HOH | D3: Achy Breaky HOH | E3: (not tied to a winner) | G3: In the Head of Household Competition ("Achy Breaky HOH"), HouseGuests must slide a disk down a table, attempting to land it on the highest-scoring numbered spots. | H3: Wikipedia
A4: BB28 | B4: Week 2 | C4: Veto | D4: Flower Power | E4: (not tied to a winner) | G4: In the Power of Veto Competition ("Flower Power"), HouseGuests must find and retrieve twelve hidden puzzle pieces. | H4: Wikipedia
A5: BB28 | B5: Week 3 | C5: HOH | D5: Wrestlegasm | E5: (not tied to a winner) | G5: The episode concluded with the HouseGuests beginning the third Head of Household competition, "Wrestlegasm". | H5: Wikipedia
A6: BB28 | B6: Week 3 | C6: Veto | D6: The Pickle Ball | E6: (not tied to a winner) | G6: In the Power of Veto Competition ("The Pickle Ball"), each HouseGuest must go head-to-head against another competitor. | H6: Wikipedia
A7: BB28 | B7: Week 4 | C7: HOH | D7: Jack The Ripper | E7: Haley | F7: 1 | G7: In the Head of Household competition ("Jack The Ripper"), HouseGuests are given five minutes to study six rooms before answering questions about the items they observed. | H7: Wikipedia
A8: BB28 | B8: Week 5 | C8: HOH | D8: Sasquatch Watch | E8: La Trice | F8: 1 | G8: In the Head of Household Competition ("Sasquatch Watch"), HouseGuest must hang on a tilting wall while being doused in water and slime. | H8: Wikipedia
A9: BB28 | B9: Week 5 | C9: Veto | D9: Saturday Night Veto | E9: (not tied to a winner) | G9: In the Veto Competition ("Saturday Night Veto"), HouseGuests must cross a bridge by stepping on one of two tiles that would highlight red or green. | H9: Wikipedia
A10: BB28 | B10: Week 6 | C10: HOH | D10: Bugs in the System | E10: (not tied to a winner) | G10: In the Head of Household competition ("Bugs in the System"), the HouseGuests face off head-to-head. | H10: Wikipedia
A11: BB28 | B11: Week 6 | C11: Veto | D11: OTEV the Belligerent B-Movie Slob | E11: (not tied to a winner) | G11: In the Veto Competition ("OTEV the Belligerent B-Movie Slob"), players must find and return the correct HouseGuest's name based on OTEV’s clues. | H11: Wikipedia
A12: BB28 | B12: Week 7 | C12: Veto | D12: Feel The Burn | E12: (not tied to a winner) | G12: They fear that "F.A.P." would take advantage of having the majority within the "Mosh Pit." In the Veto Competition ("Feel The Burn"), players must use various exercise machines to complete the most reps within a set time limit. | H12: Wikipedia
A13: BB28 | B13: Week 8 | C13: HOH | D13: 2026: A Zing Odyssey | E13: (not tied to a winner) | G13: In the Head of Household Competition ("2026: A Zing Odyssey"), the HouseGuests must answer a series of true-or-false questions, earning one point for each correct answer. | H13: Wikipedia
A14: BB28 | B14: Week 8 | C14: Veto | D14: The Gold, the Bad, and the Ugly | E14: Yash | F14: 1 | G14: In the Veto Competition ("The Gold, the Bad, and the Ugly"), the players must balance and transfer 25 gold nuggets using a seesaw shovel. | H14: Wikipedia
A15: BB28 | B15: Week 9 | C15: HOH | D15: Rainbow Rollers | E15: (not tied to a winner) | G15: The episode concluded with the HouseGuests beginning the ninth Head of Household competition, "Rainbow Rollers". | H15: Wikipedia
A16: BB28 | B16: Week 9 | C16: Veto | D16: BB Comics | E16: Yash | F16: 1 | G16: In the Veto Competition ("BB Comics"), players must zipline past a wall of superhero-themed comics, memorize their order, spot the differences, and recreate the correct sequence on their boards. | H16: Wikipedia
A17: BB28 | B17: Week 10 | C17: HOH | D17: Wet and Wild West | E17: (not tied to a winner) | G17: In the Head of Household Competition ("Wet and Wild West""), HouseGuests must catch water, fill a jar and retrieve at apple. | H17: Wikipedia
A18: BB28 | B18: Week 10 | C18: Veto | D18: Circle of Trust | E18: (not tied to a winner) | G18: In the Veto Competition ("Circle of Trust"), HouseGuests must stand on a spot whilst holding up a lie detector with their sword, with the last person standing winning the veto. | H18: Wikipedia
A19: BB28 | B19: Week 10 | C19: HOH | D19: Bleeping Through Time | E19: (not tied to a winner) | G19: Following Barrett’s eviction, Julie announces that it is double eviction, and the HouseGuests participate in the Head of Household Competition, ("Bleeping Through Time"). | H19: Wikipedia
A20: BB28 | B20: Week 10 | C20: Veto | D20: Great Ball of China | E20: Drew | F20: 1 | G20: In the Veto Competition ("Great Ball of China"), HouseGuests must first construct a wall puzzle and then roll a ball along it into a bin. | H20: Wikipedia
A21: BB28 | B21: Week 11 | C21: HOH | D21: Reverse the Curse | E21: Devens | F21: 1 | G21: In the Head of Household competition ("Reverse the Curse"), the HouseGuests must use tweezers to complete a miniature picture puzzle. | H21: Wikipedia
A22: BB28 | B22: Week 11 | C22: Veto | D22: Block Like an Egyptian | E22: (not tied to a winner) | G22: In the Veto Competition ("Block Like an Egyptian"), the players must traverse a booby-trapped course to deliver a mummified corpse to its coffin. | H22: Wikipedia
A23: BB28 | B23: Week 11 | C23: HOH | D23: Eternally Yours | E23: (not tied to a winner) | G23: In the Head of Household Competition ("Eternally Yours"), HouseGuests must correctly identify the missing player from a series of images before assembling a puzzle. | H23: Wikipedia
A24: BB28 | B24: Week 11 | C24: Veto | D24: Time Travel Toilet | E24: (not tied to a winner) | G24: In the Veto Competition ("Time Travel Toilet"), players must correctly identify the day displayed on the screen. | H24: Wikipedia
A25: BB28 | B25: Week 12 | C25: HOH | D25: To Be HoH or Not to Be | E25: (not tied to a winner) | G25: In Part 2 of the HoH competition, "To Be HoH or Not to Be", HouseGuests must correctly match the evicted players by knocking down their cutouts with a slingshot. | H25: Wikipedia
A26: BB27 | B26: Week 1 | C26: Veto | D26: Campsite Caper | E26: Ashley | F26: 1 | G26: Rachel and Zach are selected to join Amy, Ashley, Vince, and Zae in the "Campsite Caper" Veto competition. | H26: Wikipedia
A27: BB27 | B27: Week 3 | C27: HOH | D27: Twin Witness News | E27: Lauren | F27: 1 | G27: In the “Twin Witness News” Head of Household competition, HouseGuests must correctly answer a series of true-or-false questions based on events witnessed by former Big Brother 17 HouseGuests, Julia and Liz Nolan. | H27: Wikipedia
A28: BB27 | B28: Week 3 | C28: Veto | D28: Basement Break In | E28: Keanu | F28: 1 | G28: In the "Basement Break In" Power of Veto competition, players must retrieve a crystal through a laser maze in the shortest amount of time. | H28: Wikipedia
A29: BB27 | B29: Week 4 | C29: HOH | D29: Killer Carnival | E29: (not tied to a winner) | G29: In the three-round “Killer Carnival” Head of Household competition, HouseGuests begin in teams of four. | H29: Wikipedia
A30: BB27 | B30: Week 4 | C30: Veto | D30: Flee the Scene | E30: (not tied to a winner) | G30: In the "Flee the Scene" veto competition, HouseGuests must cross a bridge by stepping on one of two tiles that would highlight red or green. | H30: Wikipedia
A31: BB27 | B31: Week 5 | C31: HOH | D31: Jack the Dipper | E31: (not tied to a winner) | G31: In the "Jack the Dipper" Head of Household competition, HouseGuests face off head-to-head. | H31: Wikipedia
A32: BB27 | B32: Week 5 | C32: Veto | D32: Elusive Target | E32: (not tied to a winner) | G32: In the "Elusive Target" Veto competition, HouseGuests must slide a disk, aiming not to score the lowest each round. | H32: Wikipedia
A33: BB27 | B33: Week 6 | C33: HOH | D33: Party Slasher | E33: Rachel | F33: 1 | G33: In the “Party Slasher” Head of Household competition, HouseGuests are given five minutes to study six rooms before answering questions about the items they observed. | H33: Wikipedia
A34: BB27 | B34: Week 7 | C34: HOH | D34: Mystère Express | E34: (not tied to a winner) | G34: In the “Mystère Express” Head of Household competition, players hang on a tilting wall while being doused in water and slime. | H34: Wikipedia
A35: BB27 | B35: Week 7 | C35: Veto | D35: Wine to Die For | E35: (not tied to a winner) | G35: In the Veto competition, "Wine to Die For", players must randomly present two glasses of wine, one poisoned and one safe, to a chosen target, who must then guess which glass is safe. | H35: Wikipedia
A36: BB27 | B36: Week 8 | C36: HOH | D36: Mystère Moments | E36: Keanu | F36: 1 | G36: In the "Mystère Moments" HoH competition, players are tested with a series of True or False questions based on the video clips. | H36: Wikipedia
A37: BB27 | B37: Week 8 | C37: Veto | D37: Charcuterie Protection Agency | E37: Morgan | F37: 1 | G37: In the “Charcuterie Protection Agency” Power of Veto competition, hosted by Big Brother 26 contestant Angela Murray, players race to stack 35 variously sized charcuterie pieces in the fastest time. | H37: Wikipedia
A38: BB27 | B38: Week 9 | C38: Veto | D38: BB Comics | E38: Morgan | F38: 1 | G38: In the "BB Comics" veto competition, players must zipline past a wall of superhero-themed comics, memorize the order, and recreate the correct sequence on their boards. | H38: Wikipedia
A39: BB27 | B39: Week 10 | C39: HOH | D39: The Last Zing | E39: Vince | F39: 1 | G39: In the Head of Household competition, "The Last Zing", players must answer a series of true-or-false questions. | H39: Wikipedia
A40: BB27 | B40: Week 10 | C40: Veto | D40: BB CSI | E40: Morgan | F40: 1 | G40: In the "BB CSI" Veto competition, players must balance and transfer 25 pieces of evidence onto the lens of a giant magnifying glass. | H40: Wikipedia
A41: BB27 | B41: Week 10 | C41: HOH | D41: Wretched Reactor | E41: Morgan | F41: 2 | G41: In the "Wretched Reactor" Head of Household competition, HouseGuests must roll and land five balls at the top of a long ramp. | H41: Wikipedia
A42: BB27 | B42: Week 10 | C42: Veto | D42: Masterfind | E42: Keanu | F42: 2 | G42: In the "Masterfind" Veto competition, all HouseGuests must identify where the Mastermind is located on the screen, either A, B, or C. | H42: Wikipedia
A43: BB27 | B43: Week 11 | C43: HOH | D43: Torturous Trials | E43: Vince | F43: 1 | G43: In the "Torturous Trials" Head of Household competition, HouseGuests must hold the Mastermind’s mask with a sword, with the last player standing declared the winner. | H43: Wikipedia
A44: BB27 | B44: Week 11 | C44: HOH | D44: Forensi Scope | E44: (not tied to a winner) | G44: Immediately following Keanu's eviction, the HouseGuests begin the “Forensi Scope” Head of Household competition. | H44: Wikipedia
A45: BB27 | B45: Week 11 | C45: Veto | D45: Organized Crime | E45: Morgan | F45: 1 | G45: In the “Organized Crime” Power of Veto competition, players must correctly place major events from the season in chronological order according to the days they occurred. | H45: Wikipedia
A46: BB27 | B46: Week 12 | C46: HOH | D46: Unmask the Mastermind | E46: (not tied to a winner) | G46: Big Brother 16 HouseGuest Frankie Grande hosts Part 2 of the HoH competition, "Unmask the Mastermind," where HouseGuests must swing from a zipline to destroy three sets of blocks. | H46: Wikipedia
A47: BB26 | B47: Week 2 | C47: HOH | D47: Animal Obsession | E47: (not tied to a winner) | G47: In the "Animal Obsession" Head of Household competition, Houseguests viewed a series of videos containing animals. | H47: Wikipedia
A48: BB26 | B48: Week 4 | C48: HOH | D48: Bad A.I | E48: (not tied to a winner) | G48: In the "Bad A.I." Head of Household competition, Houseguests faced head-to-head two at a time and viewed three A.I. images of past Houseguests created by AINSLEY. | H48: Wikipedia
A49: BB26 | B49: Week 5 | C49: HOH | D49: Firewall | E49: (not tied to a winner) | G49: In the "Firewall" Head of Household competition, players had to assist AINSLEY in cooling down her "firewall" by holding onto a large wall while being tilted forward and blasted with water, and various attacks that took the format of liquid slime. | H49: Wikipedia
A50: BB26 | B50: Week 7 | C50: HOH | D50: What Came First | E50: Quinn | F50: 1 | G50: In the "What Came First" Head of Household competition, Quinn won. | H50: Wikipedia
A51: BB26 | B51: Week 8 | C51: HOH | D51: Before or After | E51: Chelsie | F51: 1 | G51: Houseguests competed in the "Before or After" Head of Household competition. | H51: Wikipedia
A52: BB26 | B52: Week 9 | C52: HOH | D52: Getting Toasted | E52: Leah | F52: 1 | G52: In the "Getting Toasted" Head of Household competition, Leah emerged victorious after 9 hours and 55 minutes. | H52: Wikipedia
A53: BB26 | B53: Week 10 | C53: HOH | D53: Eye Candy | E53: Makensy | F53: 1 | G53: In the "Eye Candy" Head of Household competition, Makensy emerged as the winner. | H53: Wikipedia
A54: BB26 | B54: Week 10 | C54: Veto | D54: Wild Robot | E54: Makensy | F54: 1 | G54: Makensy won the "Wild Robot" Power of Veto competition, sponsored by the DreamWorks Animation film, The Wild Robot, which also doubled as a Luxury Competition; Makensy not only received the Golden Power of Veto, but also won the chance to watch a special advanced screening of The Wild Robot with three other Houseguests, which she invited Cam, Kimo and Rubina to join. | H54: Wikipedia
A55: BB26 | B55: Week 10 | C55: HOH | D55: Warning Messages | E55: Chelsie | F55: 2 | G55: In the "Warning Messages" Head of Household competition, Chelsie won on a tiebreaker. | H55: Wikipedia
A56: BB26 | B56: Week 10 | C56: Veto | D56: Eye in the Sky | E56: Kimo | F56: 2 | G56: Then, all of the six remaining Houseguests got to compete in the "Eye in the Sky" Power of Veto competition, which Kimo won. | H56: Wikipedia
A57: BB26 | B57: Week 11 | C57: HOH | D57: Tiny Stack | E57: Makensy | F57: 1 | G57: Afterwards, Houseguests compete in the "Tiny Stack" Head of Household competition which Makensy won. | H57: Wikipedia
A58: BB26 | B58: Week 12 | C58: HOH | D58: Hidden Agenda | E58: Chelsie | F58: 1 | G58: In the "Hidden Agenda" Head of Household competition, Chelsie emerged as the winner. | H58: Wikipedia
A59: BB26 | B59: Week 12 | C59: Veto | D59: Passcode Protectors | E59: Makensy | F59: 1 | G59: In the "Passcode Protectors" Power of Veto competition, the Final Four Houseguests competed in a knockout format. | H59: Wikipedia
A60: BB25 | B60: Week 7 | C60: HOH | D60: The Wall | E60: Jared | F60: 1 | G60: Jared wins "The Wall" HOH competition and elects to nominate Cory and America for eviction. | H60: Wikipedia
A61: BB25 | B61: Week 7 | C61: Veto | D61: Sweaty Scrimmage | E61: Jag | F61: 1 | G61: Jag wins the "Sweaty Scrimmage" veto competition and decides to use the veto on Cory. | H61: Wikipedia
... A65: BB25 | B65: Week 9 | C65: Veto | D65: BB Exorcism | E65: Cameron | F65: 1 | G65: America, Blue, Cameron, Felicia, Matt, and Mecole take part in the "BB Exorcism" veto competition which Cameron wins. | H65: Wikipedia
A66: BB25 | B66: Week 9 | C66: HOH | D66: Humiligram | E66: (not tied to a winner) | G66: Houseguests then complete in the live "Humiligram" HOH competition which Bowie Jane wins. | H66: Wikipedia
A67: BB25 | B67: Week 11 | C67: HOH | D67: BB Comics | E67: Jag | F67: 1 | G67: Houseguests then compete in "BB Comics" HOH competition and are informed that the winning time was 8 minutes and 30 seconds. | H67: Wikipedia
A68: BB25 | B68: Week 12 | C68: HOH | D68: Demented Dentist | E68: Jag | F68: 1 | G68: Houseguests compete in the "Demented Dentist" HOH competition, which Jag wins. | H68: Wikipedia
A69: BB25 | B69: Week 12 | C69: Veto | D69: Embrassaing Expedition | E69: Jag | F69: 1 | G69: Jag, Blue, America, Matt, Bowie, and Felicia compete in the "Embrassaing Expedition" veto competition which Jag wins. | H69: Wikipedia
A70: BB25 | B70: Week 13 | C70: HOH | D70: Superhero Smackdown | E70: Matt | F70: 1 | G70: At the "Superhero Smackdown" HOH competition Matt emerges victorious. | H70: Wikipedia
A71: BB24 | B71: Week 2 | C71: Veto | D71: Mermaid Fest | E71: Michael | F71: 1 | G71: In the "Mermaid Fest" Power of Veto competition the competitors, dressed as mermaids, used their heads to push a pearl over a series of ramps, and then into a hole at the end of a bowling lane. | H71: Wikipedia
A72: BB24 | B72: Week 5 | C72: Veto | D72: Get My Sauce | E72: Michael | F72: 1 | G72: OTEV is back for the Veto competition: Get My Sauce. | H72: Wikipedia
A73: BB24 | B73: Week 7 | C73: Veto | D73: One, Two, Three, VIP | E73: Brittany | F73: 1 | G73: Tiffany from Big Brother 23 returned to host the Big BroChella Veto Competition, "One, Two, Three, VIP", which was an iteration of "Stay of Fold". | H73: Wikipedia
A74: BB24 | B74: Week 7 | C74: Veto | D74: Lunch is Served | E74: Terrance | F74: 2 | G74: The Dyre Fest attendees set up and competed in the Veto competition "Lunch is Served", which required the houseguests to transport 50 styrofoam containers from the start to their platform without dropping any. | H74: Wikipedia
A75: BB24 | B75: Week 8 | C75: HOH | D75: Carni-Small | E75: Turner | F75: 1 | G75: The Head of Household Competition "Carni-Small", the houseguests had to stack 21 mini energy drinks in a specific order. | H75: Wikipedia
A76: BB24 | B76: Week 9 | C76: Veto | D76: Amp it Up | E76: (not tied to a winner) | G76: All of the houseguests compete in the Power of Veto competition, called "Amp it Up". | H76: Wikipedia
A77: BB24 | B77: Week 10 | C77: HOH | D77: Horror Fest Lockdown | E77: Monte | F77: 1 | G77: In the HOH competition, "Horror Fest Lockdown", the players had to block six doors in complete darkness in the fastest time. | H77: Wikipedia
A78: BB23 | B78: Week 1 | C78: HOH | D78: House of Cards | E78: (not tied to a winner) | G78: After teams were picked, HouseGuests competed in the "House of Cards" HoH competition. | H78: Wikipedia
A79: BB23 | B79: Week 1 | C79: HOH | D79: Pool Sharks | E79: (not tied to a winner) | G79: The remaining HouseGuests then competed in the next HoH competition, "Pool Sharks". | H79: Wikipedia
A80: BB23 | B80: Week 2 | C80: Veto | D80: Fun Tan Lotion | E80: Derek X. | F80: 1 | G80: On Day 11, Alyssa, Claire and Derek X. were randomly selected to participate alongside Kyland, Britini and Frenchie in the "Fun Tan Lotion" PoV competition. | H80: Wikipedia
A81: BB23 | B81: Week 2 | C81: HOH | D81: Tom Talks BB | E81: (not tied to a winner) | G81: Following this, HouseGuests competed in the "Tom Talks BB" HoH competition. | H81: Wikipedia
A82: BB23 | B82: Week 3 | C82: Veto | D82: Room Key Rumble | E82: Christian | F82: 1 | G82: On Day 18, Christian (Xavier's choice), Derek F. and Whitney were selected to participate alongside Xavier, Brent and Britini in the "Room Key Rumble" PoV competition. | H82: Wikipedia
A83: BB23 | B83: Week 3 | C83: HOH | D83: Pier Pressure | E83: (not tied to a winner) | G83: The HouseGuests then competed in the HoH competition called "Pier Pressure". | H83: Wikipedia
A84: BB23 | B84: Week 4 | C84: Veto | D84: Bump, Set, Veto | E84: Christian | F84: 1 | G84: On Day 25, Claire, Derek X. (Hannah's choice) and Azah were selected to compete alongside Christian, Hannah and Whitney in the PoV competition, "Bump, Set, Veto". | H84: Wikipedia
A85: BB23 | B85: Week 5 | C85: Veto | D85: Kingdom of Curl-a-Lot | E85: Britini | F85: 1 | G85: In the "Kingdom of Curl-a-Lot" veto competition, Sarah Beth loses the second round by one rep to Britini and was criticised for keeping the $5,000 prize instead of swapping it for the veto. | H85: Wikipedia
A86: BB23 | B86: Week 6 | C86: HOH | D86: Name That Croon | E86: Kyland | F86: 1 | G86: The HouseGuests competed in an elimination-style HoH competition called "Name That Croon" where they had to identify if former competitions were HoH, PoV, or Wildcard. | H86: Wikipedia
A87: BB23 | B87: Week 8 | C87: Veto | D87: BB High School Hijinks | E87: Hannah | F87: 1 | G87: In the veto competition called "BB High School Hijinks," the HouseGuests had to arrange a series of photos in the correct order based on clues within the images that indicated the correct sequence of events. | H87: Wikipedia
A88: BB23 | B88: Week 8 | C88: HOH | D88: The Flying BB-inos | E88: (not tied to a winner) | G88: The HouseGuests began the next HoH competition called "The Flying BB-inos" where they had to stand on a suspended disc while holding onto a rope for as long as possible. | H88: Wikipedia
A89: BB23 | B89: Week 9 | C89: Veto | D89: Micro Cocktails | E89: Alyssa | F89: 1 | G89: In the veto competition called "Micro Cocktails," players used tweezers to stack 21 miniature cocktail glasses into a pyramid. | H89: Wikipedia
A90: BB23 | B90: Week 9 | C90: HOH | D90: Crash, Boom, Pow | E90: Hannah | F90: 2 | G90: In the HoH competition called "Crash, Boom, Pow" HouseGuests were shown images depicting classic comic book phrases and had to answer questions using tiles containing the phrases shown. | H90: Wikipedia
A91: BB23 | B91: Week 9 | C91: Veto | D91: Logo, Let's Go | E91: Xavier | F91: 2 | G91: All HouseGuests except for Kyland were picked to play in the PoV competition called "Logo, Let's Go" in which players had to race to complete their BB Comics puzzle and hit a buzzer. | H91: Wikipedia
A92: BB23 | B92: Week 10 | C92: HOH | D92: BB Ballers | E92: Azah | F92: 2 | G92: In the HoH competition called "BB Ballers" the remaining HouseGuests had to roll small balls up a ramp to knock twelve larger balls off the grass at the end and hit a buzzer. | H92: Wikipedia
A93: BB23 | B93: Week 10 | C93: Veto | D93: What the Bleep | E93: Kyland | F93: 1 | G93: In the "What the Bleep" PoV competition, the HouseGuests watched clips of their former housemates with bleeped out phrases, and they had to answer true/false questions about the missing words. | H93: Wikipedia
A94: BB23 | B94: Week 12 | C94: HOH | D94: Bouncy Boat Bash | E94: Xavier | F94: 1 | G94: In Part 1 of the final HoH competition called "Bouncy Boat Bash" the HouseGuests had to hold on to a suspended boat for as long as possible. | H94: Wikipedia
A95: BB22 | B95: Week 1 | C95: Veto | D95: Going Bananas | E95: (not tied to a winner) | G95: Power of Veto Competition ("Going Bananas"): Contestants had to rock back and forth on a giant banana to earn 90 seconds to stack the most fruit cutouts they can on a stand. | H95: Wikipedia
A96: BB22 | B96: Week 1 | C96: HOH | D96: A Big Brother Watch Party | E96: (not tied to a winner) | G96: Head of Household Competition ("A Big Brother Watch Party"): The houseguests watched a short video skit of a dysfunctional family's video chat Big Brother watch party. | H96: Wikipedia
A97: BB22 | B97: Week 2 | C97: Veto | D97: All Starry Night | E97: (not tied to a winner) | G97: Power of Veto Competition ("All Starry Night"): Houseguests have to stand on a slanted surface and hold a ball steady on a flat surface held out in front of them. | H97: Wikipedia
A98: BB22 | B98: Week 2 | C98: HOH | D98: Mug Shot | E98: (not tied to a winner) | G98: Head of Household Competition ("Mug Shot"): Each Houseguest must push the mugs to the nearest target possible and get most points as they can. | H98: Wikipedia
A99: BB22 | B99: Week 3 | C99: Veto | D99: Cupcake Clash | E99: (not tied to a winner) | G99: Power Veto Competition: ("Cupcake Clash") HouseGuests competed head-to-head in a randomly drawn tournament to sort out three cupcakes in a Tower of Hanoi pattern. | H99: Wikipedia
A100: BB22 | B100: Week 3 | C100: HOH | D100: Carnival Quick Shot | E100: (not tied to a winner) | G100: Head of Household Competition: ("Carnival Quick Shot") Houseguests are split into two different groups for this competition. | H100: Wikipedia
A101: BB22 | B101: Week 4 | C101: HOH | D101: Carnival Quick Shot | E101: Enzo | F101: 1 | G101: Head of Household Competition: ("Carnival Quick Shot") Continuing from the live eviction night on Thursday, the competition was played out to reveal the six winners from the first round, who competed in the final round to determine HOH. | H101: Wikipedia
A102: BB22 | B102: Week 4 | C102: Veto | D102: Face the Puppetmaster | E102: (not tied to a winner) | G102: Power of Veto Competition: ("Face the Puppetmaster") HouseGuests had to hold on to four ropes, one for each arm and leg and stay there as the ropes were pulled all around. | H102: Wikipedia
A103: BB22 | B103: Week 4 | C103: HOH | D103: Filter Faceoff | E103: (not tied to a winner) | G103: Head of Household Competition: ("Filter Faceoff") Houseguests competed in head-to-head rounds and were shown pictures from the Memory Wall, with different filters applied to the Houseguests' faces every round. | H103: Wikipedia
...

Sheet BB Wiki comps
A1: Season | B1: Week | C1: Day | D1: Type | E1: Competition | F1: Format | G1: Category | H1: Result | I1: Round | J1: Source | K1: Looks right? | L1: Correction
A2: BB28 | B2: Week 1 | C2: 1 | D2: Immunity | E2: Find the BB-tonium | F2: Reclaim the Relic | H2: Ashley & Barrett fail to advance | J2: BB Wiki
A3: BB28 | B3: Week 1 | C3: 1 | D3: Immunity | E3: 1988 Long Beach, CA | F3: In The Balance | H3: Rome wins Safety | J3: BB Wiki
A4: BB28 | B4: Week 1 | C4: 1 | D4: Immunity | E4: 2018 Fiji | F4: Build the Bridge | H4: Chuk wins Safety | J4: BB Wiki
A5: BB28 | B5: Week 1 | C5: 1 | D5: Immunity | E5: 2010 Las Vegas, NV | F5: Sequence Explosion | H5: Jason wins Safety | J5: BB Wiki
A6: BB28 | B6: Week 1 | C6: 1 | D6: HOH | E6: 175 Million BC | F6: Pyramid | G6: Endurance | H6: Dee wins HOH | I6: 1 | J6: BB Wiki
A7: BB28 | B7: Week 1 | C7: 5 | D7: POV | E7: Back From the Future | F7: Pipeline | G7: Puzzle | H7: Mallory wins the Veto | I7: 1 | J7: BB Wiki
A8: BB28 | B8: Week 1 | C8: 10 | D8: Block Buster | E8: Do Over | F8: Living Art | H8: Yash is saved | J8: BB Wiki
A9: BB28 | B9: Week 2 | C9: 10 | D9: HOH | E9: Achy Breaky HOH | F9: Shootout | G9: Skill | H9: Devens wins HOH | I9: 1 | J9: BB Wiki
A10: BB28 | B10: Week 2 | C10: 11 | D10: Time Capsule | H10: Angela is punished | J10: BB Wiki
A11: BB28 | B11: Week 2 | C11: 12 | D11: POV | E11: Flower Power | F11: Fitting In | G11: Puzzle | H11: Devens wins the Veto | I11: 1 | J11: BB Wiki
A12: BB28 | B12: Week 2 | C12: 17 | D12: Block Buster | E12: Pirate's Booty | F12: Tower of Hanoi | H12: Jason is saved | J12: BB Wiki
A13: BB28 | B13: Week 3 | C13: 17 | D13: HOH | E13: Wrestlegasm 85 | F13: What Did They Just Do? | G13: Mental | H13: Kamu wins HOH | I13: 1 | J13: BB Wiki
A14: BB28 | B14: Week 3 | C14: 18 | D14: Time Capsule | H14: Devens is rewarded | J14: BB Wiki
A15: BB28 | B15: Week 3 | C15: 19 | D15: POV | E15: The Pickle Ball | F15: Bowlerina | G15: Skill | H15: Lyric wins the Veto | I15: 1 | J15: BB Wiki
A16: BB28 | B16: Week 3 | C16: 24 | D16: Block Buster | E16: Video Tape Tumble | H16: Mallory is saved | J16: BB Wiki
A17: BB28 | B17: Week 4 | C17: 24 | D17: HOH | E17: Jack the Ripper | F17: Hide and Seek | G17: Mental | H17: Haley wins HOH | I17: 1 | J17: BB Wiki
A18: BB28 | B18: Week 4 | C18: 25 | D18: Time Capsule | H18: Dee is rewarded | J18: BB Wiki
A19: BB28 | B19: Week 4 | C19: 26 | D19: POV | E19: Murder at the Masquerade | F19: To Drink or to Bluff | G19: Crapshoot | H19: Taylor wins the Veto | I19: 1 | J19: BB Wiki
A20: BB28 | B20: Week 4 | C20: 31 | D20: Block Buster | E20: The Paw Patrol Dino Puzzle | F20: Fitting In | H20: Drew is saved | J20: BB Wiki
A21: BB28 | B21: Week 5 | C21: 31 | D21: HOH | E21: Sasquatch Watch | F21: The Wall | G21: Endurance | H21: La Trice wins HOH | I21: 1 | J21: BB Wiki
A22: BB28 | B22: Week 5 | C22: 32 | D22: Time Capsule | H22: Mallory is punished | J22: BB Wiki
A23: BB28 | B23: Week 5 | C23: 33 | D23: POV | E23: Saturday Night Veto | F23: Binary Bridge | G23: Crapshoot | H23: Kamu wins the Veto | I23: 1 | J23: BB Wiki
A24: BB28 | B24: Week 5 | C24: 38 | D24: Block Buster | E24: Newton's Apples | F24: Carnival Quick Shot | H24: Haley is saved | J24: BB Wiki
A25: BB28 | B25: Week 6 | C25: 38 | D25: HOH | E25: Bugs in the System | F25: Knockout | G25: Mental | H25: Yash wins HOH | I25: 1 | J25: BB Wiki
A26: BB28 | B26: Week 6 | C26: 39 | D26: Time Capsule | H26: Melody is punished | J26: BB Wiki
A27: BB28 | B27: Week 6 | C27: 40 | D27: POV | E27: OTEV the Belligerent B-Movie Blob | F27: OTEV | G27: Hybrid | H27: Yash wins the Veto | I27: 1 | J27: BB Wiki
A28: BB28 | B28: Week 6 | C28: 45 | D28: Block Buster | E28: Space Race | F28: Niagara Balls | H28: Angela is saved | J28: BB Wiki
A29: BB28 | B29: Week 7 | C29: 45 | D29: HOH | E29: Norse By Norsewest | F29: Only One Path | G29: Physical | H29: Dee wins HOH | I29: 1 | J29: BB Wiki
A30: BB28 | B30: Week 7 | C30: 46 | D30: Time Capsule | H30: Drew is rewarded | J30: BB Wiki
A31: BB28 | B31: Week 7 | C31: 47 | D31: POV | E31: Feel The Burn | G31: Physical | H31: La Trice wins the Veto | I31: 1 | J31: BB Wiki
A32: BB28 | B32: Week 7 | C32: 52 | D32: Block Buster | E32: BB Grand Cliptacular | F32: Getting Loopy | H32: Drew is saved | J32: BB Wiki
A33: BB28 | B33: Week 8 | C33: 52-53 | D33: Immunity | E33: Stones of Safety | F33: In The Balance | H33: Dee wins Safety | J33: BB Wiki
A34: BB28 | B34: Week 8 | C34: 52-53 | D34: Hit The Road | E34: Fit the Crops | F34: Kaitlyn's Puzzle | H34: Drew wins Safety | J34: BB Wiki
A35: BB28 | B35: Week 8 | C35: 52-53 | D35: Hit The Road | E35: Deliver the Grapes | F35: Berry Balanced | H35: Barrett wins Safety | J35: BB Wiki
A36: BB28 | B36: Week 8 | C36: 52-53 | D36: Hit The Road | E36: Adorn the Crown | F36: Hourglass | H36: Yash wins Safety | J36: BB Wiki
A37: BB28 | B37: Week 8 | C37: 53 | D37: HOH | E37: 2026: A Zing Odyssey | F37: Zingbot Competition | G37: Mental | H37: Drew wins HOH | I37: 1 | J37: BB Wiki
A38: BB28 | B38: Week 8 | C38: 54 | D38: POV | E38: The Gold, the Bad, and the Ugly | F38: Seesaw | G38: Physical | H38: Yash wins the Veto | I38: 1 | J38: BB Wiki
A39: BB28 | B39: Week 8 | C39: 59 | D39: Block Buster | E39: Your Game in Ruins | F39: Big Top Drop | H39: Devens is saved | J39: BB Wiki
A40: BB28 | B40: Week 9 | C40: 59 | D40: HOH | E40: Rainbow Rollers | F40: Perfect Shot | G40: Skill | H40: Barrett wins HOH | I40: 1 | J40: BB Wiki
A41: BB28 | B41: Week 9 | C41: 61 | D41: POV | E41: BB Comics | G41: Hybrid | H41: Yash wins the Veto | I41: 1 | J41: BB Wiki
A42: BB28 | B42: Week 9 | C42: 66 | D42: Block Buster | E42: Reinvent The Wheel | F42: Kaitlyn's Puzzle | H42: Devens is saved | J42: BB Wiki
A43: BB28 | B43: Week 10 | C43: 66 | D43: HOH | E43: Wet and Wild West | F43: Slippery Slope | G43: Physical | H43: Yash wins HOH | I43: 1 | J43: BB Wiki
A44: BB28 | B44: Week 10 | C44: 68 | D44: POV | E44: Circle of Trust | F44: What's The Hold Up | G44: Endurance | H44: Drew wins the Veto | I44: 1 | J44: BB Wiki
A45: BB28 | B45: Week 10 | C45: 73 | D45: Block Buster | E45: Crash Site Cover-Up | F45: Roll It Down | H45: Melody is saved | J45: BB Wiki
A46: BB28 | B46: Week 10 | C46: 73 | D46: HOH | E46: Bleeping Through Time | F46: What The Bleep? | G46: Mental | H46: Melody wins HOH | I46: 2 | J46: BB Wiki
A47: BB28 | B47: Week 10 | C47: 73 | D47: POV | E47: Great Ball of China | F47: Fitting In | G47: Puzzle | H47: Devens wins the Veto | I47: 2 | J47: BB Wiki
A48: BB28 | B48: Week 11 | C48: 74 | D48: Temptation | E48: The Pharaoh's Treasure | H48: Devens wins $10,000 | J48: BB Wiki
A49: BB28 | B49: Week 11 | C49: 74 | D49: HOH | E49: Reverse the Curse | F49: Microbrews | G49: Skill | H49: Devens wins HOH | I49: 1 | J49: BB Wiki
A50: BB28 | B50: Week 11 | C50: 75 | D50: POV | E50: Block Like an Egyptian | F50: Laser Maze | G50: Physical | H50: Drew wins the Veto | I50: 1 | J50: BB Wiki
A51: BB28 | B51: Week 11 | C51: 77 | D51: HOH | E51: Eternally Yours | F51: Starting Lineup | G51: Puzzle | H51: Taylor wins HOH | I51: 2 | J51: BB Wiki
A52: BB28 | B52: Week 11 | C52: 78 | D52: POV | E52: Time Travel Toilet | F52: Cover Your Days | G52: Mental | H52: Drew wins the Veto | I52: 2 | J52: BB Wiki
A53: BB28 | B53: Week 12 | C53: 80 | D53: HOH | E53: Shock and Roll | F53: Log Roll | G53: Endurance | H53: Taylor wins HOH Part 1 | J53: BB Wiki
A54: BB28 | B54: Week 12 | C54: 81 | D54: HOH | E54: To Be HOH or Not to Be HOH | F54: Who Did What? | G54: Mental | H54: Devens wins HOH Part 2 | J54: BB Wiki
A55: BB28 | B55: Week 12 | C55: 87 | D55: HOH | E55: Back In My Day | F55: Jury Statements | G55: Mental | H55: Devens wins HOH Part 3 | J55: BB Wiki
A56: BB27 | B56: Week 1 | C56: 1 | D56: Advantage (BB Buy-Off) | E56: Save Julie | F56: Build the Bridge | H56: Zach wins a Power | J56: BB Wiki
A57: BB27 | B57: Week 1 | C57: 1 | D57: Advantage (Comp Selection) | E57: Reclaim the Relic | H57: Jimmy wins a Power | J57: BB Wiki
A58: BB27 | B58: Week 1 | C58: 1 | D58: HOH | E58: Destroy the Lair | F58: In The Balance | G58: Skill | H58: Vince wins HOH | I58: 1 | J58: BB Wiki
A59: BB27 | B59: Week 1 | C59: 5 | D59: POV | E59: Campsite Caper | F59: HouseguestsOnly.com | G59: Mental | H59: Ashley wins the Veto | I59: 1 | J59: BB Wiki
A60: BB27 | B60: Week 1 | C60: 10 | D60: Block Buster | E60: Ransom Note | F60: Digital Decryption | H60: Kelley is saved | J60: BB Wiki
A61: BB27 | B61: Week 2 | C61: 10 | D61: HOH | E61: BB Break In | F61: The Black Box | G61: Physical | H61: Jimmy wins HOH | I61: 1 | J61: BB Wiki
A62: BB27 | B62: Week 2 | C62: 10 | D62: Advantage (Mystery Competitor) | E62: BB Break In | F62: The Black Box | H62: Keanu wins a Power | J62: BB Wiki
A63: BB27 | B63: Week 2 | C63: 10 | D63: Advantage (Mystery Veto) | E63: BB Break In | F63: The Black Box | H63: Kelley wins a Power | J63: BB Wiki
A64: BB27 | B64: Week 2 | C64: 10 | D64: Advantage (HOH Interrogation) | E64: BB Break In | F64: The Black Box | H64: Mickey wins a Power | J64: BB Wiki
A65: BB27 | B65: Week 2 | C65: 12 | D65: POV | E65: Caught Creepin | F65: Ready, Set, Woah | G65: Physical | H65: Keanu is awarded the Veto | I65: 1 | J65: BB Wiki
A66: BB27 | B66: Week 2 | C66: 14 | D66: Mystery POV | E66: The Case of the Mystery Veto | F66: Kaitlyn's Puzzle | G66: Puzzle | H66: Kelley wins the Mystery Veto | I66: 1 | J66: BB Wiki
A67: BB27 | B67: Week 2 | C67: 17 | D67: Block Buster | E67: Puzzling Prints | F67: Fitting In | H67: Adrian is saved | J67: BB Wiki
A68: BB27 | B68: Week 3 | C68: 17 | D68: HOH | E68: Twin Witness News | F68: What Did They Just Do? | G68: Mental | H68: Lauren wins HOH | I68: 1 | J68: BB Wiki
A69: BB27 | B69: Week 3 | C69: 19 | D69: POV | E69: Basement Break In | F69: Laser Maze | G69: Physical | H69: Keanu wins the Veto | I69: 1 | J69: BB Wiki
A70: BB27 | B70: Week 3 | C70: 24 | D70: Block Buster | E70: Study The Study | F70: Living Art | H70: Kelley is saved | J70: BB Wiki
A71: BB27 | B71: Week 4 | C71: 24 | D71: HOH | E71: Killer Carnival | F71: Only One Path | G71: Physical | H71: Rylie wins HOH | I71: 1 | J71: BB Wiki
A72: BB27 | B72: Week 4 | C72: 26 | D72: POV | E72: Flee the Scene | F72: Binary Bridge | G72: Crapshoot | H72: Keanu wins the Veto | I72: 1 | J72: BB Wiki
A73: BB27 | B73: Week 4 | C73: 31 | D73: Block Buster | E73: Safe Crackers | F73: Roll It Down | H73: Rylie is saved | J73: BB Wiki
A74: BB27 | B74: Week 5 | C74: 31 | D74: HOH | E74: Jack the Dipper | F74: Knockout | G74: Mental | H74: Ava wins HOH | I74: 1 | J74: BB Wiki
A75: BB27 | B75: Week 5 | C75: 33 | D75: POV | E75: Elusive Target | F75: Shootout | G75: Skill | H75: Katherine wins the Veto | I75: 1 | J75: BB Wiki
A76: BB27 | B76: Week 5 | C76: 38 | D76: Block Buster | E76: Jumbo Gemstones | F76: Tower of Hanoi | H76: Keanu is saved | J76: BB Wiki
A77: BB27 | B77: Week 6 | C77: 38 | D77: HOH | E77: The Party Slasher | F77: Hide and Seek | G77: Mental | H77: Rachel wins HOH | I77: 1 | J77: BB Wiki
A78: BB27 | B78: Week 6 | C78: 40 | D78: POV | E78: OTEV the Hog Father | F78: OTEV | G78: Hybrid | H78: Lauren wins the Veto | I78: 1 | J78: BB Wiki
A79: BB27 | B79: Week 6 | C79: 45 | D79: Block Buster | E79: Settle the Score | F79: Perfect Shot | H79: Mickey is saved | J79: BB Wiki
A80: BB27 | B80: Week 7 | C80: 45 | D80: HOH | E80: Mystere Express | F80: The Wall | G80: Endurance | H80: Vince wins HOH | I80: 1 | J80: BB Wiki
A81: BB27 | B81: Week 7 | C81: 47 | D81: POV | E81: Wine to Die For | F81: To Drink or to Bluff | G81: Crapshoot | H81: Mickey wins the Veto | I81: 1 | J81: BB Wiki
A82: BB27 | B82: Week 7 | C82: 52 | D82: Block Buster | E82: Hilltop Heist | F82: Block and Roll | H82: Kelley is saved | J82: BB Wiki
A83: BB27 | B83: Week 8 | C83: 52 | D83: HOH | E83: Mystere Moments | F83: Getting Loopy | G83: Mental | H83: Keanu wins HOH | I83: 1 | J83: BB Wiki
A84: BB27 | B84: Week 8 | C84: 54 | D84: POV | E84: Charcuterie Protection Agency | F84: Hourglass | G84: Skill | H84: Morgan wins the Veto | I84: 1 | J84: BB Wiki
A85: BB27 | B85: Week 8 | C85: 59 | D85: Block Buster | E85: Forensic Frenzy | F85: Niagara Balls | H85: Vince is saved | J85: BB Wiki
A86: BB27 | B86: Week 9 | C86: 59 | D86: Immunity | E86: Survive the White Locust | F86: As Close As You Can | H86: Ava wins Safety | J86: BB Wiki
A87: BB27 | B87: Week 9 | C87: 59-60 | D87: Hit The Road/HOH | E87: Mastermind's Maniacal Maze | F87: Item Maze | G87: Skill | H87: Rachel is evicted | J87: BB Wiki
A88: BB27 | B88: Week 9 | C88: 59-60 | D88: Hit The Road/HOH | E88: Mastermind's Maniacal Maze | F88: Item Maze | G88: Skill | H88: Lauren wins HOH | I88: 1 | J88: BB Wiki
A89: BB27 | B89: Week 9 | C89: 61 | D89: POV | E89: BB Comics | G89: Hybrid | H89: Morgan wins the Veto | I89: 1 | J89: BB Wiki
A90: BB27 | B90: Week 9 | C90: 66 | D90: Block Buster | E90: Key to Safety | F90: Feeling Knotty | H90: Keanu is saved | J90: BB Wiki
A91: BB27 | B91: Week 10 | C91: 66 | D91: HOH | E91: The Last Zing: The True Story of Zingbot's Demise | F91: Zingbot Competition | G91: Mental | H91: Vince wins HOH | I91: 1 | J91: BB Wiki
A92: BB27 | B92: Week 10 | C92: 68 | D92: POV | E92: BB CSI | F92: Seesaw | G92: Physical | H92: Morgan wins the Veto | I92: 1 | J92: BB Wiki
A93: BB27 | B93: Week 10 | C93: 73 | D93: Block Buster | E93: Steal Power Orbs for the Mastermind So He Can Bring His Lair On-Line | F93: Big Top Drop | H93: Lauren is saved | J93: BB Wiki
A94: BB27 | B94: Week 10 | C94: 73 | D94: HOH | E94: Wretched Reactor | F94: Carnival Quick Shot | G94: Skill | H94: Morgan wins HOH | I94: 2 | J94: BB Wiki
A95: BB27 | B95: Week 10 | C95: 73 | D95: POV | E95: Masterfind | F95: What Did They Just Do? | G95: Mental | H95: Keanu wins the Veto | I95: 2 | J95: BB Wiki
A96: BB27 | B96: Week 11 | C96: 73 | D96: HOH | E96: Torturous Trial | F96: What's The Hold Up | G96: Endurance | H96: Vince wins HOH | I96: 1 | J96: BB Wiki
A97: BB27 | B97: Week 11 | C97: 74 | D97: POV | E97: Masterpieces | F97: Microbrews | G97: Skill | H97: Morgan wins the Veto | I97: 1 | J97: BB Wiki
A98: BB27 | B98: Week 11 | C98: 77 | D98: HOH | E98: ForensiScope | F98: Tumblin' Dice | G98: Physical | H98: Morgan wins HOH | I98: 2 | J98: BB Wiki
A99: BB27 | B99: Week 11 | C99: 78 | D99: POV | E99: Organized Crime | F99: Cover Your Days | G99: Mental | H99: Morgan wins the Veto | I99: 2 | J99: BB Wiki
A100: BB27 | B100: Week 12 | C100: 80 | D100: HOH | E100: Locate the Lair | F100: Jetpack Attack | G100: Endurance | H100: Morgan wins HOH Part 1 | J100: BB Wiki
...

Sheet Have-Nots
A1: Season | B1: Week | C1: Have-Not | D1: Made a Have-Not by | E1: Source | F1: Looks right? | G1: Correction
A2: BB28 | B2: Week 1 | C2: Devens | E2: BB Wiki
A3: BB28 | B3: Week 1 | C3: Drew | E3: BB Wiki
A4: BB28 | B4: Week 1 | C4: Taylor | E4: BB Wiki
A5: BB28 | B5: Week 1 | C5: Haley | E5: BB Wiki
A6: BB28 | B6: Week 1 | C6: Chuk | E6: BB Wiki
A7: BB28 | B7: Week 2 | C7: Barrett | E7: BB Wiki
A8: BB28 | B8: Week 2 | C8: Kamu | E8: BB Wiki
A9: BB28 | B9: Week 2 | C9: Lyric | E9: BB Wiki
A10: BB28 | B10: Week 2 | C10: Jason | E10: BB Wiki
A11: BB28 | B11: Week 2 | C11: Rome | E11: BB Wiki
A12: BB28 | B12: Week 3 | C12: Dee | E12: BB Wiki
A13: BB28 | B13: Week 3 | C13: Melody | E13: BB Wiki
... A30: BB28 | B30: Week 10 | C30: Devens | E30: BB Wiki
A31: BB27 | B31: Week 1 | C31: Ava | D31: Zach | E31: BB Wiki
A32: BB27 | B32: Week 1 | C32: Rachel | E32: BB Wiki
A33: BB27 | B33: Week 1 | C33: Will | D33: Rachel | E33: BB Wiki
A34: BB27 | B34: Week 1 | C34: Zach | D34: Will | E34: BB Wiki
A35: BB27 | B35: Week 2 | C35: Mickey | E35: BB Wiki
A36: BB27 | B36: Week 2 | C36: Rachel | E36: BB Wiki
A37: BB27 | B37: Week 2 | C37: Amy | E37: BB Wiki
A38: BB27 | B38: Week 3 | C38: Katherine | D38: Rachel | E38: BB Wiki
A39: BB27 | B39: Week 3 | C39: Jimmy | D39: Mickey | E39: BB Wiki
A40: BB27 | B40: Week 7 | C40: Ashley | E40: BB Wiki
A41: BB27 | B41: Week 7 | C41: Morgan | E41: BB Wiki
A42: BB27 | B42: Week 7 | C42: Will | E42: BB Wiki
A43: BB27 | B43: Week 8 | C43: Ava | D43: Ashley | E43: BB Wiki
A44: BB27 | B44: Week 8 | C44: Lauren | D44: Morgan | E44: BB Wiki
A45: BB27 | B45: Week 8 | C45: Vince | D45: Will | E45: BB Wiki
A46: BB26 | B46: Week 1 | C46: Cam | E46: BB Wiki
A47: BB26 | B47: Week 1 | C47: Kimo | E47: BB Wiki
A48: BB26 | B48: Week 1 | C48: Quinn | E48: BB Wiki
A49: BB26 | B49: Week 1 | C49: Tucker | E49: BB Wiki
A50: BB26 | B50: Week 2 | C50: Leah | E50: BB Wiki
A51: BB26 | B51: Week 2 | C51: Makensy | E51: BB Wiki
A52: BB26 | B52: Week 2 | C52: Rubina | E52: BB Wiki
A53: BB26 | B53: Week 2 | C53: Lisa | E53: BB Wiki
A54: BB26 | B54: Week 5 | C54: Angela | E54: BB Wiki
A55: BB26 | B55: Week 5 | C55: Joseph | E55: BB Wiki
A56: BB26 | B56: Week 5 | C56: Kimo | E56: BB Wiki
A57: BB26 | B57: Week 7 | C57: Kimo | E57: BB Wiki
... A83: BB24 | B83: Week 1 | C83: Monte | E83: BB Wiki
A84: BB24 | B84: Week 2 | C84: Daniel | D84: Kyle | E84: BB Wiki
A85: BB24 | B85: Week 2 | C85: Nicole | D85: Joseph | E85: BB Wiki
A86: BB24 | B86: Week 2 | C86: Terrance | D86: Michael | E86: BB Wiki
A87: BB24 | B87: Week 2 | C87: Pooch | D87: Monte | E87: BB Wiki
A88: BB24 | B88: Week 3 | C88: Alyssa | E88: BB Wiki
A89: BB24 | B89: Week 3 | C89: Indy | E89: BB Wiki
A90: BB24 | B90: Week 4 | C90: Jasmine | D90: A&I | E90: BB Wiki
A91: BB24 | B91: Week 4 | C91: Turner | D91: A&I | E91: BB Wiki
A92: BB23 | B92: Week 1 | C92: Xavier | E92: BB Wiki
A93: BB23 | B93: Week 1 | C93: Alyssa | E93: BB Wiki
A94: BB23 | B94: Week 1 | C94: Sarah Beth | E94: BB Wiki
A95: BB23 | B95: Week 1 | C95: Christian | E95: BB Wiki
A96: BB23 | B96: Week 2 | C96: Hannah | E96: BB Wiki
A97: BB23 | B97: Week 2 | C97: Derek X. | E97: BB Wiki
A98: BB23 | B98: Week 2 | C98: Whitney | E98: BB Wiki
A99: BB23 | B99: Week 2 | C99: Brent | E99: BB Wiki
A100: BB23 | B100: Week 3 | C100: Kyland | E100: BB Wiki
A101: BB23 | B101: Week 3 | C101: Tiffany | E101: BB Wiki
A102: BB23 | B102: Week 3 | C102: Claire | E102: BB Wiki
A103: BB23 | B103: Week 4 | C103: Azah | E103: BB Wiki
... A117: BB22 | B117: Week 1 | C117: Nicole A. | E117: BB Wiki
A118: BB22 | B118: Week 2 | C118: Christmas | D118: Nicole A. | E118: BB Wiki
A119: BB22 | B119: Week 2 | C119: Nicole F. | D119: Ian | E119: BB Wiki
A120: BB22 | B120: Week 2 | C120: David | D120: Memphis | E120: BB Wiki
A121: BB22 | B121: Week 2 | C121: Kaysar | D121: Kevin | E121: BB Wiki
A122: BB22 | B122: Week 3 | C122: Cody | D122: Kaysar | E122: BB Wiki
A123: BB22 | B123: Week 3 | C123: Enzo | D123: David | E123: BB Wiki
A124: BB22 | B124: Week 3 | C124: Bayleigh | D124: Christmas | E124: BB Wiki
A125: BB22 | B125: Week 3 | C125: Janelle | D125: Nicole F. | E125: BB Wiki
A126: BB22 | B126: Week 4 | C126: Tyler | D126: Enzo | E126: BB Wiki
A127: BB22 | B127: Week 4 | C127: Dani | D127: Bayleigh | E127: BB Wiki
A128: BB22 | B128: Week 4 | C128: Da'Vonne | D128: Cody | E128: BB Wiki
A129: BB22 | B129: Week 6 | C129: David | E129: BB Wiki
A130: BB22 | B130: Week 6 | C130: Da'Vonne | E130: BB Wiki
A131: BB22 | B131: Week 6 | C131: Ian | E131: BB Wiki
A132: BB22 | B132: Week 7 | C132: Christmas | D132: Da'Vonne | E132: BB Wiki
A133: BB22 | B133: Week 7 | C133: Cody | D133: David | E133: BB Wiki
A134: BB22 | B134: Week 8 | C134: Enzo | D134: Cody | E134: BB Wiki
A135: BB22 | B135: Week 8 | C135: Kevin | D135: Christmas | E135: BB Wiki
A136: BB22 | B136: Week 9 | C136: Nicole F. | D136: Enzo | E136: BB Wiki
A137: BB21 | B137: Week 4 | C137: Christie | E137: BB Wiki
A138: BB21 | B138: Week 4 | C138: Michie | E138: BB Wiki
A139: BB21 | B139: Week 4 | C139: Kathryn | E139: BB Wiki
A140: BB21 | B140: Week 4 | C140: Tommy | E140: BB Wiki
A141: BB21 | B141: Week 5 | C141: Jessica | E141: BB Wiki
A142: BB21 | B142: Week 5 | C142: Nicole | E142: BB Wiki
A143: BB21 | B143: Week 5 | C143: Sam | E143: BB Wiki

Sheet Bios
A1: Season | B1: Player | C1: Full name | D1: Age | E1: Born | F1: Hometown | G1: Occupation | H1: Days | I1: Alliances | J1: Source | K1: Looks right? | L1: Correction
A2: BB28 | B2: Devens | C2: Patrick William "Rick" Devens | D2: 42 | E2: 30777 | F2: Macon, Georgia | G2: Communications director | H2: 87 | I2: Bermuda Triangle, Mosh Pit, The Crossovers, The Culture, The Dapper Dans, The Icons, The Primaries, The Red Corner, The Toolshed, The Wolfpack | J2: BB Wiki
A3: BB28 | B3: Taylor | C3: Taylor Brown | D3: 27 | E3: 36067 | F3: Deerfield Beach, Florida | G3: School counselor | H3: 87 | I3: The Ceasefire, The Covenant, The Culture, The Honor Society, The Primaries | J3: BB Wiki
A4: BB28 | B4: Drew | C4: Drew Campbell | D4: 22 | E4: 38021 | F4: Temecula, California | G4: Surgical dental assistant | H4: 87 | I4: 4 Seasons, F.A.P., Melodrew, Mosh Pit, The Ceasefire, The Court Jesters, The Crossovers, The Dapper Dans, The Handymen, The Jugglers, The Toolshed | J4: BB Wiki
A5: BB28 | B5: Dee | C5: Dianelys Maria "Dee" Valladares | D5: 29 | E5: 35340 | F5: Miami, Florida | G5: Entrepreneur | H5: 80 | I5: Café con Leche, Mosh Pit, The Crossovers, The Culture, The Honor Society, The Icons, The Red Corner, The Toolshed, The Wolfpack | J5: BB Wiki
A6: BB28 | B6: Melody | C6: Melody Morris | D6: 24 | F6: Phoenix, Arizona | G6: Corporate game show host | H6: 77 | I6: 4 Seasons, F.A.P., Giggle Girls, Melodrew, Mosh Pit, Sirens, The Ceasefire, The Court Jesters | J6: BB Wiki
A7: BB28 | B7: Yash | C7: Yash Patel | D7: 24 | F7: Monroe Township, New Jersey | G7: Finance analyst | H7: 73 | I7: Bermuda Triangle, The Ceasefire, The Covenant, The Culture, The Dapper Dans, The Wolfpack | J7: BB Wiki
A8: BB28 | B8: Barrett | C8: Barrett Pfeiffer | D8: 27 | E8: 36047 | F8: Austin, Texas | G8: Jumbotron engineer | H8: 73 | I8: F.A.P., Mosh Pit, The Ceasefire, The Crossovers, The Dapper Dans, The Jugglers, The Toolshed | J8: BB Wiki
A9: BB28 | B9: Angela | C9: Angela Lorraine Murray | D9: 52 | E9: 26893 | F9: Syracuse, Utah | G9: Real estate agent | H9: 66 | I9: Mosh Pit, The Crossovers, The Honor Society, The Icons, The Toolshed | J9: BB Wiki
A10: BB28 | B10: La Trice | C10: LaTrice Verrett | D10: 57 | E10: 25033 | F10: Maplewood, New Jersey | G10: Boutique salesperson | H10: 59 | I10: Mama's Angels, The Covenant, The Honor Society | J10: BB Wiki
A11: BB28 | B11: Haley | C11: Haley Jordan Thogmartin | D11: 29 | E11: 35320 | F11: Wildwood, Missouri | G11: Telemedicine executive | H11: 53 | I11: The Red Corner, The Toolshed | J11: BB Wiki
A12: BB28 | B12: Mallory | C12: Mallory Aurichio | D12: 24 | F12: Washington Township, New Jersey | G12: Rocket scientist | H12: 52 | I12: F.A.P., Giggle Girls, Mosh Pit | J12: BB Wiki
A13: BB28 | B13: Kamu | C13: Gabriel Xavier Kamuela "Kamu" Kirk | D13: 32 | E13: 34437 | F13: Phoenix, Arizona | G13: MMA fighter | H13: 45 | I13: Bermuda Triangle, The Covenant, The Handymen, The Primaries, The Red Corner, The Toolshed, The Wolfpack | J13: BB Wiki
A14: BB28 | B14: Chuk | C14: Chukwuemeka "Chuk" Anyanwu | D14: 27 | F14: Dallas, Texas | G14: Supply chain analyst | H14: 38 | I14: The Red Corner, The Toolshed | J14: BB Wiki
A15: BB28 | B15: Lyric | C15: Lyric Leolani Medeiros | D15: 25 | E15: 37012 | F15: Honolulu, Hawaii | G15: Attorney | H15: 31 | I15: 4 Seasons, Giggle Girls, Sirens, The Love Triangle | J15: BB Wiki
A16: BB28 | B16: Jason | C16: Jason De Puy | D16: 35 | E16: 33154 | F16: Los Angeles, California | G16: Drag queen | H16: 24 | I16: Café con Leche, Mama's Angels, The Court Jesters, The Love Triangle | J16: BB Wiki
A17: BB28 | B17: Rome | C17: Jack "Rome" Seymour | D17: 28 | F17: Delray Beach, Florida | G17: Pickleball coach | H17: 17 | I17: 4 Seasons, Mama's Angels, The Love Triangle | J17: BB Wiki
A18: BB28 | B18: Ashley | C18: Ashley Trail | D18: 24 | E18: 37279 | F18: Chicago, Illinois | G18: Bartender | H18: 10 | J18: BB Wiki
A19: BB27 | B19: Ashley | C19: Ashley Diane Hollis | D19: 25 | E19: 36497 | F19: New York City, New York | G19: Attorney | H19: 83 | I19: Girls Girls (BB27), Peach Cobbler, The Judges, Will's Daughters | J19: BB Wiki
A20: BB27 | B20: Vince | C20: Vincent Frank "Vince" Panaro | D20: 34 | E20: 33340 | F20: West Hills, California | G20: Unemployed | H20: 83 | I20: Burger Boys, Heavy Hitters, Strong Side, The Bond, The Judges, The Melting Pot, The Night Owls, The Unexpendables, Triplets | J20: BB Wiki
A21: BB27 | B21: Morgan | C21: Morgan Leigh Pope | D21: 33 | E21: 33502 | F21: Los Angeles, California | G21: Gamer | H21: 83 | I21: Heavy Hitters, Strong Side, Tea Party, The Judges, The Melting Pot, The Night Owls, Triple Threat (BB27) | J21: BB Wiki
A22: BB27 | B22: Ava | C22: Ava Marie Pearl | D22: 24 | E22: 37048 | F22: Manhattan, New York | G22: Aura painter | H22: 80 | I22: Bond Girls, Double the Fun, Flower Power, The Bond, Will's Daughters | J22: BB Wiki
A23: BB27 | B23: Keanu | C23: Keanu Rey Soto | D23: 33 | E23: 33742 | F23: McKinney, Texas | G23: Dungeon Master | H23: 77 | I23: The Frenemies, The Unexpendables | J23: BB Wiki
A24: BB27 | B24: Lauren | C24: Lauren Elizabeth Domingue | D24: 22 | E24: 37492 | F24: Lafayette, Louisiana | G24: Bridal stylist | H24: 73 | I24: Bond Girls, Flower Power, The Bond | J24: BB Wiki
A25: BB27 | B25: Kelley | C25: Kelley Anna-Noreen Jorgensen | D25: 29 | E25: 34916 | F25: Burbank, South Dakota | G25: Web designer | H25: 73 | I25: Flower Power | J25: BB Wiki
A26: BB27 | B26: Will | C26: Cliffton Leonard "Will" Williams | D26: 50 | E26: 27550 | F26: Charlotte, North Carolina | G26: College sports podcaster | H26: 66 | I26: Burger Boys, Peach Cobbler, The Bond, The Judges | J26: BB Wiki
A27: BB27 | B27: Rachel | C27: Rachel Eileen Villegas | D27: 40 | E27: 30971 | F27: Hoover, Alabama | G27: TV personality | H27: 60 | I27: Double the Fun, Girls Girls (BB27), Heavy Hitters, The Frenemies, The Judges, The Mom Squad (BB27), Triplets | J27: BB Wiki
A28: BB27 | B28: Mickey | C28: Michaela Chalon "Mickey" Lee | D28: 35 | F28: Atlanta, Georgia | G28: Event curator | H28: 59 | I28: Peach Cobbler, Tea Party, The Melting Pot, Triple Threat (BB27) | J28: BB Wiki
A29: BB27 | B29: Katherine | C29: Katherine Elizabeth Woodman | D29: 23 | E29: 37281 | F29: Columbia, South Carolina | G29: Fine dining server | H29: 52 | J29: BB Wiki
A30: BB27 | B30: Rylie | C30: Rylie Don Jeffries | D30: 27 | E30: 35835 | F30: Luther, Oklahoma | G30: Professional bull rider | H30: 45 | I30: Burger Boys, Heavy Hitters, The Unexpendables | J30: BB Wiki
A31: BB27 | B31: Zach | C31: Zachary Senot "Zach" Cornell | D31: 27 | E31: 35782 | F31: Cartersville, Georgia | G31: Marketing manager | H31: 38 | I31: Burger Boys, Heavy Hitters, Strong Side, The Bond, The Melting Pot | J31: BB Wiki
A32: BB27 | B32: Jimmy | C32: James Jude "Jimmy" Heagerty III | D32: 25 | E32: 36437 | F32: Washington, D.C. | G32: Strategy consultant | H32: 31 | I32: Heavy Hitters, Triple Threat (BB27), Triplets | J32: BB Wiki
A33: BB27 | B33: Adrian | C33: Adrian Rocha | D33: 23 | E33: 37111 | F33: San Antonio, Texas | G33: Carpenter | H33: 24 | I33: The Bond | J33: BB Wiki
A34: BB27 | B34: Amy | C34: Amy Marian Bingham | D34: 43 | E34: 30013 | F34: Stockton, California | G34: Insurance agent | H34: 17 | I34: Girls Girls (BB27), The Mom Squad (BB27) | J34: BB Wiki
A35: BB27 | B35: Zae | C35: Isaiah Montgomery "Zae" Frederich | D35: 23 | E35: 37384 | F35: Provo, Utah | G35: Salesperson | H35: 10 | I35: Burger Boys | J35: BB Wiki
A36: BB26 | B36: Chelsie | C36: Chelsie Marlene Baham | D36: 27 | E36: 35427 | F36: Rancho Cucamonga, California | G36: Nonprofit director | H36: 90 | I36: The Barbershop, The Collective, The Core, The Pentagon, Final Three (BB26) | J36: BB Wiki
A37: BB26 | B37: Makensy | C37: Makensy Jo Manbeck | D37: 22 | E37: 37361 | F37: Houston, Texas | G37: Construction project manager | H37: 90 | I37: The Barbershop, Final Three (BB26) | J37: BB Wiki
A38: BB26 | B38: Cam | C38: Cameron "Cam" Sullivan-Brown | D38: 25 | E38: 36142 | F38: Bowie, Maryland | G38: Physical therapist | H38: 90 | I38: The Andersons, The Barbershop, The Collective, The Core, The Pentagon, Final Three (BB26) | J38: BB Wiki
A39: BB26 | B39: Rubina | C39: Rubina Ann Bernabe | D39: 35 | E39: 32543 | F39: Los Angeles, California | G39: Event bartender | H39: 87 | I39: 5 Pointz, The Trio, Sixth Avenue, The Barbershop, Tubina | J39: BB Wiki
A40: BB26 | B40: Kimo | C40: Kimo Apaka | D40: 35 | E40: 32403 | F40: Hilo, Hawaii | G40: Mattress sales representative | H40: 80 | I40: Five Pointz, The Trio, Sixth Avenue, The Andersons, The Collective, The Crow Boys, The Visionaries | J40: BB Wiki
A41: BB26 | B41: Angela | C41: Angela Lorraine Murray | D41: 50 | E41: 26893 | F41: Syracuse, Utah | G41: Real estate agent | H41: 73 | I41: BB Guns, Golden Girlies, Sixth Avenue, The Lorraines | J41: BB Wiki
... A48: BB26 | B48: Cedric | C48: Cedric Juan Hodges | D48: 21 | E48: 37510 | F48: Boise, Idaho | G48: Former Marine | H48: 31 | I48: Crowd Control (BB26), The Barbershop, The Collective, The Core, The Pentagon | J48: BB Wiki
A49: BB26 | B49: Kenney | C49: Kenney Kelley | D49: 52 | E49: 26277 | F49: Boston, Massachusetts | G49: Former undercover cop | H49: 24 | J49: BB Wiki
A50: BB26 | B50: Lisa | C50: Lisa Sarah Weintraub | D50: 33 | E50: 33380 | F50: Los Angeles, California | G50: Celebrity chef | H50: 17 | J50: BB Wiki
A51: BB26 | B51: Matt | C51: David Matthew "Matt" Hardeman | D51: 25 | E51: 36188 | F51: Roswell, Georgia | G51: Tech sales rep | H51: 10 | I51: The Barbershop | J51: BB Wiki
A52: BB25 | B52: Jag | C52: Jagateshwar "Jag" Bains | D52: 25 | E52: 35840 | F52: Omak, Washington | G52: Truck company owner | H52: 100 | I52: 7 Deadly Sins, Crowd Control, Family Style, The Fugitives, The Handful, The Mafia (BB25), The Minutemen, The Unreliables | J52: BB Wiki
A53: BB25 | B53: Matt | C53: Matthew James "Matt" Klotz | D53: 27 | E53: 35209 | F53: Baton Rouge, Louisiana | G53: Deaflympics gold medalist | H53: 100 | I53: 3 Way Rats, 7 Deadly Sins, Family Style, Legend 25, Phalanx 5, The Fugitives, The Handful, The Mafia (BB25), The Minutemen | J53: BB Wiki
A54: BB25 | B54: Bowie Jane | C54: Miranda "Bowie Jane" Ball | D54: 46 | E54: 28402 | F54: Los Angeles, California | G54: Lawyer, Barrister & DJ | H54: 100 | I54: Bye Bye Bitches, Legend 25, The Mafia (BB25), The Professors | J54: BB Wiki
A55: BB25 | B55: Felicia | C55: Felicia Delene Cannon | D55: 63 | E55: 22085 | F55: Kennesaw, Georgia | G55: Real estate agent | H55: 96 | I55: 7 Deadly Sins, Brown Sugar Babes, Bye Bye Bitches, For Real For Real, Legend 25, The Bookends, The Professors | J55: BB Wiki
A56: BB25 | B56: Cirie | C56: Cirie Tiffany Fields | D56: 53 | E56: 25767 | F56: Jersey City, New Jersey | G56: Surgical director | H56: 93 | I56: 7 Deadly Sins, Brown Sugar Babes, Bye Bye Bitches, For Real For Real, Legend 25, The Bookends, The Crossroads, The Fields, The Professors, The Real Fields | J56: BB Wiki
A57: BB25 | B57: America | C57: America Lopez | D57: 27 | E57: 35031 | F57: Edinburg, Texas | G57: Medical receptionist | H57: 86 | I57: 3 Way Rats, Americory, Family Style, For Real For Real, The Sirens, The Unreliables | J57: BB Wiki
A58: BB25 | B58: Blue | C58: Blue Bada Kim | D58: 25 | E58: 36008 | F58: New York, New York | G58: Brand strategist | H58: 86 | I58: 7 Deadly Sins, Crowd Control, Family Style, The Handful, The Sirens | J58: BB Wiki
A59: BB25 | B59: Cory | C59: Cory Benjamin Wurtenberger | D59: 21 | E59: 37163 | F59: Weston, Florida | G59: College student | H59: 79 | I59: 3 Way Rats, Americory, For Real For Real, The Crossroads, The Handful, The Unreliables, The Writers Room | J59: BB Wiki
A60: BB25 | B60: Cameron | C60: Cameron Hardin | D60: 34 | E60: 32573 | F60: Eastman, Georgia | G60: Stay-at-home father | H60: 72 (Days 1-51 & 58-72 in house, Days 51-58 as a BB Zombie) | I60: Family Style, Legend 25, The Chillers, The Fugitives, The Handful | J60: BB Wiki
A61: BB25 | B61: Mecole | C61: Mecole Deonsha Hayes | D61: 30 | E61: 34150 | F61: Upper Marlboro, Maryland | G61: Political consultant | H61: 65 | I61: Brown Sugar Babes, Bye Bye Bitches, For Real For Real, Legend 25, The Professors, The Writers Room | J61: BB Wiki
A62: BB25 | B62: Jared | C62: Jared Lavell Fields | D62: 25 | E62: 35859 | F62: Norwalk, Connecticut | G62: Exterminator | H62: 58 (Days 1-51 in house, Days 51-58 as a BB Zombie) | I62: 7 Deadly Sins, Brown Sugar Babes, For Real For Real, Phalanx 5, The Crossroads, The Fields, The Handful, The Real Fields | J62: BB Wiki
... A99: BB23 | B99: Frenchie | C99: Brandon "Frenchie" French | D99: 34 | E99: 31778 | F99: Clarksville, Tennessee | G99: Farmer | H99: 16 | I99: The Slaughterhouse, Whenchie, French Kisses | J99: BB Wiki
A100: BB23 | B100: Travis | C100: Travis Garret Long | D100: 22 | E100: 36070 | F100: Honolulu, Hawaii | G100: Technology sales consultant | H100: 9 | J100: BB Wiki
A101: BB22 | B101: Cody | C101: Cody Christopher Calafiore | D101: 29 | E101: 33220 | F101: Howell, New Jersey | G101: Soccer coach | H101: 85 | I101: The Root, The Connect, The Core Four, The Committee, The Commission, Downlowmance, Slick Six, Triple Threat, Four Prime | J101: BB Wiki
A102: BB22 | B102: Enzo | C102: Vincenzo "Enzo" Palumbo | D102: 42 | E102: 28506 | F102: Bayonne, New Jersey | G102: Insurance adjuster | H102: 85 | I102: The Root, The Connect, Slick Six, Team Freeze, The Core Four | J102: BB Wiki
A103: BB22 | B103: Nicole F. | C103: Nicole Ann Franzel-Arroyo | D103: 28 | E103: 33785 | F103: Ubly, Michigan | G103: Social media influencer | H103: 85 | I103: Four Prime, Million Club, The Core Four, The Committee | J103: BB Wiki
A104: BB22 | B104: Christmas | C104: Christmas Joye Garrett | D104: 38 | E104: 29940 | F104: Raleigh, North Carolina | G104: Fitness entrepreneur | H104: 79 | I104: The Committee, The Carolinas | J104: BB Wiki
A105: BB22 | B105: Memphis | C105: Robert "Memphis" Garrett | D105: 37 | E105: 30291 | F105: Fort Lauderdale, Florida | G105: Restaurateur | H105: 72 | I105: The Committee, The Commission | J105: BB Wiki
A106: BB22 | B106: Tyler | C106: Tyler Ross Crispen | D106: 25 | E106: 34747 | F106: Hilton Head Island, South Carolina | G106: Jewelry company co-owner | H106: 65 | I106: Slick Six, The Carolinas, The Committee, Team Freeze, Triple Threat | J106: BB Wiki
A107: BB22 | B107: Dani | C107: Daniele "Dani" Briones | D107: 33 | E107: 31644 | F107: Orange County, California | G107: Stay-at-home mom | H107: 58 | I107: The Core Four, The Committee, Slick Six, Four Prime | J107: BB Wiki
A108: BB22 | B108: David | C108: David Alexander | D108: 30 | E108: 32874 | F108: Los Angeles, California | G108: Senior sales representative | H108: 58 | I108: Team Freeze | J108: BB Wiki
A109: BB22 | B109: Kevin | C109: Kevin Campbell | D109: 40 | E109: 29116 | F109: San Diego, California | G109: Ad agency executive | H109: 58 | I109: Adorkables, Downlowmance | J109: BB Wiki
A110: BB22 | B110: Da'Vonne | C110: Da'Vonne Dianne Rogers | D110: 32 | E110: 32273 | F110: Inglewood, California | G110: Acting coach | H110: 51 | I110: Black Girl Magic (BB22), The Connect, Slick Six | J110: BB Wiki
A111: BB22 | B111: Ian | C111: Ian Patrick Terry | D111: 29 | E111: 33316 | F111: Houston, Texas | G111: Management consultant | H111: 44 | I111: Adorkables, Four Prime, Million Club | J111: BB Wiki
A112: BB22 | B112: Bayleigh | C112: Bayleigh Amethyst Dayton | D112: 27 | E112: 34114 | F112: Los Angeles, California | G112: Model | H112: 37 | I112: Black Girl Magic (BB22), The Connect, Slick Six | J112: BB Wiki
... A115: BB22 | B115: Nicole A. | C115: Nicole Mary Frances Anthony-Fontanez | D115: 25 | E115: 34694 | F115: Long Island, New York | G115: Podcast host | H115: 16 | I115: Adorkables | J115: BB Wiki
A116: BB22 | B116: Keesha | C116: Keesha Marie Smith | D116: 42 | E116: 28703 | F116: Los Angeles, California | G116: Waitress | H116: 9 | J116: BB Wiki
A117: BB21 | B117: Michie | C117: Jackson Glen Michie | D117: 24 | E117: 34863 | F117: Los Angeles, California | G117: Server | H117: 99 | I117: Gr8ful, Fam Five, Stage Five, Six Shooters, Threemance, Unde9able | J117: BB Wiki
A118: BB21 | B118: Holly | C118: Holly Katherine Allen | D118: 31 | E118: 32153 | F118: Los Angeles, California | G118: Wine safari guide | H118: 99 | I118: Gr8ful, Stage Five, BB Besties, Six Shooters, Threemance, Unde9able | J118: BB Wiki
A119: BB21 | B119: Nicole | C119: Nicole Mary Frances Anthony-Fontanez | D119: 24 | E119: 34694 | F119: Long Island, New York | G119: Preschool aide | H119: 99 | I119: The Black Widows, The Fellowship of the Zing, Cliff's Angels | J119: BB Wiki
A120: BB21 | B120: Cliff | C120: William Clifford "Cliff" Hogg III | D120: 53 | E120: 23856 | F120: Houston, Texas | G120: Petroleum engineer | H120: 93 | I120: The Fellowship of the Zing, Cliff's Angels | J120: BB Wiki
A121: BB21 | B121: Tommy | C121: Thomas "Tommy" Bracco | D121: 28 | E121: 33093 | F121: Huguenot, New York | G121: Broadway dancer | H121: 86 | I121: Gr8ful, Six Shooters, Unde9able, Flaming Five, Staten Island, Lots of Love | J121: BB Wiki
A122: BB21 | B122: Christie | C122: Christie Lynn Murphy | D122: 28 | E122: 33166 | F122: Keyport, New Jersey | G122: Boutique owner | H122: 79 | I122: Gr8ful, Fam Five, Stage Five, Six Shooters, Unde9able, Flaming Five, Staten Island, Lots of Love | J122: BB Wiki
A123: BB21 | B123: Jessica | C123: Jessica Milagros Guzman Sanchez | D123: 37 | E123: 29873 | F123: Oak Park, Illinois | G123: Plus-size model | H123: 79 | I123: The Black Widows, Cliff's Angels | J123: BB Wiki
A124: BB21 | B124: Nick | C124: Nicholas "Nick" Maccarone | D124: 27 | E124: 33767 | F124: Sewell, New Jersey | G124: Therapist | H124: 72 | I124: Gr8ful, Stage Five, Unde9able, Flaming Five | J124: BB Wiki
A125: BB21 | B125: Analyse | C125: Analyse Marie "Sis" Talavera | D125: 22 | E125: 35499 | F125: Simi Valley, California | G125: College soccer star | H125: 65 | I125: Gr8ful, Fam Five, BB Besties, Stage Five, Six Shooters, Unde9able | J125: BB Wiki
A126: BB21 | B126: Kathryn | C126: Kathryn Elaine Dunn | D126: 29 | E126: 32882 | F126: Dallas, Texas | G126: Digital marketing executive | H126: 58 | I126: Stage Five, Threemance, Cliff's Angels | J126: BB Wiki
A127: BB21 | B127: Jack | C127: John Kirkwood "Jack" Matthews | D127: 28 | E127: 33061 | F127: Tampa, Florida | G127: Fitness trainer | H127: 51 | I127: Gr8ful, Stage Five, Six Shooters, Unde9able, Lots of Love | J127: BB Wiki
A128: BB21 | B128: Sam | C128: Samuel Titus "Sam" Smith | D128: 31 | E128: 32184 | F128: Mountain Top, Pennsylvania | G128: Truck driver | H128: 44 | I128: Stage Five, Unde9able, Flaming Five | J128: BB Wiki
... A131: BB21 | B131: Ovi | C131: Ovi Kabir | D131: 22 | E131: 35384 | F131: Knoxville, Tennessee | G131: College student | H131: 30 (Days 1-15 in house, Days 15-30 in Camp Comeback) | I131: Fam Five, The Fellowship of the Zing | J131: BB Wiki
A132: BB21 | B132: David | C132: David Alexander | D132: 29 | E132: 32874 | F132: Atlanta, Georgia | G132: Photographer | H132: 17 (Day 1 in house, Days 15-30 in Camp Comeback) | J132: BB Wiki

Sheet Sources disagree
A1: Season | B1: Week | C1: Round | D1: Field | E1: Wikipedia | F1: Big Brother Wiki | G1: Source | H1: Looks right? | I1: Correction
A2: BB26 | B2: Week 3 | C2: 1 | D2: Initial nominations | E2: Angela, Kenney, Tucker | F2: Kenney, Makensy, Tucker | G2: BB Wiki
A3: BB26 | B3: Week 3 | C3: 1 | D3: Veto winner | E3: Tucker, Makensy | F3: Makensy | G3: BB Wiki
A4: BB25 | B4: Week 1 | C4: 1 | D4: Initial nominations | E4: Cory, Felicia, Jared, Kirsten | F4: Jared, Kirsten | G4: BB Wiki
A5: BB25 | B5: Week 1 | C5: 1 | D5: Veto used | E5: Yes | F5: No | G5: BB Wiki
A6: BB23 | B6: Week 7 | C6: 1 | D6: Initial nominations | E6: Claire, Derek F., Xavier | F6: Claire, Xavier | G6: BB Wiki
A7: BB23 | B7: Week 8 | C7: 1 | D7: HOH | E7: Tiffany, Claire | F7: Claire | G7: BB Wiki
A8: BB22 | B8: Week 6 | C8: 1 | D8: Initial nominations | E8: David, Kevin, Tyler | F8: Kevin, Tyler | G8: BB Wiki

Sheet What was different
A1: Season | B1: Week | C1: Type | D1: Text | E1: Source | F1: Looks right? | G1: Correction
A2: BB28 | B2: Week 1 | C2: Twist / outcome | D2: Block Buster: Yash | E2: Wikipedia
A3: BB28 | B3: Week 1 | C3: Wikipedia note [e] | D3: This HouseGuest won the BB Block Buster competition and was saved from possible eviction. | E3: Wikipedia
A4: BB28 | B4: Week 1 | C4: Wikipedia note [i] | D4: This HouseGuest won a competition and was immune from eviction. | E4: Wikipedia
A5: BB28 | B5: Week 2 | C5: Twist / outcome | D5: Block Buster: Jason | E5: Wikipedia
A6: BB28 | B6: Week 2 | C6: Wikipedia note [e] | D6: This HouseGuest won the BB Block Buster competition and was saved from possible eviction. | E6: Wikipedia
A7: BB28 | B7: Week 2 | C7: Veto (episode summary) | D7: Drew, however, pushes Devens to use the Veto on Melody instead, causing Devens to question where Drew's true loyalties lie. | E7: Wikipedia
A8: BB28 | B8: Week 2 | C8: Veto (episode summary) | D8: Melody is hurt that Devens chose not to use the Veto on her but feels slightly more secure now that Rome is sitting beside her on the block. | E8: Wikipedia
A9: BB28 | B9: Week 3 | C9: Twist / outcome | D9: Block Buster: Mallory | E9: Wikipedia
A10: BB28 | B10: Week 3 | C10: Wikipedia note [e] | D10: This HouseGuest won the BB Block Buster competition and was saved from possible eviction. | E10: Wikipedia
A11: BB28 | B11: Week 3 | C11: Veto (episode summary) | D11: Jason tells each nominee that he would use the veto on them if he won, while also assuring Kamu that he would not use it. | E11: Wikipedia
A12: BB28 | B12: Week 4 | C12: Twist / outcome | D12: Block Buster: Drew | E12: Wikipedia
A13: BB28 | B13: Week 4 | C13: Wikipedia note [e] | D13: This HouseGuest won the BB Block Buster competition and was saved from possible eviction. | E13: Wikipedia
... A277: BB21 | B277: Week 13 | C277: Wikipedia note [e] | D277: As Head of Household, Michie chose to evict Nicole. | E277: Wikipedia

Sheet Episodes
A1: Season | B1: Week | C1: No. overall | D1: No. | E1: Title | F1: Days | G1: Air date | H1: Viewers (M) | I1: Summary | J1: Source | K1: Looks right? | L1: Correction
A2: BB28 | B2: Week 1 | C2: 976 | D2: 1 | E2: Episode 1 | F2: Day 1 | G2: 46212 | H2: 3.88 | I2: Fourteen new HouseGuests move into the Big Brother House. Julie Chen Moonves revealed that none of them would become the season's first Head of Household. To begin the game, the HouseGuests were told they would be traveling through time to retrieve three remaining HouseGuests, all of whom were reality TV icons. To earn safety, the fourteen players were instructed by Enzo Palumbo, creator of Meow Meow Enterprise, to searched the House for BBtomium, which would earn them the opportunity to compete for safety. The BBtonium had different equations on them. Houseguests must find Palumbo on the memory wall and see which number he is holding and find the BBtonium that adds up to the correct number. Ashley and Barrett were the only two HouseGuests who did not earn the chance to compete in the second challenge to earn safety. HouseGuest then had to divide into three groups of four where one HouseGuest from each group would earn safety. The first group, La Trice, Mallory, Kamu, and Rome, traveled back to July 9, 1988. In the first Safety Competition, each HouseGuest was tasked with placing eight pieces of "radial merchandise" onto an unsteady display rack. Each item had a different weight and must be carefully arranged to keep the rack balanced. The first HouseGuest to successfully balance all eight items and press their buzzer earned safety. Rome successfully balanced all items and won immunity for the week. As his reward, he delivered the first letter, bringing Big Brother 26 houseguest Angela Murray into the game. The second group, Taylor, Chuk, Drew, and Haley, traveled to July 7, 2018, where they competed in a Survivor-inspired challenge. In the second Safety Competition Part 2, each HouseGuest had to make their way across a river using only two planks of different lengths. By strategically placing and repositioning the planks one at a time, it would created a path to the opposite side. The first HouseGuest to successfully reach the other side earned safety. Chuk won the competition and delivered the next letter to Jeff Probst, bringing Survivor contestant Rick Devens into the game. The final group, Yash, Melody, Lyric, and Jason, traveled back to June 27, 2010. In the third Safety Competition Part 3, each HouseGuest must listen to a series of audio clips before answering questions by choosing between three possible responses: Bahama Mama, Fuzzy Navel, or Purple Hooter. After each question, the HouseGuest who buzzed in last would be eliminated from the competition. The final remaining player won safety for the week. Jason won the challenge and successfully brought Big Brother winner Rachel Reilly into the game. For the first Head of Household competition, the entire cast traveled back to 175 million BC. Before the competition, Rachel met her untimely demise after falling into a volcano, forcing Julie to travel to December 20, 2023, to retrieve her replacement. | J2: Wikipedia
A3: BB28 | B3: Week 1 | C3: 977 | D3: 2 | E3: Big Brother: Unlocked 7/10/26 | F3: Day 1 | G3: 46213 | H3: 2.35 | I3: In Big Brother: Unlocked, Survivor 45 winner Dee Valladares entered the game. Former Big Brother winners Derrick Levasseur and Taylor Hale then used the dining table time machine to travel to fifteen minutes prior to Rachel's untimely demise in 175 million BC to save her from her fate. After returning to the present, Derek, Taylor and Rachel were joined with Jerry O'Connell to recap and revisit the first night of the season. Featured segments included "Missing Moments", "Cirie's Survival Tips", and "Something Surprising". The episode concluded with Angela, Dee, and Devens competing to become the season's first Head of Household. | J3: Wikipedia
A4: BB28 | B4: Week 1 | C4: 978 | D4: 3 | E4: Episode 3 | F4: Days 1–4 | G4: 46215 | H4: 2.92 | I4: For the first Head of Household competition, each reality icon was assisted by the four new players who brought them into the game. As Rachel's replacement, Dee inherited Rachel's group of four HouseGuests. In the Head Of Household Competition, each group of four newbies stood on a boulder and used ropes to support a suspended stacking platform while their icon assembled a fire-themed puzzle. If the puzzle fell or the platform touched the ground the player had to restart from the beginning. The first HouseGuest to complete the puzzle would become the first Head of Household, while the group with the fewest correct puzzle pieces on their platform at the end of the competition would become the season's first Have-Nots. Dee won the competition, becoming the first Head of Household. As a result, Devens' group, consisting of Chuk, Drew, Haley, and Taylor, finished with the fewest pieces on their platform and became the first Have-Nots of the season. After her victory, Dee celebrated with Angela, who shared advice on how to handle the responsibilities of being the Week 1 Head of Household. Meanwhile, Chuk, Kamu, and Haley quickly formed a strong bond. Dee and Devens also had a conversation to put aside their differences following Survivor 50: In the Hands of the Fans. Wanting to protect one another while strengthening their positions in the game, they first aligned with Kamu, Chuk, and Haley to create an alliance called "The Red Corner". They then brought in Angela, Barrett, and Drew to form a different alliance known as "The Crossovers". Elsewhere in the house, Rome and Lyric began flirting, and their growing connection quickly became noticeable to the other players. As nominations approached, Dee decided it would be fairest to nominate one player from each of the three time-travel groups. Kamu was skeptical of the plan, arguing that Dee should not nominate someone from the group that had helped her become Head of Household and tried to convince her to nominate Barrett instead. On Day 4, Dee stuck with her original plan and nominated Mallory, Taylor, and Yash for eviction. | J4: Wikipedia
A5: BB28 | B5: Week 1 | C5: 979 | D5: 4 | E5: Episode 4 | F5: Days 4–7 | G5: 46218 | H5: 3.29 | I5: Following the first Nomination Ceremony of the season, Yash feels betrayed by Dee after helping her win the Head of Household competition. Taylor knows she needs to remain calm, while Mallory feels hurt and upset by her nomination. The HouseGuests become wary of Mallory’s emotional reaction, questioning whether her response could make her a bigger target. The Icons celebrate together, with Dee identifying Yash as her main target while keeping Mallory as a potential backup option. Melody and Lyric begin questioning whether they should distance themselves from Mallory to avoid becoming associated with her. Meanwhile, Rome and Lyric grow even closer, sharing more intimate moments and strengthening their bond. During the Veto Draw, Barrett and Melody were selected to compete alongside the three nominees and Dee. In the Power of Veto Competition ("Back From the Future"), each HouseGuest must help future Howie Gordon defeat future Will Kirby by constructing a path between the "Table Time Machine" and Will's throne using a series of tubes. The route must pass through all eleven amplifier rings before reaching the throne. The first HouseGuest to successfully connect the entire course won the Golden Power of Veto. Mallory ultimately finished first, winning the first Power of Veto competition of the summer. Jason begins to confide in Angela, playing up his emotions in an attempt to get her on his side. However, after he confides with Melody and Drew, the information gets back to Angela. Drew also informs Devens that Jason may be targeting him in the near future. With Jason safe for the week, Dee continues trying to make strategic decisions that benefit her game. She considers nominating Barrett or Ashley as replacement nominees, as neither were included in a group on the first night. On Day 7, Mallory uses the Power of Veto on herself, and Dee nominates Ashley as her replacement, keeping her promise to nominate at least one person from each original group. | J5: Wikipedia
A6: BB28 | B6: Week 1 | C6: 980 | D6: 5 | E6: Episode 5 | F6: Days 7–10 | G6: 46219 | H6: 3.3 | I6: Dee continues to push for Yash to be the first evicted, fearing that he could target her in the future and rally the rest of the guys from her alliance. Taylor feels safe regardless of the outcome of the upcoming BB Block Buster. The HouseGuests begin to notice a tight alliance forming between Kamu, Haley, and Chuk, with the Icons also appearing to be closely aligned with them. Angela grows suspicious that Rome may be gathering numbers against their side of the house, while Rome begins forming a close alliance with La Trice and Jason. Ashley attempts to campaign for her safety by approaching Melody, claiming that other side are votes to keep her. This information gets back to Drew and the rest of his alliance, causing them to become concerned about Ashley's gameplay and intentions. In the BB Block Buster Competition ("Do Over"), nominees must scan a series of images featuring their fellow HouseGuests with hairstyles from different eras. They must correctly identify the HouseGuest who appears in the most images within two minutes. The first HouseGuest to submit the correct answer wins the Block Buster, leaving the remaining two nominees on the block. Yash secures the win, leaving Ashley and Taylor as the final nominees for the week. On Day 10, Ashley is unanimously evicted from the Big Brother house. | J6: Wikipedia
A7: BB28 | B7: Week 2 | C7: 981 | D7: 6 | E7: Episode 6 | F7: Days 5, 10–11 | G7: 46222 | H7: 3.11 | I7: Following the unanimous vote, most HouseGuests felt uneasy as the vote did not reveal where the house alliances stand. In the Head of Household Competition ("Achy Breaky HOH"), HouseGuests must slide a disk down a table, attempting to land it on the highest-scoring numbered spots. The competition was played in three rounds, with a new rule introduced for each round. In the first round, HouseGuests were paired up and competed against their partner. In the second round, pairs remained together but attempted to eliminate another pair by earning the highest combined score. In the final round, the remaining HouseGuests competed individually, with the player achieving the highest solo score winning the competition. Devens scored the highest and became the second Head of Household. Rome confided in Devens, hoping to protect his side of the house and the people closest to him. He named Jason and Lyric as his two closest allies. Angela privately pulled Devens aside and pushed him to nominate those two close allies, with Rome as the backdoor target. Later that night, a large group consisting of members from "The Red Corner" and "The Crossovers" come together to form an eight person alliance called "The Toolshed." Angela is voted to enter the BB Time Capsule. Her attempt to gain a power is unsuccessful, as she earned the "Hard Boiled-Detective" punishment from Big Brother 27. On Day 11, Devens nominated Jason, Lyric, and Melody for eviction. Before the nomination ceremony can adjourn, an argument broke out between Jason and Angela. | J7: Wikipedia
A8: BB28 | B8: Week 2 | C8: 982 | D8: 7 | E8: Episode 7 | F8: Days 11–14 | G8: 46225 | H8: 3.18 | I8: Jason and Angela publicly go head-to-head during the nomination ceremony. Angela informs the HouseGuests that Jason has been playing on her emotions to gain sympathy and further his game. Haley and Devens also reveal to the girls that Jason has been manipulating them as well. Rome's betrayal is then brought to light, exposing his role in the situation. Melody, La Trice, and Lyric are left blindsided and hurt. Rome to apologize to La Trice as he felt forced to narrow down his list of allies. Meanwhile, Devens and Dee celebrate successfully blowing up the house with his nominations. During the Veto draw, Rome's backdoor plan is set in place as Angela and Barrett are selected to compete alongside the nominees and Devens. In the Power of Veto Competition ("Flower Power"), HouseGuests must find and retrieve twelve hidden puzzle pieces. Once they have collected all their pieces, they must assemble the pieces inside their frame. The first player to complete their puzzle wins the Golden Power of Veto. Devens wins the competition and the Power of Veto. Rome and Lyric attempt to distance themselves in hopes of no longer being viewed as a dangerous "showmance". Lyric approaches Devens and promises that if he were to remove her from the block, she would not target him in the coming weeks. Drew, however, pushes Devens to use the Veto on Melody instead, causing Devens to question where Drew's true loyalties lie. On Day 14, Devens uses the Power of Veto to save Lyric and nominates Rome in her place. | J8: Wikipedia
A9: BB28 | B9: Week 2 | C9: 983 | D9: 8 | E9: Episode 8 | F9: Days 14–17 | G9: 46226 | H9: 3.52 | I9: Melody is hurt that Devens chose not to use the Veto on her but feels slightly more secure now that Rome is sitting beside her on the block. Lyric continues to flirt with Chuck and Yash, though the HouseGuests remain skeptical that she and Rome have truly ended their relationship. The HouseGuests begin to notice another potential showmance forming between Melody and Drew, further convincing Dee and Angela that he may not be fully loyal to their side of the house. In the BB Block Buster Competition ("Pirate's Booty"), nominees must maneuver colored gemstones, aiming to sort four stacks by color by only moving one gem at a time. The first HouseGuest to correctly sort their gems and hit their buzzer will win the Block Buster, leaving the remaining two nominees on the block. Jason wins the Block Buster, leaving Melody and Rome as the final nominees for the week. On Day 17, Rome is evicted from the Big Brother house by a vote of 12–1 with Taylor being the sole vote to evict Melody. Note: Big Brother: Unlocked surprise guest Ross Matthews joins Julie Chen Moonves on stage to discuss the season. | J9: Wikipedia
A10: BB28 | B10: Week 3 | C10: 984 | D10: 9 | E10: Big Brother: Unlocked 7/24/26 | F10: Day 17, Various | G10: 46227 | H10: 1.74 | I10: The episode opened with the fallout of the second eviction. Former Big Brother winners Derrick Levasseur and Taylor Hale, along with Jerry O'Connell, were joined by Ross Matthews to recap and revisit the first two weeks of the season. They are also joined by recent evictee Rome. Featured segments included "Missing Moments", "BB Bad Ass/Dumb Ass", "The Rant Room", "Creator Corner" and "Something Surprising". O'Connell entered the BB Time Capsule and revealed the powers and punishments that are up for grabs. The episode concluded with the HouseGuests beginning the third Head of Household competition, "Wrestlegasm". | J10: Wikipedia
A11: BB28 | B11: Week 3 | C11: 985 | D11: 10 | E11: Episode 10 | F11: Days 17–18 | G11: 46229 | H11: 3.31 | I11: The house begin to question who cast the rogue vote for Melody. Lyric insisted that she was not the one who voted to keep her. Drew and Barrett realize they are at the bottom of both of their alliances and want to keep their options open moving forward. Before the Head of Household competition, Angela is informed that her egg punishment has officially ended. In the Head of Household Competition ("Wrestlegasm"), The HouseGuests must answer a series of true or false questions about a live wrestling match performed in the backyard, featuring an appearance from former Big Brother HouseGuest Jessie Godderz. If a player answers incorrectly, they are eliminated from the competition. The last HouseGuest remaining would win the HoH competition. Kamu wins and becomes the new Head of Household. Kamu wanted to target two strong competitors in hopes of making a strong move. Drew and Kamu formed the "Handymen" alliance, and Kamu immediately voiced that Jason and Mallory were his targets. However, he still needed a third nominee. Angela suspected that Drew was the rogue vote and began stirring up trouble, but she and Dee both felt it was too soon to target him. Kamu informed Lyric that she was safe that week and that he did not want to nominate her. Devens is voted to enter the BB Time Capsule. His attempt to gain a power is successful, as he earned the "Diamond Power of Veto" power first seen on Big Brother 4. He keeps his power a secret from the house but only informs Dee that he won. Before nominations, Drew approached Kamu to make sure he did not nominate Jason immediately, as it would give him another opportunity to win safety. Kamu told Jason that he did not want to put him up "today." After the conversation, Jason began to feel that he was being treated similarly to how Rome had been treated the previous week. Kamu then had to go back on his word to Lyric, as he needed someone to serve as a pawn. On Day 18, Kamu nominated La Trice, Lyric, and Mallory for eviction. | J11: Wikipedia
A12: BB28 | B12: Week 3 | C12: 986 | D12: 11 | E12: Episode 11 | F12: Days 18–21 | G12: 46232 | H12: 3.29 | I12: Though Lyric is upset with Kamu for nominating her, she reassures him to make him feel comfortable in case she does not win the Power of Veto or Block Buster. Jason knows he is the target and hopes that he would be selected to compete in the veto competition. Meanwhile, the houseguests question who has the power, as no one has received a punishment. Drew and Kamu debate whether Kamu should nominate Jason or keep him off the block. During the Veto Draw, Haley and Jason were selected to compete alongside the three nominees and Kamu. Jason tells each nominee that he would use the veto on them if he won, while also assuring Kamu that he would not use it. In the Power of Veto Competition ("The Pickle Ball"), each HouseGuest must go head-to-head against another competitor. They need to spin on a giant pickle for one minute before attempting to score the highest number of points by hitting balls into numbered slots. After five rounds, the HouseGuest with the highest score would win the Golden Power of Veto. Lyric beats Mallory in the final round and wins the Power of Veto. Jason attempts to create chaos in the house by informing Dee that he wants to protect the Icons while targeting Haley, Chuk, and Kamu in the future. He then approaches Chuk and reveals that he would like to go after the three "icons". However, both trios quickly learn about Jason's plans. Kamu decides to expose Jason's messy gameplay during Mallory's planned tea party. Jason then begins to go around the house informing Kamu of any and all strategic gameplay talk between by banging a tea kettle. On Day 21, Lyric uses the Power of Veto to save herself, and Kamu nominates Jason as the replacement nominee. | J12: Wikipedia
A13: BB28 | B13: Week 3 | C13: 987 | D13: 12 | E13: Episode 12 | F13: Days 21–24 | G13: 46233 | H13: 3.47 | I13: The house immediately begins planning out different scenarios for the final outcome. Mallory’s allies, Melody and Lyric, campaign to gather the votes needed to keep her over La Trice and Jason. They attempt to pull in Yash, Drew, and Barrett, while also discussing the possibility of keeping Jason if he remains on the block against La Trice. Drew and Barrett find themselves caught in the middle, as "The Toolshed" alliance would want either Mallory or Jason out this week. The alliance members begin discussing Drew and Barrett's true loyalties and where they stand with them, especially after Drew campaigns for Mallory. Taylor continues to waver back and forth on whether she is willing to vote against La Trice. In the BB Block Buster Competition ("Video Tape Tumble"), nominees must attempt to retrieve video tapes placed on a wobble tower. Players can rearrange the tower as they collect the tapes, but if a tape touches the ground or their tower falls, their current score is locked in. The player who successfully deposits the most tapes wins safety. Mallory wins the Block Buster, leaving Jason and La Trice as the final nominees for the week. On Day 24, Jason is evicted from the Big Brother house by a unanimous vote of 12–0. | J13: Wikipedia
... A168: BB24 | B168: Week 2 | C168: 826 | D168: 6 | E168: Episode 6 | F168: Days 10–13 | G168: 44762 | H168: 3.54 | I168: The Girls Girls alliance, with Taylor, explain to Jasmine their plan to evict Pooch. Jasmine agrees as long as nominations stay the same after the veto. Taylor plans to still win the veto for herself to guarantee her own safety. Pooch and Joseph develop a significant "bromance" from their time spent together in the house. Players were then picked for the Power of Veto competition. Ameerah, Michael, and Terrance were chosen to compete alongside Jasmine, Pooch, and Taylor, as the Head of Household and two nominees. Taylor hopes that Michael will use the veto on her if he wins, while Jasmine does not want have to name a replacement nominee. In the "Mermaid Fest" Power of Veto competition the competitors, dressed as mermaids, used their heads to push a pearl over a series of ramps, and then into a hole at the end of a bowling lane. Michael was the first person to collect a pearl into each of his three holes and received the Power of Veto. On Day 13, Michael chose not to use the Power of Veto, leaving Jasmine's nominees the same. | J168: Wikipedia
A169: BB24 | B169: Week 2 | C169: 827 | D169: 7 | E169: Episode 7 | F169: Days 10, 13–17 | G169: 44766 | H169: 3.36 | J169: Wikipedia
A170: BB24 | B170: Week 2 | C170: 828 | D170: 8 | E170: Episode 8 | F170: Days 10, 13–17 | G170: 44766 | H170: 3.36 | I170: Pooch and Taylor continue to both believe that they are just pawns and will not be evicted. Meanwhile, a "showmance" begins forming between Alyssa and Kyle causing Alyssa to inform him about the Girls Girls alliance. Taylor discusses with Ameerah, wanting to backdoor Monte in a future week. Because of their alliance, Ameerah tells Monte what Taylor wants to do, and the two discuss with Nicole whom they should ultimately vote to evict. Pooch and Taylor are each given one last chance to attempt to save themselves by giving a speech. On Day 16, by a unanimous vote of twelve, Pooch was the first HouseGuest to be evicted from the house. In his exit interview with Julie, Pooch stated that he underestimated the women in the house. The "Festie Besties" twist was then introduced to the game. Julie informed the HouseGuests that going forward, they would be playing the game with a partner, known as a "Bestie". The partner of the HouseGuest that won Head of Household will be safe for the week; HouseGuests will also be nominated and play for Power of Veto in pairs, but evicted independently. HouseGuests then participated in the next Head of Household competition. HouseGuests have to hold down buttons on a "lighter" until the music playing stops when they must sit down in a chair as fast as possible. The last HouseGuest to sit down, or those who let go of their button before the music stopped, in each round were eliminated from the competition and had to choose a partner.Turner was the first HouseGuest to sit down in the final round and became the next Head of Household. He was then paired with Jasmine, the last person remaining without a partner, guaranteeing her safety for the week. Turner considers nominating Ameerah or Nicole, because he views them both as threats and wants to get revenge for Pooch's eviction. The Po's Pack alliance, consisting of Alyssa, Nicole, Ameerah, Kyle, Michael, and Monte, agree to prioritize the alliance since they are all paired with members outside of it. Alyssa and Indy were chosen to be have-nots for the week by Jasmine. Nicole wants Turner to nominate Brittany and Michael and eventually be nominated herself, so that the Po's Pack can backdoor Taylor. Turner ultimately sets his sights on Brittany and Michael or Nicole and Taylor. On Day 17, Turner nominated Brittany and Michael for eviction. | J170: Wikipedia
A171: BB24 | B171: Week 3 | C171: 829 | D171: 9 | E171: Episode 9 | F171: Days 17–20 | G171: 44769 | H171: 3.77 | I171: Having been picked to compete with Taylor in the Veto competition, Nicole broke down crying, agonizing over whether to throw the competition. The house was worried about this emotional display, coming so soon after Paloma's departure, and Taylor tried to assure Nicole that she would support whatever decision she made. Nicole interpreted this as a hint to quit the game, and she angrily related the episode to other HouseGuests, including Daniel, who confronted Taylor, accusing her of having caused Paloma to quit the game and of trying to do the same with Nicole. Taylor was left in tears. For the Veto competition, each team needed to construct a puzzle on top of a pole. As one team member ran for the pieces, the other was lifted upwards. The first team to complete the puzzle would win the Power of Veto. Just before the competition started, Jasmine fainted due to her fear of heights. After she regained consciousness, Jasmine and Turner opted out of the competition, leaving just two teams to battle for the Power of Veto. Nicole did not need to work too hard to throw the competition, and Michael and Brittany won the Power of Veto. After the Veto competition, Taylor is distraught but is told by Monte to meet in the HOH room later that night. Joseph, Turner, Michael, Taylor, Brittany, Monte, and Kyle recognize they are on the outs in the game and band together to form the Leftovers alliance and plan to blindside and evict Ameerah. | J171: Wikipedia
A172: BB24 | B172: Week 3 | C172: 830 | D172: 10 | E172: Episode 10 | F172: Days 20–23 | G172: 44770 | H172: 3.56 | I172: Brittany and Michael used the PoV to remove themselves from the block. Turner then named Ameerah and Terrance as replacement nominees, coming as a shock to most of the Po's Pack alliance. Terrance requested that they vote to evict him rather than Ameerah, but the Leftovers' alliance believed they had the numbers to evict Ameerah. Ameerah and Terrance were each given a chance to speak as an attempt save themselves. On Day 23, by a vote of 7–4, with Alyssa, Indy, Jasmine, and Nicole voting to evict Terrance, Ameerah was evicted from the Big Brother house. Julie then informed the nominees that each week, the surviving Besties would be able to join another group, becoming a trio, but that all other aspects of the twist would still be in play. Terrance opted to join Joseph and Monte. The HouseGuests then participated in the next HoH competition, based on the upcoming film The Invitation. 1,500 envelopes fell from the air and HouseGuests searched them to find an "invitation" to the second part of the competition. The first eight to do so were allowed to move forward. Jasmine was the first to find an invitation, followed by Terrance and Brittany. | J172: Wikipedia
A173: BB24 | B173: Week 4 | C173: 831 | D173: 11 | E173: Episode 11 | F173: Days 20, 22–24 | G173: 44773 | H173: 4.07 | I173: The eight houseguests (Jasmine, Terrance, Brittany, Monte, Daniel, Joseph, Nicole, Alyssa) who found an invitation competed in round 2 of the HOH competition, which was a form of table shuffleboard using glasses full of "blood". Monte scored the most points and became the new HOH. Monte and the Leftovers Alliance plans to target and backdoor Nicole, but does not want Taylor to go on the block again for the third time if she is not comfortable. On Day 24, Monte nominated Alyssa and Indy for eviction, with the main plan to backdoor Nicole if he gets Taylor's approval. | J173: Wikipedia
A174: BB24 | B174: Week 4 | C174: 832 | D174: 12 | E174: Episode 12 | F174: Days 24–27 | G174: 44776 | H174: 3.83 | I174: After nominations, Brittany, Michael, and Taylor discuss their danger in game moving forward. Daniel and Kyle are selected to compete in the veto competition Trippy Watch Party. In this competition, one bestie answered questions regarding a story seen by the remaining besties after eating "psychedelic slop". Daniel and Kyle won the veto competition. Kyle wanted to use the veto on Alyssa, but the Michael and Brittany convince the Leftovers that it was best to leave the current nominees on the block to protect their alliance next week, as Brittany and Michael are the only Festie Besties not insulated by a pawn. Just before the veto ceremony, Monte tells Daniel and Nicole that the veto should not be used because the votes to save Nicole may not be there. Thinking Monte is lying, Daniel and Nicole decide to go against the HOH's wishes, though this means Daniel is ultimately backdooring his closest ally. At the veto ceremony, Daniel and Kyle use their vetoes, and Monte nominates Nicole and Taylor, much to Taylor's dismay. | J174: Wikipedia
A175: BB24 | B175: Week 4 | C175: 833 | D175: 13 | E175: Episode 13 | F175: Days 27–30 | G175: 44777 | H175: 3.6 | I175: The house remains on edge as there are players trying to determine who was exactly involved in backdooring Ameerah. Nicole and Daniel try to fish out who exactly was involved, where they were able to identify 6 of the 7 members of the "Leftovers" alliance. While Nicole is trying to garner votes to stay, she exposes her past as a former police officer of 10 years to the "Girls Girls" alliance (Alyssa, Indy, Jasmine) where she was actually a detectective for two of those years. Also, the showmance heats up between Alyssa and Kyle after the veto was used to take Alyssa off the block, even though Kyle and his alliance were intending to take Alyssa out. On Day 30, Nicole failed to convince people to vote for her to stay, so she was evicted 9-1, with Daniel being the sole vote to save her. With Taylor needing to choose a new Festie Bestie group, she decides to join Alyssa and Indy. | J175: Wikipedia
A176: BB24 | B176: Week 5 | C176: 834 | D176: 14 | E176: Episode 14 | F176: Days 30–31 | G176: 44780 | H176: 3.96 | I176: Following Nicole's exit, Daniel's emotions get the better of him as he starts to tell the house, "You all can't split the $750,000 cash prize! Start playing for yourselves!" and further lashes out at Monte. As the new HOH competition is being set up, he confronts Monte as being set up well in this game in front of the whole house and as the mastermind/manipulator who got Nicole evicted and claims "Either You or Michael are going to make it to the Final Two. Good job man! Keep up the good work!" which Monte did not take lightly. Daniel further inquires why they moved to get Nicole out, where he told Daniel it was his own fault his friend is gone. The next HOH is competition is announced as BB Fest Pooch-a-palooza: Mind Your Step, which is a balance beam obstacle course. Michael edges out Daniel to win his first HOH of the season. In an attempt to cover their tracks, the "Leftovers" concoct a plan to nominate Joseph, Monte and Terrance in an attempt to hide their alliance. On day 31, Michael sticks to the plan and nominates Joseph, Monte and Terrance for eviction. | J176: Wikipedia
A177: BB24 | B177: Week 5 | C177: 835 | D177: 15 | E177: Episode 15 | F177: Days 31–34 | G177: 44783 | H177: 3.86 | I177: Following the nomination ceremony, and with nowhere or nobody to turn to, Daniel attempts to convince Michael and the house to target Monte. After talking with Terrance, the two are on the same page and Terrance is convinced to throw the Veto Competition. Michael selects the third team competing in the Veto, Turner and Jasmine. OTEV is back for the Veto competition: Get My Sauce. It comes down to Terrance and Michael, where Terrance throws the final round to let Michael win his 4th POV of the season. Once the competition is over, Daniel and Terrance start to work on convincing the group outside the "Leftovers" alliance to target Monte, who in turn agree and attempt to approach Michael one at a time. Michael does not like their approach, as he feels like they are trying to use him to do their "dirty work". At the Veto Ceremony, Michael and Brittany elect to use the POV and remove Joseph, Monte and Terrance from the nomination block. Michael then nominates Daniel and Kyle, and in his speech calls Daniel out for rubbing the house the wrong way. | J177: Wikipedia
A178: BB24 | B178: Week 5 | C178: 836 | D178: 16 | E178: Episode 16 | F178: Days 27, 30, 34–37 | G178: 44784 | H178: 3.63 | I178: After the events of the veto meeting, Daniel becomes aware that Kyle is a part of a larger alliance, originally referred to as "The Sorry Six" by him and Nicole. Despite efforts to save himself, Daniel became the fifth evicted houseguest by a vote of 8-1, with Terrance voting for Kyle. Following his eviction, Julie announced that the Festie Bestie twist was officially over and the jury phase was officially beginning. The remaining houseguests, excluding Michael, began competing in the sixth HOH challenge. Houseguests must hold onto a wall for as long as they can in a challenge titled "Conspiracy Fest". | J178: Wikipedia
A179: BB24 | B179: Week 6 | C179: 837 | D179: 17 | E179: Episode 17 | F179: Days 37–38 | G179: 44787 | H179: 3.95 | I179: Following Daniel's exit, the houseguests finish participating in the HOH competition. When four are left (Indy, Kyle, Taylor and Joseph), Indy drops and Kyle and Joseph drop so they are unable to get blood on their hands for the week, making Taylor the new HOH. Taylor begins deciding what she wants to do with her HOH reign and seeks help from The Leftovers. She initially does not want to nominate a woman so she insists on nominate two of her alliance members, Monte and Turner, instead. However she does not go through with this, and instead nominates Indy and Terrance for eviction. | J179: Wikipedia
A180: BB24 | B180: Week 6 | C180: 838 | D180: 18 | E180: Episode 18 | F180: Days 38–40 | G180: 44790 | H180: 4.06 | I180: Indy reacts rather upset at the fact she was nominated, given Taylor told her she would be safe. At the veto competition, Taylor, Indy, Terrance, Alyssa, Jasmine and Kyle all partake in a challenge where they must score a certain amount of points with a ball, whoever has the fewest points after each round is eliminated, and is able to claim a prize, one of which is the Power of Veto. With Taylor still not sure what her plans are, she threatens Alyssa to take the veto instead of her trip to London, however Alyssa takes her trip anyways which upsets Taylor. Kyle wins the power of veto, and is spoken to by The Leftovers to use the veto on one of Indy or Terrance, so Taylor can easily backdoor Alyssa after holding a grudge against her for taking her trip away from her. | J180: Wikipedia
A181: BB24 | B181: Week 6 | C181: 839 | D181: 19 | E181: Episode 19 | F181: Days 40–44 | G181: 44791 | H181: 3.41 | I181: The Leftovers continue to pressure Kyle into using the veto to save one of the nominations, so they will be able to backdoor his showmance Alyssa. However he decides not to use the Power of Veto. After this, and exposing his four person alliance within The Leftovers known as "The Pound", which includes himself, Joseph, Monte and Turner, Michael and Brittany wonder if sticking with The Leftovers is their best interest moving forward. At the eviction, Indy is evicted by a vote of 7-1, with Michael voting to evict Terrance, becoming the first member of the jury. Julie reveals a new twist to the houseguests, where they will be split into two groups, one outside and one inside, and will partake in a weeks worth of game simultaneously. An HOH competition is played by the houseguests, excluding Taylor, Terrance became the runner-up and therefore the HOH of the outside group, while Michael won the competition and therefore became the HOH of the inside group. Note: This is the first live eviction episode to include a live studio audience since the finale of Big Brother 21. | J181: Wikipedia
... A194: BB24 | B194: Week 11 | C194: 852 | D194: 32 | E194: Episode 32 | F194: Days 72–73 | G194: 44822 | H194: 4.47 | I194: After the HOH competition, Turner confronts Brittany about the vote, who has nothing to say to Turner. Taylor decides to nominate Brittany and Turner, stating that one of them voted against her. Both nominees tell Taylor they voted to save her, but Taylor is set on Turner as her target. The houseguest competed for the most powerful Veto of the summer in "Math Fest". The houseguest had to determine the day that various events occurred from photos and sum the days. Monte narrowly beat out Brittany, winning the final POV and securing a spot on finale night. With the sole vote to evict, Monte plans to keep Turner, but Taylor hopes to convince him otherwise. | J194: Wikipedia
A195: BB24 | B195: Week 11 | C195: 853 | D195: 33 | E195: Episode 33 | F195: Days 73–79 | G195: 44826 | H195: 3.14 | J195: Wikipedia
A196: BB24 | B196: Week 12 | C196: 854 | D196: 34 | E196: Episode 34 | F196: Day 79 Various | G196: 44827 | H196: 2.39 | I196: Monte, Taylor, and Turner celebrated being the final three HouseGuests with a dinner provided by production and champagne. The three looked back over their time in the house highlighting what they believed to be the best moments. | J196: Wikipedia
A197: BB24 | B197: Week 12 | C197: 855 | D197: 35 | E197: Episode 35 | F197: Days 79–82 | G197: 44829 | H197: 4.03 | I197: Monte, Taylor, and Turner compete in the final Head of Household competition. Turner outlasts the other two in Part 1, and Monte subsequently defeats Taylor in Part 2. In a live showdown for Part 3, Monte answers more questions correctly than Turner and is named the final HOH. Despite making an earlier final 2 deal with Turner, Monte votes to evict him, citing his need for a big move on his resume. Monte and Taylor then face the jury, where Monte highlights his challenge prowess and late game strategy while Taylor discusses her resiliency in surviving the block five times. The jury votes 8-1 to crown Taylor the winner of Big Brother 24, with Turner being the lone vote for Monte. Host Julie Chen later reveals that Taylor was also named America's Favorite Houseguest, bringing her total show winnings to $800,000. | J197: Wikipedia
A198: BB23 | B198: Week 1 | C198: 784 | D198: 1 | E198: Episode 1 | F198: Day 1 | G198: 44384 | H198: 4.25 | I198: Sixteen HouseGuests entered the house. In four groups, the HouseGuests participated in "kick-off" competitions, wherein competitors had to arrange a plexiglass display to match the example. Once believing their display was exact, they hit their buzzer to ring in. If correct, they won, and would become a 'team captain', eligible to become Head of Household (HoH). Frenchie, Whitney, Christian, and Claire won their respective competitions. Captains chose teammates based on short introductions. After teams were picked, HouseGuests competed in the "House of Cards" HoH competition. Each captain had to build a pyramid of cards on a platform balanced by their teammates. The first captain to build their pyramid and hit their buzzer became HoH, giving their teammates immunity; the last team to finish became Have-Nots. Frenchie won HoH, while Christian's team became Have-Nots. Frenchie was offered to participate in a challenge wherein he had to throw two dice onto a platform in 45 seconds. If he completed the challenge, his team would be safe for two weeks, but if he lost, he was no longer HoH, his team no longer had immunity, and Claire, as runner-up would become HoH. Frenchie rejected the offer. | J198: Wikipedia
A199: BB23 | B199: Week 1 | C199: 785 | D199: 2 | E199: Episode 2 | F199: Days 1–3 | G199: 44388 | H199: 3.76 | I199: Frenchie began strategizing, saying that he would not nominate anyone from his entry group or any female HouseGuest. He set his target on "meatheads" (Christian, Brent, Travis). On Day 2, the Wildcard competition was introduced. Each non-winning team from the HoH competition had to elect one teammate to participate, with the winner receiving immunity and an additional game-changing dilemma. The elected HouseGuests were Christian, Hannah and Kyland. In the competition, "Do Not Disturb", the three had to search a room for a set of keys, wallet and a cellphone, while making as little noise as possible. The louder the noise produced, the more points would be added to their combined totals. The HouseGuests were given five minutes to compete, with fifty penalty points being added every ten seconds thereafter. Christian won with 125 points. Christian had to spin a wheel containing numbers 1 through 3, corresponding to the number of teammates he could give immunity to. The wheel landed on 1; he granted immunity to Xavier. Frenchie decided to target Alyssa, Christian's teammate, perceiving their close relationship as a "showmance". On Day 3, Frenchie nominated Alyssa and Kyland for eviction. | J199: Wikipedia
A200: BB23 | B200: Week 1 | C200: 786 | D200: 3 | E200: Episode 3 | F200: Days 3–6 | G200: 44391 | H200: 3.63 | I200: The HouseGuests were confused following the nominations ceremony, and Alyssa and Christian approached Frenchie in order to gain insight into his decision. After they were able to convince Frenchie that they were just friends, Frenchie realized his mistake and instead planned to backdoor Derek X. after noticing his close relationship with Travis. Brent, Derek's teammate, warned him that he might be at risk, while also attempting to convince Frenchie to target Travis instead. Meanwhile, Azah, Derek F, Kyland, Tiffany and Xavier formed "The Cookout" alliance. On Day 4, Tiffany, Travis (Kyland's choice) and Derek X. were chosen to compete alongside Frenchie, Alyssa and Kyland in the "Massive Cocktails" Power of Veto (PoV) competition. For this competition, HouseGuests were required to arrange large pieces of fruit on a downhill ramp in order to guide their ball into the glass box at the end. Derek X. was the first HouseGuest to successfully aim his ball through the pieces of fruit and into the glass box, therefore winning the PoV. At the PoV ceremony on Day 6, Derek X. removed Kyland from the block at Frenchie's request; Frenchie nominated Travis, going back on the deal he made on Day 1. | J200: Wikipedia
A201: BB23 | B201: Week 1 | C201: 787 | D201: 4 | E201: Episode 4 | F201: Days 6–9 | G201: 44392 | H201: 3.81 | I201: Following the PoV ceremony, Frenchie formed multiple alliances, including an eight-person alliance called the "Slaughterhouse", as well as an all-girl alliance called the "French Kisses" with Azah, Claire, Hannah and Tiffany, though they doubted his intentions. The HouseGuests then celebrated Kyland's thirtieth birthday, which included a birthday cake and a striptease from Travis posing as "Travisa". Prior to the eviction, Travis met with Frenchie and Brent to make a last-ditch effort to save himself, though his efforts proved futile as, on Day 9, Travis was the first HouseGuest to be evicted from the Big Brother house by a vote of 11–2; Big D and Tiffany both cast a rogue vote against Alyssa. The remaining HouseGuests then competed in the next HoH competition, "Pool Sharks". Each HouseGuest had to stand at a spot numbered from 1 to 30, with 1 being the easiest spot and 30 being the hardest spot, and attempt to hit a ball into a shark's mouth. Before the competition began, each HouseGuest was required to enter a number into their keypad to claim a spot from 1 to 30. The HouseGuest with the highest number that scored successfully was the winner; Kyland became the second HoH. | J201: Wikipedia
A202: BB23 | B202: Week 2 | C202: 788 | D202: 5 | E202: Episode 5 | F202: Days 9–10 | G202: 44395 | H202: 3.49 | I202: Following Kyland's win, the HouseGuests attempted to figure out the identities of the rogue voters; Tiffany's vote for Alyssa was part of a deal she made with Frenchie so that she could know whether or not to trust him, while Frenchie wanted to frame Derek X. On Day 10, Brent, Frenchie and Sarah Beth were selected to participate in the "BB Flying Colors" Wildcard competition. For this competition, the three competitors were presented with several colorful images, and afterwards were asked a question based on the images, with the answer being a color. The first HouseGuest to reach three points won the competition. Sarah Beth won. After the competition, Sarah Beth was offered immunity as long as she switched teams with one of Kyland's immune teammates, Claire or Tiffany. If she took the offer, the HouseGuest she chose to swap with would no longer be immune. She chose not to take the offer, feeling comfortable in her relationship with Kyland. Prior to the nominations ceremony, several HouseGuests with the exception of Britini expressed a desire for Frenchie to be nominated. Thus, later that evening, Kyland nominated Britini and Frenchie for eviction. | J202: Wikipedia
A203: BB23 | B203: Week 2 | C203: 789 | D203: 6 | E203: Episode 6 | F203: Days 10–13 | G203: 44398 | H203: 3.5 | I203: With two of their teammates on the block, the Jokers (Azah, Britini, Big D and Frenchie) were distraught. Upon learning that the Slaughterhouse had thrown Frenchie under the bus, he spilled details of the alliance to his fellow HouseGuests, telling many of them that Alyssa, Brent, Christian, Kyland and Whitney were all aligned. As a result, a consensus was reached by the majority of the house that, in order to protect their alliances, Frenchie could not win the veto. On Day 11, Alyssa, Claire and Derek X. were randomly selected to participate alongside Kyland, Britini and Frenchie in the "Fun Tan Lotion" PoV competition. The HouseGuests competed separately and were required to fill their containers with suntan oil in order to retrieve a whistle from the container in the fastest time. Derek X. completed the competition in the fastest time (4:41) and therefore won the veto. Although the Jokers attempted to put a plan together in order to ensure that their team would remain intact, Derek X. and Kyland could not trust Frenchie's promises, and Kyland did not want to get unnecessary blood on his hands. On Day 13, Derek X. chose not to use the veto, solidifying Britini and Frenchie as the final nominees. | J203: Wikipedia
A204: BB23 | B204: Week 2 | C204: 790 | D204: 7 | E204: Episode 7 | F204: Days 13–16 | G204: 44399 | H204: 3.87 | I204: With nominations locked in, Frenchie campaigned heavily to stay in the game, while Britini opted to keep a low profile to keep the target solely on Frenchie. Meanwhile, Kyland pulled the Aces (Brent, Derek X., Hannah and Whitney) aside to ask them for safety in return for him keeping them safe this week; though Derek X. was willing to make a promise, Brent and Whitney were hesitant to respond. Eventually, the HouseGuests became wary of Brent and Whitney's position within the game, and the Kings and Queens discussed targeting them the following week provided no teammate from Aces win HoH. On Day 16, Frenchie was evicted by a vote of 11–1, with only Big D voting for him to stay. Following this, HouseGuests competed in the "Tom Talks BB" HoH competition. For this competition, the HouseGuests watched two videos from comedian and second season Celebrity Big Brother HouseGuest Tom Green interviewing members of the public about Big Brother. Afterwards, they were asked true or false questions based on what they saw; if a HouseGuest answered incorrectly, they were eliminated. Xavier was the last HouseGuest standing and became the third HoH of the season. | J204: Wikipedia
A205: BB23 | B205: Week 3 | C205: 791 | D205: 8 | E205: Episode 8 | F205: Days 16–17 | G205: 44402 | H205: 3.31 | I205: Xavier and Tiffany discussed nominating Brent, perceiving him to be a socially strong player. Hannah in particular wanted to target Brent, having thrown the HoH competition along with Derek X. so that he could not receive immunity for the week. A new alliance, "The Royal Flush", formed between the Kings, the Queens and Derek X., with the intentions of voting Brent out this week. On Day 17, Britini, Derek X. and Tiffany competed in the "Unlucky 13" Wildcard competition. They had to take cards one at a time across a balance beam and place them into one of four slots belonging to another competitor. If a competitor's cards totaled thirteen, they were eliminated. After eliminating Britini first, Derek X. threw the competition, and Tiffany was the winner. To receive immunity, she had to participate in a game of chance which would also allocate safety to one member of both the Jokers and the Aces; she declined the offer. Wanting to make Brent feel safe, Xavier told him that he was going up as a pawn, and that Britini was the target, but Azah was unhappy with the plan and opted to take Britini's place on the block. However, not wanting to use his own ally as a pawn, Xavier nominated Brent and Britini for eviction. | J205: Wikipedia
A206: BB23 | B206: Week 3 | C206: 792 | D206: 9 | E206: Episode 9 | F206: Days 17–20 | G206: 44405 | H206: 3.79 | I206: Brent did not believe that he was the pawn, but nevertheless felt as though he had the numbers to stay over Britini. Tiffany and Derek X sabotaging Britini in the Wildcard competition led to a disagreement between Tiffany and Azah, with the two agreeing to disagree, while Hannah was introduced as the unofficial sixth member of The Cookout alliance. On Day 18, Christian (Xavier's choice), Derek F. and Whitney were selected to participate alongside Xavier, Brent and Britini in the "Room Key Rumble" PoV competition. In six one-on-one rounds, the HouseGuests each chose which other HouseGuest they wanted to compete against. They had to spin on a handle to bring down a barrier covering six numbered pins. They then had to knock down three of the pins so that the remaining three corresponded to a specific room number. Christian won the final round against Xavier and was therefore the winner. Brent believed that he was the HouseGuest orchestrating the blindside, suggesting to Christian to not use the veto and send Britini home in what he perceived would be a close vote. On Day 20, Christian chose not to use the veto, but only to solidify the plan to blindside Brent. | J206: Wikipedia
A207: BB23 | B207: Week 3 | C207: 793 | D207: 10 | E207: Episode 10 | F207: Days 20–23 | G207: 44406 | H207: 3.86 | I207: Brent believed that Xavier and Christian made a mistake not using the Veto as he thought he had the votes from an alliance between the Aces and the Queens called "The Mafia". However, the Queens only created the alliance to ensure their safety had Brent won HoH, and they along with the rest of the house planned on blindsiding him at the live eviction. The HouseGuests debated who should win the HoH competition based on who they wanted to target for the upcoming week; several HouseGuests believed Alyssa and Christian to be the most threatening duo at this point in the game. On Day 23, via a unanimous vote of 11–0 Brent was the third houseguest to be evicted. The HouseGuests then competed in the HoH competition called "Pier Pressure". Each team had to assemble a surfboard puzzle one HouseGuest at a time without letting their time clock expire, or else the team would be eliminated. The HouseGuest on the winning team that installed the final piece and buzzed in would be crowned HoH. Since the Kings completed their puzzle first and Christian finished the puzzle and hit the buzzer, he became the fourth HoH of the season. | J207: Wikipedia
... A311: BB21 | B311: Week 13 | C311: 746 | D311: 40 | E311: Episode 40 | F311: Days 93–99 | G311: 43733 | H311: 4.2 | I311: Will Kirby, Big Brother 2 and Big Brother 7 alum, returned to host the Jury Roundtable where the jury discussed who deserved to win Big Brother. Head of Household: Part 2: ("Foggy Memory") HouseGuests had to match pictures to Day numbers. Once they found the number, they had to climb up a wall and place it with the picture. The HouseGuest to correctly fill the wall in the least amount of time won. Holly won with a time of 10:38; therefore, Nicole was automatically nominated. Part 3: ("The Jury is Out") Holly and Michie had to watch a series of videos featuring jury members. The jury members made three statements about their time in the Big Brother House. Then, Holly and Michie had to guess which one was false. If they correctly guessed it, they got a point. The HouseGuest to get the most questions correct won the final part. Michie won with 8 points, automatically nominating Holly alongside Nicole. On Day 99, by Michie's sole vote, Nicole was evicted and became the ninth and final jury member. The jury, then joined by Nicole, questioned Michie and Holly as to why they should win. Chen-Moonves gave the pre-jury a time to talk about different controversies that happened in the House and gave the other HouseGuests a time to say what they wanted to say. The jury, by a vote of 6–3, named Michie the winner of the season. | J311: Wikipedia
